Workbook
Name TGT_MIN: '集計・設定'!$C$4
Name TGT_MAX: '集計・設定'!$C$5

Sheet 集計・設定
A1: 自治体 地域公共交通計画・環境基本計画 終期一覧 集計・設定
A3: ■ 営業対象とする終期（令和年度）
B4: 下限 | C4: 9 | D4: ▼プルダウンで選ぶと全シートの判定（◎）と終期セルの色が切り替わります。例：R10年度に終わる計画も見る→上限を10に／R10だけ見る→下限・上限とも10に。
B5: 上限 | C5: 9 | D5: R8年度で終わる計画は作成中のため対象外（初期値は下限9・上限9）。終期セルの色：緑＝対象年度、橙＝上限の翌年度（次の営業候補）。
A7: ■ 県別の集計
B8: 県 | C8: 市町村数 | D8: ◎ 営業 | E8: △ 着手済・要確認 | F8: ？ 期間要確認 | G8: ✕ 対象外 | H8: 未調査 | I8: 一部のみ調査
B9: 青森県 | C9: =COUNTA('青森県'!$C$4:$C$43) | D9: =COUNTIF('青森県'!$C$4:$C$43,"◎ 営業") | E9: =COUNTIF('青森県'!$C$4:$C$43,"△ 着手済・要確認") | F9: =COUNTIF('青森県'!$C$4:$C$43,"？ 期間要確認") | G9: =COUNTIF('青森県'!$C$4:$C$43,"✕ 対象外") | H9: =COUNTIF('青森県'!$S$4:$S$43,"未調査") | I9: =COUNTIF('青森県'!$S$4:$S$43,"交通のみ調査")+COUNTIF('青森県'!$S$4:$S$43,"環境のみ調査")
B10: 岩手県 | C10: =COUNTA('岩手県'!$C$4:$C$36) | D10: =COUNTIF('岩手県'!$C$4:$C$36,"◎ 営業") | E10: =COUNTIF('岩手県'!$C$4:$C$36,"△ 着手済・要確認") | F10: =COUNTIF('岩手県'!$C$4:$C$36,"？ 期間要確認") | G10: =COUNTIF('岩手県'!$C$4:$C$36,"✕ 対象外") | H10: =COUNTIF('岩手県'!$S$4:$S$36,"未調査") | I10: =COUNTIF('岩手県'!$S$4:$S$36,"交通のみ調査")+COUNTIF('岩手県'!$S$4:$S$36,"環境のみ調査")
B11: 宮城県 | C11: =COUNTA('宮城県'!$C$4:$C$38) | D11: =COUNTIF('宮城県'!$C$4:$C$38,"◎ 営業") | E11: =COUNTIF('宮城県'!$C$4:$C$38,"△ 着手済・要確認") | F11: =COUNTIF('宮城県'!$C$4:$C$38,"？ 期間要確認") | G11: =COUNTIF('宮城県'!$C$4:$C$38,"✕ 対象外") | H11: =COUNTIF('宮城県'!$S$4:$S$38,"未調査") | I11: =COUNTIF('宮城県'!$S$4:$S$38,"交通のみ調査")+COUNTIF('宮城県'!$S$4:$S$38,"環境のみ調査")
B12: 秋田県 | C12: =COUNTA('秋田県'!$C$4:$C$28) | D12: =COUNTIF('秋田県'!$C$4:$C$28,"◎ 営業") | E12: =COUNTIF('秋田県'!$C$4:$C$28,"△ 着手済・要確認") | F12: =COUNTIF('秋田県'!$C$4:$C$28,"？ 期間要確認") | G12: =COUNTIF('秋田県'!$C$4:$C$28,"✕ 対象外") | H12: =COUNTIF('秋田県'!$S$4:$S$28,"未調査") | I12: =COUNTIF('秋田県'!$S$4:$S$28,"交通のみ調査")+COUNTIF('秋田県'!$S$4:$S$28,"環境のみ調査")
B13: 山形県 | C13: =COUNTA('山形県'!$C$4:$C$38) | D13: =COUNTIF('山形県'!$C$4:$C$38,"◎ 営業") | E13: =COUNTIF('山形県'!$C$4:$C$38,"△ 着手済・要確認") | F13: =COUNTIF('山形県'!$C$4:$C$38,"？ 期間要確認") | G13: =COUNTIF('山形県'!$C$4:$C$38,"✕ 対象外") | H13: =COUNTIF('山形県'!$S$4:$S$38,"未調査") | I13: =COUNTIF('山形県'!$S$4:$S$38,"交通のみ調査")+COUNTIF('山形県'!$S$4:$S$38,"環境のみ調査")
B14: 福島県 | C14: =COUNTA('福島県'!$C$4:$C$62) | D14: =COUNTIF('福島県'!$C$4:$C$62,"◎ 営業") | E14: =COUNTIF('福島県'!$C$4:$C$62,"△ 着手済・要確認") | F14: =COUNTIF('福島県'!$C$4:$C$62,"？ 期間要確認") | G14: =COUNTIF('福島県'!$C$4:$C$62,"✕ 対象外") | H14: =COUNTIF('福島県'!$S$4:$S$62,"未調査") | I14: =COUNTIF('福島県'!$S$4:$S$62,"交通のみ調査")+COUNTIF('福島県'!$S$4:$S$62,"環境のみ調査")
B15: 茨城県 | C15: =COUNTA('茨城県'!$C$4:$C$47) | D15: =COUNTIF('茨城県'!$C$4:$C$47,"◎ 営業") | E15: =COUNTIF('茨城県'!$C$4:$C$47,"△ 着手済・要確認") | F15: =COUNTIF('茨城県'!$C$4:$C$47,"？ 期間要確認") | G15: =COUNTIF('茨城県'!$C$4:$C$47,"✕ 対象外") | H15: =COUNTIF('茨城県'!$S$4:$S$47,"未調査") | I15: =COUNTIF('茨城県'!$S$4:$S$47,"交通のみ調査")+COUNTIF('茨城県'!$S$4:$S$47,"環境のみ調査")
B16: 栃木県 | C16: =COUNTA('栃木県'!$C$4:$C$28) | D16: =COUNTIF('栃木県'!$C$4:$C$28,"◎ 営業") | E16: =COUNTIF('栃木県'!$C$4:$C$28,"△ 着手済・要確認") | F16: =COUNTIF('栃木県'!$C$4:$C$28,"？ 期間要確認") | G16: =COUNTIF('栃木県'!$C$4:$C$28,"✕ 対象外") | H16: =COUNTIF('栃木県'!$S$4:$S$28,"未調査") | I16: =COUNTIF('栃木県'!$S$4:$S$28,"交通のみ調査")+COUNTIF('栃木県'!$S$4:$S$28,"環境のみ調査")
B17: 群馬県 | C17: =COUNTA('群馬県'!$C$4:$C$38) | D17: =COUNTIF('群馬県'!$C$4:$C$38,"◎ 営業") | E17: =COUNTIF('群馬県'!$C$4:$C$38,"△ 着手済・要確認") | F17: =COUNTIF('群馬県'!$C$4:$C$38,"？ 期間要確認") | G17: =COUNTIF('群馬県'!$C$4:$C$38,"✕ 対象外") | H17: =COUNTIF('群馬県'!$S$4:$S$38,"未調査") | I17: =COUNTIF('群馬県'!$S$4:$S$38,"交通のみ調査")+COUNTIF('群馬県'!$S$4:$S$38,"環境のみ調査")
B18: 宮崎県 | C18: =COUNTA('宮崎県'!$C$4:$C$29) | D18: =COUNTIF('宮崎県'!$C$4:$C$29,"◎ 営業") | E18: =COUNTIF('宮崎県'!$C$4:$C$29,"△ 着手済・要確認") | F18: =COUNTIF('宮崎県'!$C$4:$C$29,"？ 期間要確認") | G18: =COUNTIF('宮崎県'!$C$4:$C$29,"✕ 対象外") | H18: =COUNTIF('宮崎県'!$S$4:$S$29,"未調査") | I18: =COUNTIF('宮崎県'!$S$4:$S$29,"交通のみ調査")+COUNTIF('宮崎県'!$S$4:$S$29,"環境のみ調査")
B19: 合計 | C19: =SUM(C9:C18) | D19: =SUM(D9:D18) | E19: =SUM(E9:E18) | F19: =SUM(F9:F18) | G19: =SUM(G9:G18) | H19: =SUM(H9:H18) | I19: =SUM(I9:I18)
A21: ■ 判定の見方
A22: ◎ 営業：どちらかの計画の終期が対象年度（初期値R9）で、次の計画の作業は見つかっていない
A23: △ 着手済・要確認：終期は対象年度だが、次期計画の策定業務委託やパブコメをすでに確認済。委託先が決まっている可能性が高い
A24: ？ 期間要確認：終期がわからないため判定できない
A25: ✕ 対象外：終期が対象年度の外（R8以前は作成中または終了、R10以降は先）、または新計画を策定済
A26: －：その計画がない（環境基本計画を作っていない町村など）
A28: ■ 入力する列
A29: 各県シートの「終期(令和年度)」と「改定状況」（未確認／着手済／策定済／計画なし）を直すと、判定が自動で変わります。
A30: 「未確認」は、改定の動きが検索で見つからなかったという意味です。動きがないと確かめたわけではありません。
A31: 確度：確認済＝検索結果の本文に期間が書かれていた／推定＝策定時期などから推測（終期のセルは茶色の斜体）／不明＝確認できなかった
A33: ■ 国交省一覧との照合（T列）
A34: 国土交通省「地域公共交通計画の作成状況一覧」（令和8年5月末時点）と照合。掲載＝計画作成済み、期間満了＝一覧で灰色（計画期間が満了）。一覧には計画期間の記載がないため、終期は各計画書で確認。
... A40: 計画リンクはエビデンスとして検索結果に出たURLを載せています。営業に行く前に、リンク先の計画書で計画期間を確かめてください。特に「推定」「不明」の行は必ず確認してください。

Sheet 青森県
A1: 青森県 地域公共交通計画・環境基本計画の終期一覧（2026年9月30日時点の調査）
A2: ="営業判定の対象：終期 R"&TGT_MIN&"〜R"&TGT_MAX&"年度 →◎（着手済は△、期間不明は？）。終期セルの色：緑＝対象年度／橙＝その翌年度（次の候補）。対象年度は「集計・設定」シートのC4・C5のプルダウンで切替。"
A3: No | B3: 市町村 | C3: 営業判定 | D3: 交通判定 | E3: 環境判定 | F3: 地域公共交通計画 | G3: 交通 計画期間 | H3: 交通 終期(令和年度) | I3: 交通 確度 | J3: 交通 改定状況 | K3: 交通 計画リンク（エビデンス） | L3: 環境基本計画 | M3: 環境 計画期間 | N3: 環境 終期(令和年度) | O3: 環境 確度 | P3: 環境 改定状況 | Q3: 環境 計画リンク（エビデンス） | R3: 注釈（改定作業の状況など） | S3: 調査状況 | T3: 国交省一覧(R8.5末)
A4: 1 | B4: 青森市 | C4: =IF(OR(D4="◎",E4="◎"),"◎ 営業",IF(OR(D4="△",E4="△"),"△ 着手済・要確認",IF(OR(D4="？",E4="？"),"？ 期間要確認","✕ 対象外"))) | D4: =IF(J4="計画なし","－",IF(J4="策定済","✕",IF(H4="","？",IF(AND(H4>=TGT_MIN,H4<=TGT_MAX),IF(J4="着手済","△","◎"),"✕")))) | E4: =IF(P4="計画なし","－",IF(P4="策定済","✕",IF(N4="","？",IF(AND(N4>=TGT_MIN,N4<=TGT_MAX),IF(P4="着手済","△","◎"),"✕")))) | F4: 青森市地域公共交通計画 | G4: R6〜R10 | H4: 10 | I4: 確認済 | J4: 未確認 | K4: https://www.city.aomori.aomori.jp/somu/shiseijouhou/jyouhou-koukai/tyougi/documents/tiikikoutuumoukeikaku.pdf | L4: 青森市環境基本計画（令和7年12月制定の青森市環境基本条例第8条に基づき策定中） | M4: R8〜R10 | N4: 10 | O4: 確認済 | P4: 着手済 | Q4: https://www.city.aomori.aomori.jp/_res/projects/default_project/_page_/001/011/090/05_080722siryou3.pdf | R4: 環境基本計画は新条例（R7.12）に基づく新規策定中。R8.7.22環境審議会資料によるとR8.10素案審議→R8.12パブコメ→R9.2計画案審議→策定予定（期間は総合計画前期基本計画終期に合わせR10まで）。関連: https://www.city.aomori.aomori.jp/_res/projects/default_project/_page_/001/009/192/080220anken1.pdf 。交通計画URLは市の審議会資料PDF（計画本体ページは未確認）。 | S4: 調査済 | T4: 掲載
A5: 2 | B5: 弘前市 | C5: =IF(OR(D5="◎",E5="◎"),"◎ 営業",IF(OR(D5="△",E5="△"),"△ 着手済・要確認",IF(OR(D5="？",E5="？"),"？ 期間要確認","✕ 対象外"))) | D5: =IF(J5="計画なし","－",IF(J5="策定済","✕",IF(H5="","？",IF(AND(H5>=TGT_MIN,H5<=TGT_MAX),IF(J5="着手済","△","◎"),"✕")))) | E5: =IF(P5="計画なし","－",IF(P5="策定済","✕",IF(N5="","？",IF(AND(N5>=TGT_MIN,N5<=TGT_MAX),IF(P5="着手済","△","◎"),"✕")))) | F5: 弘前市地域公共交通計画 | G5: R6〜R10 | H5: 10 | I5: 確認済 | J5: 未確認 | K5: https://www.city.hirosaki.aomori.jp/jouhou/keikaku/kokyokotu/kotsukeikaku.pdf | L5: 第3次弘前市環境基本計画 | M5: R3〜R12 | N5: 12 | O5: 推定 | P5: 未確認 | Q5: https://www.city.hirosaki.aomori.jp/jouhou/keikaku/2021-0401-kankyoukihon.html | R5: 環境：R3.3策定（改訂）の記載は資料編 https://city.hirosaki.aomori.jp/jouhou/keikaku/files/shiryouhen.pdf で示唆されるが、期間は今回の検索でも確認できず推定のまま。 | S5: 調査済 | T5: 掲載
A6: 3 | B6: 八戸市 | C6: =IF(OR(D6="◎",E6="◎"),"◎ 営業",IF(OR(D6="△",E6="△"),"△ 着手済・要確認",IF(OR(D6="？",E6="？"),"？ 期間要確認","✕ 対象外"))) | D6: =IF(J6="計画なし","－",IF(J6="策定済","✕",IF(H6="","？",IF(AND(H6>=TGT_MIN,H6<=TGT_MAX),IF(J6="着手済","△","◎"),"✕")))) | E6: =IF(P6="計画なし","－",IF(P6="策定済","✕",IF(N6="","？",IF(AND(N6>=TGT_MIN,N6<=TGT_MAX),IF(P6="着手済","△","◎"),"✕")))) | F6: 八戸圏域地域公共交通計画（広域） | G6: R5〜R10 | H6: 10 | I6: 確認済 | J6: 未確認 | K6: https://wwwtb.mlit.go.jp/tohoku/content/000181287.pdf | L6: 第3次八戸市環境基本計画 | M6: R5〜R14 | N6: 14 | O6: 推定 | P6: 未確認 | Q6: https://www.city.hachinohe.aomori.jp/gyoseijoho/keikaku_plan/kurashi_tetsuzuki/1/1/7959.html | R6: 環境：今回の検索でも期間確認できず推定のまま。関連：第2次八戸市地球温暖化対策実行計画区域施策編 https://www.city.hachinohe.aomori.jp/gyoseijoho/keikaku_plan/kurashi_tetsuzuki/1/1/7961.html 。 | S6: 調査済 | T6: 掲載（広域：八戸圏域）／期間満了
A7: 4 | B7: 黒石市 | C7: =IF(OR(D7="◎",E7="◎"),"◎ 営業",IF(OR(D7="△",E7="△"),"△ 着手済・要確認",IF(OR(D7="？",E7="？"),"？ 期間要確認","✕ 対象外"))) | D7: =IF(J7="計画なし","－",IF(J7="策定済","✕",IF(H7="","？",IF(AND(H7>=TGT_MIN,H7<=TGT_MAX),IF(J7="着手済","△","◎"),"✕")))) | E7: =IF(P7="計画なし","－",IF(P7="策定済","✕",IF(N7="","？",IF(AND(N7>=TGT_MIN,N7<=TGT_MAX),IF(P7="着手済","△","◎"),"✕")))) | F7: 黒石市地域公共交通計画 | G7: R7〜R11 | H7: 11 | I7: 確認済 | J7: 策定済 | K7: http://www.city.kuroishi.aomori.jp/shisei/keikaku/2025-0523-1102-33.html | L7: 第二次黒石市環境基本計画 | M7: 不明 | O7: 不明 | P7: 未確認 | Q7: http://www.city.kuroishi.aomori.jp/shisei/keikaku/kankyou-kihon-keikaku.html | R7: 交通：R7.3策定、R7〜R11の5年間。R1.10策定の地域公共交通網形成計画を継承。策定支援業務委託はR6.5公告（NJSS https://www2.njss.info/offers/view/29276332）。環境：第二次計画のページは確認したが計画期間は検索結果で確認できず（要確認）。 【追加調査 2026-10】環境：一般検索・市サイト限定検索（計4回）とも第二次黒石市環境基本計画のページ（http://www.city.kuroishi.aomori.jp/shisei/keikaku/kankyou-kihon-keikaku.html）は出るが計画期間の記載は検索結果に出ず。検索要約に『第3次黒石市環境基本計画』が掲載されている旨の言及が2回あったが、完全一致検索ではヒットせず未確認（同ページに第3次が追加された可能性あり、要確認）。R2.3頃のパブコメページ http://www.city.kuroishi.aomori.jp/shisei/comments/2020-0327-2054-15.html あり（内容未確認）。市サイトはWebFetchブロック。確認日2026-10-02。 | S7: 調査済 | T7: 掲載
A8: 5 | B8: 五所川原市 | C8: =IF(OR(D8="◎",E8="◎"),"◎ 営業",IF(OR(D8="△",E8="△"),"△ 着手済・要確認",IF(OR(D8="？",E8="？"),"？ 期間要確認","✕ 対象外"))) | D8: =IF(J8="計画なし","－",IF(J8="策定済","✕",IF(H8="","？",IF(AND(H8>=TGT_MIN,H8<=TGT_MAX),IF(J8="着手済","△","◎"),"✕")))) | E8: =IF(P8="計画なし","－",IF(P8="策定済","✕",IF(N8="","？",IF(AND(N8>=TGT_MIN,N8<=TGT_MAX),IF(P8="着手済","△","◎"),"✕")))) | F8: 五所川原市地域公共交通計画 | G8: R5〜R10 | H8: 10 | I8: 確認済 | J8: 未確認 | K8: https://www.city.goshogawara.lg.jp/kurashi/machi/chiikikoukyokoutsukeikaku.html | M8: 不明 | O8: 不明 | P8: 未確認 | R8: 交通：R5.6策定（パブコメR5.4.17〜5.16）。期間は検索結果で未確認のため5年と仮定した推定値（要確認）。R6.3に五所川原市地域公共交通推進計画（R6〜R10、確認済 https://www.city.goshogawara.lg.jp/jouhou/keikaku/files/koutuu_suisin.pdf）。H28.3網形成計画・H30.3再編実施計画あり。環境：環境基本計画は検索で見当たらず。代替として五所川原市地球温暖化対策実行計画（区域施策編）が存在する模様（https://www.city.goshogawara.lg.jp/kurashi/kurashi/files/planR2_gaiyouban.pdf の可能性）。事務事業編相当は環境保全率先行動計画（H21〜H25）。 【ファクトチェック 2026-10-01: 誤り】確認期間: R5〜R10（令和5年6月策定、令和10年度までの取組を定める）／次期: 確認できず（次期計画の策定支援業務・パブコメは見当たらず。概要版が gaiyouR7.1/R7.6/R8.1 と更新されており、R8.1時点で計画の変更あり）／根拠: https://www.city.goshogawara.lg.jp/kurashi/machi/files/suishinnkeikaku-gaiyou.ver.pdf 【追加調査 2026-10】環境：市サイト限定検索・完全一致検索とも『五所川原市環境基本計画』『環境基本条例』は見当たらず。環境関連は一般廃棄物処理基本計画（R3〜R12, https://www.city.goshogawara.lg.jp/kurashi/kurashi/files/pianR2.pdf）、生活排水基本計画、環境保全率先行動計画、ゼロカーボンシティ宣言のみヒット。計画なしの明示的根拠はないため未確認のまま。確認日2026-10-02。 | S8: 交通のみ調査 | T8: 掲載
A9: 6 | B9: 十和田市 | C9: =IF(OR(D9="◎",E9="◎"),"◎ 営業",IF(OR(D9="△",E9="△"),"△ 着手済・要確認",IF(OR(D9="？",E9="？"),"？ 期間要確認","✕ 対象外"))) | D9: =IF(J9="計画なし","－",IF(J9="策定済","✕",IF(H9="","？",IF(AND(H9>=TGT_MIN,H9<=TGT_MAX),IF(J9="着手済","△","◎"),"✕")))) | E9: =IF(P9="計画なし","－",IF(P9="策定済","✕",IF(N9="","？",IF(AND(N9>=TGT_MIN,N9<=TGT_MAX),IF(P9="着手済","△","◎"),"✕")))) | F9: 十和田市地域公共交通計画 | G9: R5〜R9 | H9: 9 | I9: 確認済 | J9: 未確認 | K9: https://www.city.towada.lg.jp/kurashi/koutsu/files/keikaku.pdf | M9: 不明 | O9: 不明 | P9: 計画なし | R9: 交通：計画期間R5〜R9（5か年、検索結果で確認）。概要版 https://www.city.towada.lg.jp/kurashi/koutsu/files/gaiyouban.pdf 。策定支援業務仕様書 https://www.city.towada.lg.jp/kurashi/koutsu/files/shiyousyo.pdf あり（日付不明、現行計画策定時のものの可能性が高い。次期計画分かは要確認）。R9終了のため次期計画はR8〜R9に着手見込み。環境：環境基本計画は検索で見当たらず。R7.3に十和田市地球温暖化対策実行計画（区域施策編）策定（https://www.city.towada.lg.jp/shisei/gyousei/machidukuri/files/keikakugaiyouban.pdf）。 【ファクトチェック 2026-10-01: 正しい】確認期間: R5〜R9（2023〜2027年度）／次期: 確認できず（市サイト内検索で次期計画の策定支援プロポーザル・協議会審議は見当たらず。前回はR4年度にプロポーザル https://www.city.towada.lg.jp/kurashi/koutsuu/koutsuukeikaku.ht／根拠: https://www.city.towada.lg.jp/kurashi/koutsuu/files/keikaku.pdf 【追加調査 2026-10】環境：市サイト限定検索で環境基本計画は見当たらず。十和田市地球温暖化対策実行計画（区域施策編）案（2025/1/16版、計画期間2025〜2030年度 https://www.city.towada.lg.jp/shisei/gyousei/machidukuri/files/kuikisesakuhenan.pdf）の整合・連携先として第2次総合計画・都市計画MP・森林整備計画・国土強靭化計画・地域公共交通計画等が列挙されるが環境基本計画は挙がっておらず、環境分野の総合計画は区域施策編＋事務事業編（とわだエコ・オフィスプラン）で代替とみられる。確認日2026-10-02。 | S9: 調査済 | T9: 掲載
A10: 7 | B10: 三沢市 | C10: =IF(OR(D10="◎",E10="◎"),"◎ 営業",IF(OR(D10="△",E10="△"),"△ 着手済・要確認",IF(OR(D10="？",E10="？"),"？ 期間要確認","✕ 対象外"))) | D10: =IF(J10="計画なし","－",IF(J10="策定済","✕",IF(H10="","？",IF(AND(H10>=TGT_MIN,H10<=TGT_MAX),IF(J10="着手済","△","◎"),"✕")))) | E10: =IF(P10="計画なし","－",IF(P10="策定済","✕",IF(N10="","？",IF(AND(N10>=TGT_MIN,N10<=TGT_MAX),IF(P10="着手済","△","◎"),"✕")))) | F10: 三沢市地域公共交通計画 | G10: 不明 | I10: 不明 | J10: 未確認 | K10: https://www.city.misawa.lg.jp/index.cfm/12,21981,57,254,html | L10: 第2次三沢市環境基本計画 | M10: H31〜R10 | N10: 10 | O10: 確認済 | P10: 未確認 | Q10: https://www.city.misawa.lg.jp/index.cfm/12,31881,c,html/31881/20181207-151357.pdf | R10: 交通：H28.3策定の地域公共交通網形成計画を継承して地域公共交通計画を策定（策定時期・期間は検索で確認できず）。素案ページ https://www.city.misawa.lg.jp/index.cfm/12,47680,79,350,html 。環境：第2次計画（素案表紙に2019.4〜2029.3と明記）。URLは素案PDF。 | S10: 調査済 | T10: 掲載
A11: 8 | B11: むつ市 | C11: =IF(OR(D11="◎",E11="◎"),"◎ 営業",IF(OR(D11="△",E11="△"),"△ 着手済・要確認",IF(OR(D11="？",E11="？"),"？ 期間要確認","✕ 対象外"))) | D11: =IF(J11="計画なし","－",IF(J11="策定済","✕",IF(H11="","？",IF(AND(H11>=TGT_MIN,H11<=TGT_MAX),IF(J11="着手済","△","◎"),"✕")))) | E11: =IF(P11="計画なし","－",IF(P11="策定済","✕",IF(N11="","？",IF(AND(N11>=TGT_MIN,N11<=TGT_MAX),IF(P11="着手済","△","◎"),"✕")))) | F11: 下北地域公共交通計画（広域） | G11: R7〜R11 | H11: 11 | I11: 確認済 | J11: 策定済 | K11: https://www.city.mutsu.lg.jp/government/katsudou/kyoudou/files/simokitatiikikoukyoukoutuukeikakusoann.pdf | M11: 不明 | O11: 不明 | P11: 未確認 | R11: 交通：下北地域公共交通総合連携協議会（むつ市・大間町・東通村・風間浦村・佐井村）がR7.3策定、2025〜2029。URLは素案PDF（パブコメR7.2.17〜3.3）。前計画はH30.3の下北地域公共交通網形成計画。市単独ではむつ市公共交通再編関連資料（2026）https://www.city.mutsu.lg.jp/kurashi/koutsu/koutsu_sisaku/files/mutsu_kokyokotsusaihen_2026.pdf あり（地域公共交通計画ではなく再編計画の可能性）。環境：環境基本計画は検索で見当たらず。第4期むつ市地球温暖化対策推進実行計画（事務事業編）R7.6策定（https://www.city.mutsu.lg.jp/kurashi/kankyo/kankyo/files/ondankakeikaku4.pdf）。 【追加調査 2026-10】環境：市サイト限定検索・完全一致検索（『むつ市環境基本計画』『むつ市環境基本条例』）とも該当なし。生活環境ページ https://www.city.mutsu.lg.jp/kurashi/kankyo/kankyo/ には地球温暖化対策推進実行計画・緑の基本計画等のみ。計画なしの明示的根拠はないため未確認のまま。確認日2026-10-02。 | S11: 交通のみ調査 | T11: 掲載（広域：下北地域）
A12: 9 | B12: つがる市 | C12: =IF(OR(D12="◎",E12="◎"),"◎ 営業",IF(OR(D12="△",E12="△"),"△ 着手済・要確認",IF(OR(D12="？",E12="？"),"？ 期間要確認","✕ 対象外"))) | D12: =IF(J12="計画なし","－",IF(J12="策定済","✕",IF(H12="","？",IF(AND(H12>=TGT_MIN,H12<=TGT_MAX),IF(J12="着手済","△","◎"),"✕")))) | E12: =IF(P12="計画なし","－",IF(P12="策定済","✕",IF(N12="","？",IF(AND(N12>=TGT_MIN,N12<=TGT_MAX),IF(P12="着手済","△","◎"),"✕")))) | G12: 不明 | I12: 不明 | J12: 未確認 | L12: 第2次つがる市環境基本計画 | M12: 不明 | O12: 不明 | P12: 未確認 | Q12: https://www.city.tsugaru.aomori.jp/soshiki/minsei/shimin/kankyoeisei/gomi/kankyoukihonkeikaku/10184.html | R12: 交通：地域公共交通計画は検索で確認できず。つがる市地域公共交通会議（H20.9設置）https://www.city.tsugaru.aomori.jp/soshiki/somu/tiikisousei/kikakusinnkou/kokyokotu/6434.html 。環境：第2次計画のページは確認、期間不明。区域施策編は西つがる3市町（つがる市・鰺ヶ沢町・深浦町）共同で策定（R6.3パブコメ https://www.town.fukaura.lg.jp/fixed_docs/2024032100017/）。 【追加調査 2026-10】環境：市サイト限定検索で『つがる市環境基本計画』一覧 https://www.city.tsugaru.aomori.jp/soshiki/minsei/shimin/kankyoeisei/gomi/kankyoukihonkeikaku/index.html と第2次計画ページ（10184.html、PDF約10MB公開、つがる市環境基本条例に基づく計画）を確認。計画期間・策定年は検索結果で確認できず（計4回検索）。市サイトはWebFetchブロック。確認日2026-10-02。 | S12: 環境のみ調査 | T12: 未掲載
A13: 10 | B13: 平川市 | C13: =IF(OR(D13="◎",E13="◎"),"◎ 営業",IF(OR(D13="△",E13="△"),"△ 着手済・要確認",IF(OR(D13="？",E13="？"),"？ 期間要確認","✕ 対象外"))) | D13: =IF(J13="計画なし","－",IF(J13="策定済","✕",IF(H13="","？",IF(AND(H13>=TGT_MIN,H13<=TGT_MAX),IF(J13="着手済","△","◎"),"✕")))) | E13: =IF(P13="計画なし","－",IF(P13="策定済","✕",IF(N13="","？",IF(AND(N13>=TGT_MIN,N13<=TGT_MAX),IF(P13="着手済","△","◎"),"✕")))) | F13: 平川市地域公共交通計画 | G13: 不明 | I13: 不明 | J13: 未確認 | K13: https://www.city.hirakawa.lg.jp/kurashi/keikaku/2021-0514-1007-25.html | L13: 平川市環境基本計画 | M13: H29〜R8 | N13: 8 | O13: 確認済 | P13: 未確認 | Q13: https://www.city.hirakawa.lg.jp/kurashi/keikaku/kankyokihonkeikaku.html | R13: 交通：R3（素案R3.3）策定、R4新庁舎開庁に合わせた再編のマスタープラン。期間は検索で確認できず（5年ならR3〜R7で既に終期到来の可能性、要確認）。策定業務プロポーザルページ https://www.city.hirakawa.lg.jp/shigoto/keiyaku/proposal/koukyoukoutsukeikaku_proposal.html（現行計画分か次期分か不明）。弘前圏域地域公共交通計画にも参加 https://www.city.hirakawa.lg.jp/kurashi/keikaku/hirosakikenikikoutsuukeikaku.html 。環境：H29〜R8の10年間でR8年度（今年度）終了。次期計画の策定業務公募等は検索で見つからず（要注視・有望）。 | S13: 調査済 | T13: 掲載
A14: 11 | B14: 平内町 | C14: =IF(OR(D14="◎",E14="◎"),"◎ 営業",IF(OR(D14="△",E14="△"),"△ 着手済・要確認",IF(OR(D14="？",E14="？"),"？ 期間要確認","✕ 対象外"))) | D14: =IF(J14="計画なし","－",IF(J14="策定済","✕",IF(H14="","？",IF(AND(H14>=TGT_MIN,H14<=TGT_MAX),IF(J14="着手済","△","◎"),"✕")))) | E14: =IF(P14="計画なし","－",IF(P14="策定済","✕",IF(N14="","？",IF(AND(N14>=TGT_MIN,N14<=TGT_MAX),IF(P14="着手済","△","◎"),"✕")))) | F14: 平内町地域公共交通計画 | G14: R4〜R8 | H14: 8 | I14: 推定 | J14: 未確認 | K14: https://www.town.hiranai.aomori.jp/chosei/machizukuri/3/1241.html | M14: 不明 | O14: 不明 | P14: 計画なし | R14: 交通：町HPに計画掲載、令和3年度策定と検索結果に記載（期間は未確認、5年計画と仮定しR4〜R8推定）。R8終了なら次期改定の動きに注意。環境基本計画は町/村名検索・公式サイト内検索で見当たらず（計画なしの確証はないため未確認）。 【追加調査 2026-10】環境：町サイト限定検索（town.hiranai.aomori.jp）で環境基本計画は見当たらず。町民課所管の環境関連計画として出るのは平内町地球温暖化対策実行計画（事務事業編、R2.3策定、R2〜R6）https://www.town.hiranai.aomori.jp/soshiki/chomin/1/3/1/chikyuondankataisaku01.html 、一般廃棄物処理基本計画、災害廃棄物処理計画のみ。環境分野は第六次平内町長期振興計画 https://www.town.hiranai.aomori.jp/soshiki/kikaku/1/1/2/414.html の分野別計画で扱う。町の計画一覧（まちづくり・計画 https://www.town.hiranai.aomori.jp/chosei/machizukuri/index.html ）にも無く計画なしと判断（明示的な記載ではない点に留意）。確認日2026-10-02。 | S14: 調査済 | T14: 掲載
A15: 12 | B15: 今別町 | C15: =IF(OR(D15="◎",E15="◎"),"◎ 営業",IF(OR(D15="△",E15="△"),"△ 着手済・要確認",IF(OR(D15="？",E15="？"),"？ 期間要確認","✕ 対象外"))) | D15: =IF(J15="計画なし","－",IF(J15="策定済","✕",IF(H15="","？",IF(AND(H15>=TGT_MIN,H15<=TGT_MAX),IF(J15="着手済","△","◎"),"✕")))) | E15: =IF(P15="計画なし","－",IF(P15="策定済","✕",IF(N15="","？",IF(AND(N15>=TGT_MIN,N15<=TGT_MAX),IF(P15="着手済","△","◎"),"✕")))) | F15: 今別町地域公共交通計画 | G15: R5〜R9 | H15: 9 | I15: 確認済 | J15: 未確認 | K15: https://www.town.imabetsu.lg.jp/gyousei/koukai/2023-0828-1639-1.html | M15: 不明 | O15: 不明 | P15: 未確認 | R15: 交通：策定支援業務プロポーザル2022-10（https://www.town.imabetsu.lg.jp/news/gyousei/2022-1017-1745-1.html）、計画公表ページ2023-08-28。期間は検索結果で未確認（R5〜R9推定）。JR津軽線蟹田〜三厩は2027年4月廃止・バス/乗合タクシー転換予定（NPO今別外ヶ浜交通）で計画見直しの可能性あり。環境基本計画は町/村名検索・公式サイト内検索で見当たらず（計画なしの確証はないため未確認）。 【ファクトチェック 2026-10-01: 正しい】確認期間: R5〜R9（5年間）／次期: 確認できず（次期計画の策定業務・アンケートは見当たらず。ただしJR津軽線蟹田以北について、代行バス・わんタク・町営バス等を統合した自動車交通を令和9年4月1日から運行予定（広報今別733号 https://www.town.imabetsu／根拠: https://www.town.imabetsu.lg.jp/gyousei/koukai/2023-0828-1639-1.html 【追加調査 2026-10】環境：町サイト限定検索（town.imabetsu.lg.jp）で『環境基本計画』『地球温暖化対策実行計画』とも該当なし。町の施策一覧 https://www.town.imabetsu.lg.jp/gyousei/shisaku/ には総合計画（第6次、R7〜R16 https://www.town.imabetsu.lg.jp/gyousei/shisaku/files/No.6_sougou.pdf ）・総合戦略・地域公共交通計画等のみで、脱炭素は総合計画内で言及。計画なしの可能性大だが明示根拠に乏しく未確認のまま。確認日2026-10-02。 | S15: 交通のみ調査 | T15: 掲載
A16: 13 | B16: 蓬田村 | C16: =IF(OR(D16="◎",E16="◎"),"◎ 営業",IF(OR(D16="△",E16="△"),"△ 着手済・要確認",IF(OR(D16="？",E16="？"),"？ 期間要確認","✕ 対象外"))) | D16: =IF(J16="計画なし","－",IF(J16="策定済","✕",IF(H16="","？",IF(AND(H16>=TGT_MIN,H16<=TGT_MAX),IF(J16="着手済","△","◎"),"✕")))) | E16: =IF(P16="計画なし","－",IF(P16="策定済","✕",IF(N16="","？",IF(AND(N16>=TGT_MIN,N16<=TGT_MAX),IF(P16="着手済","△","◎"),"✕")))) | G16: 不明 | I16: 不明 | J16: 未確認 | M16: 不明 | O16: 不明 | P16: 未確認 | R16: 交通：村名検索・村HP内検索で地域公共交通計画は見当たらず（公共交通ページ https://www.vill.yomogita.lg.jp/kurashi/kotsu/ のみ）。青森市計画は市単独。なお青森県地域公共交通計画（R5〜R9、県全域）は県計画として全市町村を対象。環境基本計画は町/村名検索・公式サイト内検索で見当たらず（計画なしの確証はないため未確認）。 【追加調査 2026-10】環境：村サイト限定検索（vill.yomogita.lg.jp）で環境基本計画は見当たらず。計画ページ https://www.vill.yomogita.lg.jp/sonsei/keikaku/ には過疎計画（R3〜R7）・青森圏域国土強靱化地域計画等。検索要約で『蓬田村地球温暖化対策推進実行計画』の存在が示唆されたがURL未確認。計画なしの確証はなく未確認のまま。確認日2026-10-02。 | S16: 未調査 | T16: 未掲載
A17: 14 | B17: 外ヶ浜町 | C17: =IF(OR(D17="◎",E17="◎"),"◎ 営業",IF(OR(D17="△",E17="△"),"△ 着手済・要確認",IF(OR(D17="？",E17="？"),"？ 期間要確認","✕ 対象外"))) | D17: =IF(J17="計画なし","－",IF(J17="策定済","✕",IF(H17="","？",IF(AND(H17>=TGT_MIN,H17<=TGT_MAX),IF(J17="着手済","△","◎"),"✕")))) | E17: =IF(P17="計画なし","－",IF(P17="策定済","✕",IF(N17="","？",IF(AND(N17>=TGT_MIN,N17<=TGT_MAX),IF(P17="着手済","△","◎"),"✕")))) | F17: 外ヶ浜町地域公共交通計画 | G17: R6〜R10 | H17: 10 | I17: 推定 | J17: 未確認 | K17: https://www.town.sotogahama.lg.jp/gyosei/public/2024-0227-tiikikoukyokoutukeikaku_pabukome.html | M17: 不明 | O17: 不明 | P17: 計画なし | R17: 交通計画は2024年2月27日パブコメ実施（URLは同パブコメページ、期間は5年と推定）。JR津軽線蟹田〜三厩の代行・転換が絡む。環境基本計画は確認できず（今回検索でも見当たらず）、代替として地球温暖化対策実行計画（区域施策編）令和8年3月策定: https://www.town.sotogahama.lg.jp/gyosei/keikaku/files/01_soto_kuikisesaku_plan.pdf 環境基本計画は検索で確認できず（計画なしの確証なし）。 【追加調査 2026-10】環境：町サイト限定検索で環境基本計画は見当たらず。各種計画ページ https://www.town.sotogahama.lg.jp/gyosei/keikaku/ の環境系は外ヶ浜町地球温暖化対策実行計画（区域施策編、2026-03-24策定）https://www.town.sotogahama.lg.jp/gyosei/keikaku/files/01_soto_kuikisesaku_plan.pdf と事務事業編（2020.3）https://www.town.sotogahama.lg.jp/kurashi/kankyo/2021-1022-ontaiho.html 、一般廃棄物処理基本計画のみ。2023.9ゼロカーボンシティ宣言。区域施策編のみで環境基本計画なしと判断。確認日2026-10-02。 | S17: 調査済 | T17: 掲載
A18: 15 | B18: 鰺ヶ沢町 | C18: =IF(OR(D18="◎",E18="◎"),"◎ 営業",IF(OR(D18="△",E18="△"),"△ 着手済・要確認",IF(OR(D18="？",E18="？"),"？ 期間要確認","✕ 対象外"))) | D18: =IF(J18="計画なし","－",IF(J18="策定済","✕",IF(H18="","？",IF(AND(H18>=TGT_MIN,H18<=TGT_MAX),IF(J18="着手済","△","◎"),"✕")))) | E18: =IF(P18="計画なし","－",IF(P18="策定済","✕",IF(N18="","？",IF(AND(N18>=TGT_MIN,N18<=TGT_MAX),IF(P18="着手済","△","◎"),"✕")))) | F18: 鰺ヶ沢町地域公共交通計画 | G18: R6〜R10 | H18: 10 | I18: 推定 | J18: 未確認 | K18: http://www.town.ajigasawa.lg.jp/gyosei_jyoho/kotsu/kokyokotukeikaku.html | M18: 不明 | O18: 不明 | P18: 計画なし | R18: 交通：旧メモ「単独計画は確認できず」は誤り。町HPで2024年3月策定を確認（パブコメ http://www.town.ajigasawa.lg.jp/gyosei_jyoho/publiccomment/kokyokotukeikaku.html）。期間は未確認で5年と仮定しR6〜R10推定。五所川原圏域定住自立圏構成町。環境基本計画は町/村名検索・公式サイト内検索で見当たらず（計画なしの確証はないため未確認）。 【追加調査 2026-10】環境：『鰺ヶ沢町 環境基本計画』検索・町サイト限定検索（環境基本計画/環境計画/環境基本条例）とも環境基本計画は見当たらず。環境分野は西つがる3市町（五所川原市・鰺ヶ沢町・深浦町）共同の地球温暖化対策実行計画（区域施策編） http://www.town.ajigasawa.lg.jp/gyosei_jyoho/keikaku/kikakusinkou240516.html と再生可能エネルギー導入計画 https://www.town.ajigasawa.lg.jp/gyosei_jyoho/keikaku/seisakusaiene.html のみ（区域施策編のみ）。町計画一覧 https://www.town.ajigasawa.lg.jp/gyosei_jyoho/keikaku/index.html はWebFetchブロックで目視不可。確認日2026-10-02 | S18: 調査済 | T18: 掲載
A19: 16 | B19: 深浦町 | C19: =IF(OR(D19="◎",E19="◎"),"◎ 営業",IF(OR(D19="△",E19="△"),"△ 着手済・要確認",IF(OR(D19="？",E19="？"),"？ 期間要確認","✕ 対象外"))) | D19: =IF(J19="計画なし","－",IF(J19="策定済","✕",IF(H19="","？",IF(AND(H19>=TGT_MIN,H19<=TGT_MAX),IF(J19="着手済","△","◎"),"✕")))) | E19: =IF(P19="計画なし","－",IF(P19="策定済","✕",IF(N19="","？",IF(AND(N19>=TGT_MIN,N19<=TGT_MAX),IF(P19="着手済","△","◎"),"✕")))) | F19: 深浦町地域公共交通計画 | G19: R6〜R10 | H19: 10 | I19: 推定 | J19: 未確認 | K19: https://www.town.fukaura.lg.jp/doc/2020031800019/file_contents/2020031800019_fixed_docs_2020031800019_file_contents_kotsukeikaku.pdf | M19: 不明 | O19: 不明 | P19: 計画なし | R19: 交通：計画書表紙「令和6年4月」。前計画は深浦町地域公共交通網形成計画（2020年3月策定）。期間は未確認で5年と仮定しR6〜R10推定。環境基本計画は町/村名検索・公式サイト内検索で見当たらず（計画なしの確証はないため未確認）。 【追加調査 2026-10】環境：町名検索・町サイト限定検索で環境基本計画は見当たらず。環境系は西つがる3市町地球温暖化対策実行計画［区域施策編］ https://www.town.fukaura.lg.jp/fixed_docs/2024032100017/ 、西つがる3市町再エネ導入計画 https://www.town.fukaura.lg.jp/fixed_docs/2024052000038/ 、循環型社会形成推進地域計画のみ（区域施策編のみ）。確認日2026-10-02 | S19: 調査済 | T19: 掲載
A20: 17 | B20: 西目屋村 | C20: =IF(OR(D20="◎",E20="◎"),"◎ 営業",IF(OR(D20="△",E20="△"),"△ 着手済・要確認",IF(OR(D20="？",E20="？"),"？ 期間要確認","✕ 対象外"))) | D20: =IF(J20="計画なし","－",IF(J20="策定済","✕",IF(H20="","？",IF(AND(H20>=TGT_MIN,H20<=TGT_MAX),IF(J20="着手済","△","◎"),"✕")))) | E20: =IF(P20="計画なし","－",IF(P20="策定済","✕",IF(N20="","？",IF(AND(N20>=TGT_MIN,N20<=TGT_MAX),IF(P20="着手済","△","◎"),"✕")))) | G20: 不明 | I20: 不明 | J20: 未確認 | M20: 不明 | O20: 不明 | P20: 計画なし | R20: 交通：村HP内検索で地域公共交通計画は見当たらず（コミュニティバスのみ https://www.nishimeya.jp/kurashi_tetsuzuki/kokyokotsu/300.html）。弘前市地域公共交通計画（R6.3）は市単独とみられる。なお青森県地域公共交通計画（R5〜R9、県全域）は県計画として全市町村を対象。環境：村HP内検索で環境基本計画は見当たらず（再生可能エネルギー振興策 https://www.nishimeya.jp/sonseijoho/seisaku_keikaku/5/7/228.html、災害廃棄物処理計画R8.1はあり）。計画なしの可能性が高いが確証なく未確認。 【追加調査 2026-10】環境：村名検索・村サイト限定検索で環境基本計画は見当たらず。西目屋村地球温暖化対策実行計画（区域施策編、2024年3月策定） https://www.nishimeya.jp/sonseijoho/gyozaisei/872.html 、バイオマス活用推進計画、再エネ振興策のみ（区域施策編のみ）。確認日2026-10-02 | S20: 環境のみ調査 | T20: 未掲載
A21: 18 | B21: 藤崎町 | C21: =IF(OR(D21="◎",E21="◎"),"◎ 営業",IF(OR(D21="△",E21="△"),"△ 着手済・要確認",IF(OR(D21="？",E21="？"),"？ 期間要確認","✕ 対象外"))) | D21: =IF(J21="計画なし","－",IF(J21="策定済","✕",IF(H21="","？",IF(AND(H21>=TGT_MIN,H21<=TGT_MAX),IF(J21="着手済","△","◎"),"✕")))) | E21: =IF(P21="計画なし","－",IF(P21="策定済","✕",IF(N21="","？",IF(AND(N21>=TGT_MIN,N21<=TGT_MAX),IF(P21="着手済","△","◎"),"✕")))) | G21: 不明 | I21: 不明 | J21: 未確認 | M21: 不明 | O21: 不明 | P21: 計画なし | R21: 交通：町名検索・町HP内検索で地域公共交通計画は見当たらず（都市計画マスタープラン・総合計画のみ）。弘前圏域8市町村の弘南鉄道維持活性化基本方針（2020）あり。なお青森県地域公共交通計画（R5〜R9、県全域）は県計画として全市町村を対象。環境基本計画は町/村名検索・公式サイト内検索で見当たらず（計画なしの確証はないため未確認）。 【追加調査 2026-10】環境：町名検索・町サイト限定検索で環境基本計画は見当たらず。藤崎町地球温暖化対策実行計画（R7策定、計画期間R8〜R12、2030年度52%削減・検索要約による） https://www.town.fujisaki.lg.jp/index.cfm/7,23198,24,339,html のみ（区域施策編のみ）。確認日2026-10-02 | S21: 環境のみ調査 | T21: 未掲載
A22: 19 | B22: 大鰐町 | C22: =IF(OR(D22="◎",E22="◎"),"◎ 営業",IF(OR(D22="△",E22="△"),"△ 着手済・要確認",IF(OR(D22="？",E22="？"),"？ 期間要確認","✕ 対象外"))) | D22: =IF(J22="計画なし","－",IF(J22="策定済","✕",IF(H22="","？",IF(AND(H22>=TGT_MIN,H22<=TGT_MAX),IF(J22="着手済","△","◎"),"✕")))) | E22: =IF(P22="計画なし","－",IF(P22="策定済","✕",IF(N22="","？",IF(AND(N22>=TGT_MIN,N22<=TGT_MAX),IF(P22="着手済","△","◎"),"✕")))) | F22: 大鰐町地域公共交通計画 | G22: R5〜R9 | H22: 9 | I22: 推定 | J22: 未確認 | K22: http://www.town.owani.lg.jp/aboutowani/plan/kokyo-kotsu.html | M22: 不明 | O22: 不明 | P22: 未確認 | R22: 町HP「大鰐町地域公共交通計画策定について」ページに計画PDF（ファイル名R5.5.pdf）掲載→R5.5策定と見られ、5年計画ならR5〜R9（期間は未確認・推定）。過去に計画案策定支援業務の公募型プロポーザル実施: http://www.town.owani.lg.jp/news/index.cfm/detail.1.12187.html （日付未確認）。弘南鉄道大鰐線は運行休止/廃止方向で交通再編の動きあり。環境基本計画・温対計画は検索で見当たらず。 【ファクトチェック 2026-10-01: 確認できず】確認期間: None／次期: 確認できず（関連: 弘南鉄道大鰐線は2028年3月末で運行休止と発表され、代替交通は県主催の検討会議で調整中 https://trafficnews.jp/post/592513）／根拠: http://www.town.owani.lg.jp/aboutowani/plan/kokyo-kotsu.html 【追加調査 2026-10】【2026-10-02調査】検索3回（計画期間・次期計画/プロポ）で、町HP http://www.town.owani.lg.jp/aboutowani/plan/kokyo-kotsu.html のPDF（R5.5.pdf）以外に期間を示す本文は得られず、R5〜R9は推定のまま。町サイトはWebFetch不可（egress blocked）。次期計画の委託・パブコメ等は検索で見当たらず。 【追加調査 2026-10】環境：町名検索・町サイト限定検索（環境基本計画/温対実行計画/環境基本条例）とも該当なし。町計画ページ（振興計画・都市計画MP・地域防災計画等 http://www.town.owani.lg.jp/aboutowani/plan/shinko.html ）に環境計画は出ず。温対区域施策編も未確認のため根拠弱く未確認。確認日2026-10-02 | S22: 交通のみ調査 | T22: 掲載
A23: 20 | B23: 田舎館村 | C23: =IF(OR(D23="◎",E23="◎"),"◎ 営業",IF(OR(D23="△",E23="△"),"△ 着手済・要確認",IF(OR(D23="？",E23="？"),"？ 期間要確認","✕ 対象外"))) | D23: =IF(J23="計画なし","－",IF(J23="策定済","✕",IF(H23="","？",IF(AND(H23>=TGT_MIN,H23<=TGT_MAX),IF(J23="着手済","△","◎"),"✕")))) | E23: =IF(P23="計画なし","－",IF(P23="策定済","✕",IF(N23="","？",IF(AND(N23>=TGT_MIN,N23<=TGT_MAX),IF(P23="着手済","△","◎"),"✕")))) | G23: 不明 | I23: 不明 | J23: 未確認 | M23: 不明 | O23: 不明 | P23: 未確認 | R23: 交通：村HP内検索で地域公共交通計画は見当たらず。弘南鉄道弘南線・大鰐線 維持活性化支援計画（5市町村、2021年1月）に参加 http://www.vill.inakadate.lg.jp/docs/2021022200016/。なお青森県地域公共交通計画（R5〜R9、県全域）は県計画として全市町村を対象。環境基本計画は町/村名検索・公式サイト内検索で見当たらず（計画なしの確証はないため未確認）。 【追加調査 2026-10】環境：村名検索・村サイト限定検索で環境基本計画・温対実行計画・環境基本条例いずれも該当なし（公共施設等総合管理計画等のみ http://www.vill.inakadate.lg.jp/docs/2016102100010/files/sougoukannri-kaitei.pdf ）。計画なしの可能性高いが確証なく未確認。確認日2026-10-02 | S23: 未調査 | T23: 未掲載
A24: 21 | B24: 板柳町 | C24: =IF(OR(D24="◎",E24="◎"),"◎ 営業",IF(OR(D24="△",E24="△"),"△ 着手済・要確認",IF(OR(D24="？",E24="？"),"？ 期間要確認","✕ 対象外"))) | D24: =IF(J24="計画なし","－",IF(J24="策定済","✕",IF(H24="","？",IF(AND(H24>=TGT_MIN,H24<=TGT_MAX),IF(J24="着手済","△","◎"),"✕")))) | E24: =IF(P24="計画なし","－",IF(P24="策定済","✕",IF(N24="","？",IF(AND(N24>=TGT_MIN,N24<=TGT_MAX),IF(P24="着手済","△","◎"),"✕")))) | G24: 不明 | I24: 不明 | J24: 未確認 | M24: 不明 | O24: 不明 | P24: 未確認 | R24: 交通：町名検索・町HP内検索で地域公共交通計画は見当たらず（都市計画マスタープラン案R7.2に公共交通の記述あり https://www.town.itayanagi.aomori.jp/administration/salary/files/toshimasu.pdf）。なお青森県地域公共交通計画（R5〜R9、県全域）は県計画として全市町村を対象。環境基本計画は町/村名検索・公式サイト内検索で見当たらず（計画なしの確証はないため未確認）。 【追加調査 2026-10】環境：町名検索・町サイト限定検索で環境基本計画・温対実行計画・環境基本条例いずれもヒットなし（地域再生計画の汚水処理関連のみ）。計画なしの可能性高いが確証なく未確認。確認日2026-10-02 | S24: 未調査 | T24: 未掲載
A25: 22 | B25: 鶴田町 | C25: =IF(OR(D25="◎",E25="◎"),"◎ 営業",IF(OR(D25="△",E25="△"),"△ 着手済・要確認",IF(OR(D25="？",E25="？"),"？ 期間要確認","✕ 対象外"))) | D25: =IF(J25="計画なし","－",IF(J25="策定済","✕",IF(H25="","？",IF(AND(H25>=TGT_MIN,H25<=TGT_MAX),IF(J25="着手済","△","◎"),"✕")))) | E25: =IF(P25="計画なし","－",IF(P25="策定済","✕",IF(N25="","？",IF(AND(N25>=TGT_MIN,N25<=TGT_MAX),IF(P25="着手済","△","◎"),"✕")))) | G25: 不明 | I25: 不明 | J25: 未確認 | M25: 不明 | O25: 不明 | P25: 計画なし | R25: 交通：町名検索・町HP内検索で地域公共交通計画は見当たらず（各種計画ページ https://www.town.tsuruta.lg.jp/syoukai/syoukai-kakusyu/index.html に該当表示なし、要目視確認）。なお青森県地域公共交通計画（R5〜R9、県全域）は県計画として全市町村を対象。環境基本計画は町/村名検索・公式サイト内検索で見当たらず（計画なしの確証はないため未確認）。 【追加調査 2026-10】環境：町名検索・町サイト限定検索で環境基本計画は見当たらず。各種計画ページ https://www.town.tsuruta.lg.jp/syoukai/syoukai-kakusyu/index.html には鶴田町地域脱炭素実行計画（温対法21条4項の区域施策編・気候変動適応計画兼ねる、R7〜R12、2025年4月策定） https://www.town.tsuruta.lg.jp/info/document/jikko_keikaku.pdf が掲載（区域施策編のみ）。ページはWebFetchブロックで目視未了。確認日2026-10-02 | S25: 環境のみ調査 | T25: 未掲載
A26: 23 | B26: 中泊町 | C26: =IF(OR(D26="◎",E26="◎"),"◎ 営業",IF(OR(D26="△",E26="△"),"△ 着手済・要確認",IF(OR(D26="？",E26="？"),"？ 期間要確認","✕ 対象外"))) | D26: =IF(J26="計画なし","－",IF(J26="策定済","✕",IF(H26="","？",IF(AND(H26>=TGT_MIN,H26<=TGT_MAX),IF(J26="着手済","△","◎"),"✕")))) | E26: =IF(P26="計画なし","－",IF(P26="策定済","✕",IF(N26="","？",IF(AND(N26>=TGT_MIN,N26<=TGT_MAX),IF(P26="着手済","△","◎"),"✕")))) | F26: 中泊町地域公共交通計画 | G26: R5〜R9 | H26: 9 | I26: 確認済 | J26: 未確認 | K26: https://www.town.nakadomari.lg.jp/material/files/group/3/koutuukeikakur6.pdf | M26: 不明 | O26: 不明 | P26: 計画なし | R26: 交通：計画書表紙「令和5年4月」、計画ページ https://www.town.nakadomari.lg.jp/soshikikarasagasu/sogosenryakuka/gyomuannai/5/1/1/4311.html 。ファイル名にr6とあり令和6年に改訂の可能性。期間は未確認で5年と仮定しR5〜R9推定。環境基本計画は町/村名検索・公式サイト内検索で見当たらず（計画なしの確証はないため未確認）。 【ファクトチェック 2026-10-01: 正しい】確認期間: R5〜R9／次期: 確認できず（町のプロポーザル一覧に交通計画関連は見当たらず）／根拠: https://www.town.nakadomari.lg.jp/soshikikarasagasu/sogosenryakuka/gyomuannai/5/1/1/4311.html 【追加調査 2026-10】環境：町名検索・町サイト限定検索で環境基本計画は見当たらず。中泊町地球温暖化対策実行計画（事務事業編・区域施策編）、再エネ導入戦略、NAKAZERO共創アクション（脱炭素行動計画、R8.4策定、脱炭素先行地域選定） https://www.town.nakadomari.lg.jp/soshikikarasagasu/sogosenryakuka/gyomuannai/tikyuuondankataisaku/5369.html のみ（区域施策編のみ）。確認日2026-10-02 | S26: 調査済 | T26: 掲載
A27: 24 | B27: 野辺地町 | C27: =IF(OR(D27="◎",E27="◎"),"◎ 営業",IF(OR(D27="△",E27="△"),"△ 着手済・要確認",IF(OR(D27="？",E27="？"),"？ 期間要確認","✕ 対象外"))) | D27: =IF(J27="計画なし","－",IF(J27="策定済","✕",IF(H27="","？",IF(AND(H27>=TGT_MIN,H27<=TGT_MAX),IF(J27="着手済","△","◎"),"✕")))) | E27: =IF(P27="計画なし","－",IF(P27="策定済","✕",IF(N27="","？",IF(AND(N27>=TGT_MIN,N27<=TGT_MAX),IF(P27="着手済","△","◎"),"✕")))) | G27: 不明 | I27: 不明 | J27: 未確認 | M27: 不明 | O27: 不明 | P27: 未確認 | R27: 交通・環境とも町単独計画は検索で確認できず（町HP「まちの計画」 https://www.town.noheji.aomori.jp/life/chosei/machidukuri/machi-keikaku は存在するが内容未確認、町サイトは取得不可）。地域間幹線系統確保維持費補助金交付要綱あり https://www.town.noheji.aomori.jp/reiki_int/reiki_honbun/c041RG00000724.html 。改定作業の情報なし。 【追加調査 2026-10】環境：町名検索・町サイト限定検索で環境基本計画・温対実行計画・環境基本条例いずれも見当たらず（ヒットは地域防災計画・過疎計画R3〜R7等。過疎計画内に温暖化対策の記述あり https://www.town.noheji.aomori.jp/application/files/8816/4030/5415/ebdf28da23a799a96da8885110e20596.pdf ）。町サイトWebFetch不可。確証なく未確認。確認日2026-10-02 | S27: 未調査 | T27: 未掲載
A28: 25 | B28: 七戸町 | C28: =IF(OR(D28="◎",E28="◎"),"◎ 営業",IF(OR(D28="△",E28="△"),"△ 着手済・要確認",IF(OR(D28="？",E28="？"),"？ 期間要確認","✕ 対象外"))) | D28: =IF(J28="計画なし","－",IF(J28="策定済","✕",IF(H28="","？",IF(AND(H28>=TGT_MIN,H28<=TGT_MAX),IF(J28="着手済","△","◎"),"✕")))) | E28: =IF(P28="計画なし","－",IF(P28="策定済","✕",IF(N28="","？",IF(AND(N28>=TGT_MIN,N28<=TGT_MAX),IF(P28="着手済","△","◎"),"✕")))) | F28: 七戸町地域公共交通網形成計画 | G28: 不明 | I28: 不明 | J28: 未確認 | K28: https://www.town.shichinohe.lg.jp/gyosei/keikaku/kurashi/post-197.html | M28: 不明 | O28: 不明 | P28: 計画なし | R28: 網形成計画（策定支援プロポ: http://www.town.shichinohe.lg.jp/jigyo/nyuusatsu/post-65.html）。期間未確認で既に期限切れの可能性、後継の地域公共交通計画は未確認（H21に地域公共交通会議設置・総合連携計画策定の経緯あり）。環境基本計画は確認できず、関連として地域省エネルギー重点ビジョン（H22）あり（計画なしは弱い根拠）。 環境基本計画は検索で確認できず（計画なしの確証なし）。 【追加調査 2026-10】環境：町名検索・町サイト限定検索・条例検索で環境基本計画/環境基本条例は見当たらず。七戸町地球温暖化対策実行計画（区域施策編、令和6年3月） https://www.town.shichinohe.lg.jp/gyosei/2024/d97c0d43297ff492dc72aae03439179b.pdf が町政情報に掲載（区域施策編のみ）。他に地域省エネルギー重点ビジョン（H22）。確認日2026-10-02 | S28: 調査済 | T28: 掲載／期間満了
A29: 26 | B29: 六戸町 | C29: =IF(OR(D29="◎",E29="◎"),"◎ 営業",IF(OR(D29="△",E29="△"),"△ 着手済・要確認",IF(OR(D29="？",E29="？"),"？ 期間要確認","✕ 対象外"))) | D29: =IF(J29="計画なし","－",IF(J29="策定済","✕",IF(H29="","？",IF(AND(H29>=TGT_MIN,H29<=TGT_MAX),IF(J29="着手済","△","◎"),"✕")))) | E29: =IF(P29="計画なし","－",IF(P29="策定済","✕",IF(N29="","？",IF(AND(N29>=TGT_MIN,N29<=TGT_MAX),IF(P29="着手済","△","◎"),"✕")))) | G29: 不明 | I29: 不明 | J29: 着手済 | M29: 不明 | O29: 不明 | P29: 未確認 | R29: 交通計画は未確認だが、2026年8月31日に「交通まちづくりワークショップ」開催告知（町バス利用者・学生・保護者・事業者対象）: https://www.town.rokunohe.aomori.jp/docs/2026083100015 。地域公共交通計画策定に向けた作業と推定（計画名・プロポは未確認）。環境基本計画・温対計画は検索で見当たらず。 【追加調査 2026-10】環境：町名検索・町サイト限定検索で環境基本計画・温対実行計画・環境基本条例いずれも見当たらず（公共施設等総合管理計画H29等のみ https://www.town.rokunohe.aomori.jp/file/chousei/shisaku/kokyoshisetsusougoukanriplan/kokyoshisetsusougoukanriplan.pdf ）。確証なく未確認。確認日2026-10-02 | S29: 未調査 | T29: 未掲載
A30: 27 | B30: 横浜町 | C30: =IF(OR(D30="◎",E30="◎"),"◎ 営業",IF(OR(D30="△",E30="△"),"△ 着手済・要確認",IF(OR(D30="？",E30="？"),"？ 期間要確認","✕ 対象外"))) | D30: =IF(J30="計画なし","－",IF(J30="策定済","✕",IF(H30="","？",IF(AND(H30>=TGT_MIN,H30<=TGT_MAX),IF(J30="着手済","△","◎"),"✕")))) | E30: =IF(P30="計画なし","－",IF(P30="策定済","✕",IF(N30="","？",IF(AND(N30>=TGT_MIN,N30<=TGT_MAX),IF(P30="着手済","△","◎"),"✕")))) | G30: 不明 | I30: 不明 | J30: 未確認 | M30: 不明 | O30: 不明 | P30: 未確認 | R30: 町単独の地域公共交通計画は確認できず。下北地域公共交通計画（2025年3月策定、下北地域公共交通総合連携協議会）の対象はむつ市・大間町・東通村・風間浦村・佐井村の5市町村で横浜町は含まれない（むつ市資料 https://www.city.mutsu.lg.jp/government/katsudou/kyoudou/files/04kotsu.pdf で確認）。下北半島都市圏広域立地適正化方針（R5.8）には含まれる。町HPに2026-04-10付PDFあり内容未確認 https://www.town.yokohama.lg.jp/index.cfm/6,9299,c,html/9299/20260410-143501.pdf 。環境基本計画・区域施策編も検索で見当たらず（横浜市との再エネ連携協定はあり）。 【追加調査 2026-10】環境：環境基本計画は町名検索・町サイト(town.yokohama.lg.jp)限定検索ともヒットせず。町サイトではゼロカーボンシティ宣言ページに地球温暖化対策実行計画（事務事業編、R6.3策定）と、今後区域施策編を策定予定との記載のみ https://www.town.yokohama.lg.jp/index.cfm/6,11904,18,194,html 。環境基本計画の有無は断定できず未確認のまま。（確認日2026-10-02） | S30: 未調査 | T30: 未掲載
A31: 28 | B31: 東北町 | C31: =IF(OR(D31="◎",E31="◎"),"◎ 営業",IF(OR(D31="△",E31="△"),"△ 着手済・要確認",IF(OR(D31="？",E31="？"),"？ 期間要確認","✕ 対象外"))) | D31: =IF(J31="計画なし","－",IF(J31="策定済","✕",IF(H31="","？",IF(AND(H31>=TGT_MIN,H31<=TGT_MAX),IF(J31="着手済","△","◎"),"✕")))) | E31: =IF(P31="計画なし","－",IF(P31="策定済","✕",IF(N31="","？",IF(AND(N31>=TGT_MIN,N31<=TGT_MAX),IF(P31="着手済","△","◎"),"✕")))) | G31: 不明 | I31: 不明 | J31: 未確認 | M31: 不明 | O31: 不明 | P31: 計画なし | R31: 東北町地域公共交通会議あり（会議録 https://www.town.tohoku.lg.jp/chousei/info/info_yakuba_03-54.html ）。地域公共交通計画の有無は検索で確認できず（東北運輸局の計画一覧PDF https://wwwtb.mlit.go.jp/tohoku/content/000338501.pdf がヒットしたが中身未確認）。環境基本計画も見当たらず、関連は「小川原湖環境再生」計画（地域再生計画、汚水処理）程度。第2期まち・ひと・しごと創生推進計画はR8.4〜R13.3。 【追加調査 2026-10】環境：町サイト限定検索で環境基本計画はヒットせず、代わりに東北町地球温暖化対策実行計画（区域施策編）（計画期間2026〜2035＝R8〜R17、2030年度50%削減・2050実質ゼロ）の策定業務プロポーザル資料・計画ページのみ（区域施策編で対応）。 https://www.town.tohoku.lg.jp/chousei/info/info_yakuba_09-42.html 、仕様書 https://www.town.tohoku.lg.jp/chousei/info/file/info_yakuba_09-29-02.pdf 。根拠は検索結果ベースでやや弱い。（確認日2026-10-02） 根拠: 計画期間は、2026（令和8）年度から2035（令和17）年度までの10年間（区域施策編・検索要約） | S31: 環境のみ調査 | T31: 未掲載
A32: 29 | B32: 六ヶ所村 | C32: =IF(OR(D32="◎",E32="◎"),"◎ 営業",IF(OR(D32="△",E32="△"),"△ 着手済・要確認",IF(OR(D32="？",E32="？"),"？ 期間要確認","✕ 対象外"))) | D32: =IF(J32="計画なし","－",IF(J32="策定済","✕",IF(H32="","？",IF(AND(H32>=TGT_MIN,H32<=TGT_MAX),IF(J32="着手済","△","◎"),"✕")))) | E32: =IF(P32="計画なし","－",IF(P32="策定済","✕",IF(N32="","？",IF(AND(N32>=TGT_MIN,N32<=TGT_MAX),IF(P32="着手済","△","◎"),"✕")))) | F32: 六ヶ所村地域公共交通計画 | G32: R7〜（終期不明） | I32: 不明 | J32: 策定済 | K32: https://www.rokkasho.jp/index.cfm/14,19918,c,html/19918/20250620-120455.pdf | M32: 不明 | O32: 不明 | P32: 計画なし | R32: R7.3策定（素案住民意見聴取後）。計画ページ https://www.rokkasho.jp/index.cfm/11,19571,31,177,html 。R7.6に計画に基づく再編・見直し検討及び実証運行支援業務の公募型プロポーザル実施 https://www.rokkasho.jp/index.cfm/14,19918,31,177,html 。環境基本計画は検索で見当たらず（関連: 水環境保全計画、地域新エネルギービジョン、バイオマスタウン構想）。 【追加調査 2026-10】環境：村サイト限定検索で環境基本計画はヒットせず。代わりに六ヶ所村地球温暖化対策実行計画（区域施策編）（R6.3策定、R6〜R15、ゼロカーボンシティ宣言R4.12）http://www.rokkasho.jp/index.cfm/10,17954,31,124,html 、新エネルギー推進計画、水環境保全計画あり。区域施策編等の個別計画で対応と判断（根拠は検索結果ベース）。（確認日2026-10-02） 根拠: 区域施策編の計画期間 令和6年度～令和15年度（検索要約） | S32: 調査済 | T32: 掲載
A33: 30 | B33: おいらせ町 | C33: =IF(OR(D33="◎",E33="◎"),"◎ 営業",IF(OR(D33="△",E33="△"),"△ 着手済・要確認",IF(OR(D33="？",E33="？"),"？ 期間要確認","✕ 対象外"))) | D33: =IF(J33="計画なし","－",IF(J33="策定済","✕",IF(H33="","？",IF(AND(H33>=TGT_MIN,H33<=TGT_MAX),IF(J33="着手済","△","◎"),"✕")))) | E33: =IF(P33="計画なし","－",IF(P33="策定済","✕",IF(N33="","？",IF(AND(N33>=TGT_MIN,N33<=TGT_MAX),IF(P33="着手済","△","◎"),"✕")))) | F33: 八戸圏域地域公共交通計画（八戸圏域8市町村共同） | G33: R5〜R10 | H33: 10 | I33: 確認済 | J33: 未確認 | K33: https://wwwtb.mlit.go.jp/tohoku/content/000181287.pdf | M33: 不明 | O33: 不明 | P33: 未確認 | R33: 交通計画は八戸圏域8市町村の圏域共同計画（R5〜R10）。環境基本計画は町名検索・ゼロカーボン検索とも該当なし（地域再生計画等のみヒット）。区域施策編も未確認。 【追加調査 2026-10】環境：町名検索・町サイト限定検索とも環境基本計画はヒットせず。町サイトでは第2次総合計画後期基本計画（R6〜R10）https://www.town.oirase.aomori.jp/uploaded/attachment/22191.pdf の環境保全施策、都市計画MP、地球温暖化対策実行計画（事務事業編）、自然・地域と再生可能エネルギー共生審議会 https://www.town.oirase.aomori.jp/soshiki/1232/kanykoukyousei.html のみ。区域施策編も確認できず。（確認日2026-10-02） | S33: 交通のみ調査 | T33: 掲載（広域：八戸圏域）
A34: 31 | B34: 大間町 | C34: =IF(OR(D34="◎",E34="◎"),"◎ 営業",IF(OR(D34="△",E34="△"),"△ 着手済・要確認",IF(OR(D34="？",E34="？"),"？ 期間要確認","✕ 対象外"))) | D34: =IF(J34="計画なし","－",IF(J34="策定済","✕",IF(H34="","？",IF(AND(H34>=TGT_MIN,H34<=TGT_MAX),IF(J34="着手済","△","◎"),"✕")))) | E34: =IF(P34="計画なし","－",IF(P34="策定済","✕",IF(N34="","？",IF(AND(N34>=TGT_MIN,N34<=TGT_MAX),IF(P34="着手済","△","◎"),"✕")))) | F34: 下北地域公共交通計画（下北地域公共交通総合連携協議会：むつ市・大間町・東通村・風間浦村・佐井村） | G34: R7〜R11 | H34: 11 | I34: 確認済 | J34: 策定済 | K34: https://www.city.mutsu.lg.jp/government/katsudou/kyoudou/files/simokitatiikikoukyoukoutuukeikakusoann.pdf | M34: 不明 | O34: 不明 | P34: 未確認 | R34: 交通計画は下北5市町村の圏域共同計画（2025〜2029＝R7〜R11、R7.3策定）。t_urlはむつ市サイト掲載の素案PDF（確定版URLは検索で見つからず）。環境基本計画・温暖化対策実行計画とも検索でヒットせず。 【追加調査 2026-10】環境：環境基本計画は検索でヒットせず。町サイト(town.ooma.lg.jp)の公表情報一覧に第3次地球温暖化対策実行計画（2024-12-13公表、事務事業編とみられる）、第2次(2019)、第1次(2013)の記載あり https://www.town.ooma.lg.jp/allpub_index.html 。環境基本計画の有無は断定できず。（確認日2026-10-02） | S34: 交通のみ調査 | T34: 掲載（広域：下北地域）
A35: 32 | B35: 東通村 | C35: =IF(OR(D35="◎",E35="◎"),"◎ 営業",IF(OR(D35="△",E35="△"),"△ 着手済・要確認",IF(OR(D35="？",E35="？"),"？ 期間要確認","✕ 対象外"))) | D35: =IF(J35="計画なし","－",IF(J35="策定済","✕",IF(H35="","？",IF(AND(H35>=TGT_MIN,H35<=TGT_MAX),IF(J35="着手済","△","◎"),"✕")))) | E35: =IF(P35="計画なし","－",IF(P35="策定済","✕",IF(N35="","？",IF(AND(N35>=TGT_MIN,N35<=TGT_MAX),IF(P35="着手済","△","◎"),"✕")))) | F35: 下北地域公共交通計画（下北地域公共交通総合連携協議会：むつ市・大間町・東通村・風間浦村・佐井村） | G35: R7〜R11 | H35: 11 | I35: 確認済 | J35: 策定済 | K35: https://www.city.mutsu.lg.jp/government/katsudou/kyoudou/files/simokitatiikikoukyoukoutuukeikakusoann.pdf | M35: 不明 | O35: 不明 | P35: 未確認 | R35: 交通計画は下北5市町村の圏域共同計画（2025〜2029＝R7〜R11、R7.3策定）。t_urlはむつ市サイト掲載の素案PDF（確定版URLは検索で見つからず）。環境基本計画は検索でヒットせず（原発モニタリング・風力アセス関連のみ）。 【追加調査 2026-10】環境：環境基本計画は検索でヒットせず（原発関連の環境放射線モニタリング基本計画のみ：県 https://www.pref.aomori.lg.jp/soshiki/kikikanri/atom/higashidori-monitoring-keikaku-R0803.pdf ）。村サイト限定検索は結果なし。温暖化対策実行計画も確認できず。（確認日2026-10-02） | S35: 交通のみ調査 | T35: 掲載（広域：下北地域）
A36: 33 | B36: 風間浦村 | C36: =IF(OR(D36="◎",E36="◎"),"◎ 営業",IF(OR(D36="△",E36="△"),"△ 着手済・要確認",IF(OR(D36="？",E36="？"),"？ 期間要確認","✕ 対象外"))) | D36: =IF(J36="計画なし","－",IF(J36="策定済","✕",IF(H36="","？",IF(AND(H36>=TGT_MIN,H36<=TGT_MAX),IF(J36="着手済","△","◎"),"✕")))) | E36: =IF(P36="計画なし","－",IF(P36="策定済","✕",IF(N36="","？",IF(AND(N36>=TGT_MIN,N36<=TGT_MAX),IF(P36="着手済","△","◎"),"✕")))) | F36: 下北地域公共交通計画（下北地域公共交通総合連携協議会：むつ市・大間町・東通村・風間浦村・佐井村） | G36: R7〜R11 | H36: 11 | I36: 確認済 | J36: 策定済 | K36: https://www.city.mutsu.lg.jp/government/katsudou/kyoudou/files/simokitatiikikoukyoukoutuukeikakusoann.pdf | M36: 不明 | O36: 不明 | P36: 未確認 | R36: 交通計画は下北5市町村の圏域共同計画（2025〜2029＝R7〜R11、R7.3策定）。t_urlはむつ市サイト掲載の素案PDF（確定版URLは検索で見つからず）。環境基本計画・温暖化対策実行計画とも検索でヒットせず。 【追加調査 2026-10】環境：環境基本計画は検索でヒットせず。村サイト(kazamaura.jp)では第2次風間浦村地球温暖化対策実行計画（事務事業編）の2024年度実施状況 https://www.kazamaura.jp/2026/01/27/%E7%AC%AC%EF%BC%92%E6%AC%A1%E9%A2%A8%E9%96%93%E6%B5%A6%E6%9D%91%E5%9C%B0%E7%90%83%E6%B8%A9%E6%9A%96%E5%8C%96%E5%AF%BE%E7%AD%96%E5%AE%9F%E8%A1%8C%E8%A8%88%E7%94%BB%EF%BC%88%E4%BA%8B%E5%8B%99%E4%BA%8B-4/ 、ゼロカーボンシティ宣言（R5.3.1）、ブルーカーボン調査のみ。（確認日2026-10-02） | S36: 交通のみ調査 | T36: 掲載（広域：下北地域）
A37: 34 | B37: 佐井村 | C37: =IF(OR(D37="◎",E37="◎"),"◎ 営業",IF(OR(D37="△",E37="△"),"△ 着手済・要確認",IF(OR(D37="？",E37="？"),"？ 期間要確認","✕ 対象外"))) | D37: =IF(J37="計画なし","－",IF(J37="策定済","✕",IF(H37="","？",IF(AND(H37>=TGT_MIN,H37<=TGT_MAX),IF(J37="着手済","△","◎"),"✕")))) | E37: =IF(P37="計画なし","－",IF(P37="策定済","✕",IF(N37="","？",IF(AND(N37>=TGT_MIN,N37<=TGT_MAX),IF(P37="着手済","△","◎"),"✕")))) | F37: 下北地域公共交通計画（下北地域公共交通総合連携協議会：むつ市・大間町・東通村・風間浦村・佐井村） | G37: R7〜R11 | H37: 11 | I37: 確認済 | J37: 策定済 | K37: https://www.city.mutsu.lg.jp/government/katsudou/kyoudou/files/simokitatiikikoukyoukoutuukeikakusoann.pdf | M37: 不明 | O37: 不明 | P37: 未確認 | R37: 交通計画は下北5市町村の圏域共同計画（2025〜2029＝R7〜R11、R7.3策定）。t_urlはむつ市サイト掲載の素案PDF（確定版URLは検索で見つからず）。環境基本計画・温暖化対策実行計画とも検索でヒットせず。 【追加調査 2026-10】環境：環境基本計画は検索でヒットせず。村サイト(vill.sai.lg.jp)では脱炭素先行地域（2023.4選定）関連補助金 https://www.vill.sai.lg.jp/status-initiatives/decarbonization/ 、ゼロカーボンシティさい表明、ブルーカーボン推進事業のみ。温暖化対策実行計画の有無も未確認。（確認日2026-10-02） | S37: 交通のみ調査 | T37: 掲載（広域：下北地域）
A38: 35 | B38: 三戸町 | C38: =IF(OR(D38="◎",E38="◎"),"◎ 営業",IF(OR(D38="△",E38="△"),"△ 着手済・要確認",IF(OR(D38="？",E38="？"),"？ 期間要確認","✕ 対象外"))) | D38: =IF(J38="計画なし","－",IF(J38="策定済","✕",IF(H38="","？",IF(AND(H38>=TGT_MIN,H38<=TGT_MAX),IF(J38="着手済","△","◎"),"✕")))) | E38: =IF(P38="計画なし","－",IF(P38="策定済","✕",IF(N38="","？",IF(AND(N38>=TGT_MIN,N38<=TGT_MAX),IF(P38="着手済","△","◎"),"✕")))) | F38: 八戸圏域地域公共交通計画（八戸圏域8市町村共同） | G38: R5〜R10 | H38: 10 | I38: 確認済 | J38: 未確認 | K38: https://wwwtb.mlit.go.jp/tohoku/content/000181287.pdf | M38: 不明 | O38: 不明 | P38: 計画なし | R38: 交通計画は八戸圏域8市町村の圏域共同計画（R5〜R10）。環境基本計画・地球温暖化対策実行計画とも検索でヒットせず（地域再生計画・風力アセスのみ）。 【追加調査 2026-10】環境：町名検索・町サイト限定検索とも環境基本計画はヒットせず。代わりに三戸町地球温暖化対策実行計画（事務事業編＋町全体の区域の削減施策を含む、R6〜R12、2030年度58.7%削減）https://www.town.sannohe.aomori.jp/soshiki/soumu/gyouseijouhou/1/4712.html と2050ゼロカーボン宣言。温暖化実行計画で対応と判断（根拠は検索結果ベース）。（確認日2026-10-02） 根拠: 計画期間 令和6年度～令和12年度（温暖化実行計画・検索要約） | S38: 調査済 | T38: 掲載（広域：八戸圏域）
A39: 36 | B39: 五戸町 | C39: =IF(OR(D39="◎",E39="◎"),"◎ 営業",IF(OR(D39="△",E39="△"),"△ 着手済・要確認",IF(OR(D39="？",E39="？"),"？ 期間要確認","✕ 対象外"))) | D39: =IF(J39="計画なし","－",IF(J39="策定済","✕",IF(H39="","？",IF(AND(H39>=TGT_MIN,H39<=TGT_MAX),IF(J39="着手済","△","◎"),"✕")))) | E39: =IF(P39="計画なし","－",IF(P39="策定済","✕",IF(N39="","？",IF(AND(N39>=TGT_MIN,N39<=TGT_MAX),IF(P39="着手済","△","◎"),"✕")))) | F39: 八戸圏域地域公共交通計画（八戸圏域8市町村共同） | G39: R5〜R10 | H39: 10 | I39: 確認済 | J39: 未確認 | K39: https://wwwtb.mlit.go.jp/tohoku/content/000181287.pdf | M39: 不明 | O39: 不明 | P39: 計画なし | R39: 交通計画は八戸圏域8市町村の圏域共同計画（R5〜R10）。環境基本計画は検索でヒットせず。代替として五戸町地球温暖化対策実行計画（区域施策編・地域気候変動適応計画兼ねる、R7.3策定、環境省地域脱炭素実現支援事業で作成）あり：https://www.town.gonohe.aomori.jp/chosei/tikyuondankahonpen.pdf （概要版 https://www.town.gonohe.aomori.jp/chosei/tikyuondankagaiyouban.pdf ）。期間は検索結果で確認できず。環境省策定状況 https://www.env.go.jp/policy/local_keikaku/sakutei2/02/02442.html 【追加調査 2026-10】環境：町名検索で環境基本計画はヒットせず、町サイトPDFは五戸町地球温暖化対策実行計画（区域施策編・適応計画兼、R7.3策定、計画期間R7〜R12）https://www.town.gonohe.aomori.jp/chosei/tikyuondankahonpen.pdf 、概要版 https://www.town.gonohe.aomori.jp/chosei/tikyuondankagaiyouban.pdf 、ごみ処理基本計画（R8〜R17）のみ。区域施策編のみと判断。（確認日2026-10-02） 根拠: 令和7（2025）年度から令和12（2030）年度までの6年間（区域施策編概要版・検索要約） | S39: 調査済 | T39: 掲載（広域：八戸圏域）
A40: 37 | B40: 田子町 | C40: =IF(OR(D40="◎",E40="◎"),"◎ 営業",IF(OR(D40="△",E40="△"),"△ 着手済・要確認",IF(OR(D40="？",E40="？"),"？ 期間要確認","✕ 対象外"))) | D40: =IF(J40="計画なし","－",IF(J40="策定済","✕",IF(H40="","？",IF(AND(H40>=TGT_MIN,H40<=TGT_MAX),IF(J40="着手済","△","◎"),"✕")))) | E40: =IF(P40="計画なし","－",IF(P40="策定済","✕",IF(N40="","？",IF(AND(N40>=TGT_MIN,N40<=TGT_MAX),IF(P40="着手済","△","◎"),"✕")))) | F40: 八戸圏域地域公共交通計画（八戸圏域8市町村共同） | G40: R5〜R10 | H40: 10 | I40: 確認済 | J40: 未確認 | K40: https://wwwtb.mlit.go.jp/tohoku/content/000181287.pdf | M40: 不明 | O40: 不明 | P40: 未確認 | R40: 交通計画は八戸圏域8市町村の圏域共同計画（R5〜R10）。環境基本計画・温暖化対策実行計画とも検索でヒットせず。 【追加調査 2026-10】環境：環境基本計画は町名検索・町サイト限定検索ともヒットせず。町サイト計画ページには田子町総合計画、地球温暖化対策実行計画（事務事業編、H24〜H28と古い）https://www.town.takko.lg.jp/index.cfm/13,234,50,202,html 、森林整備計画等。計画一覧 http://www.town.takko.lg.jp/index.cfm/13,0,50,202,html の全体は未確認のため未確認のまま。（確認日2026-10-02） | S40: 交通のみ調査 | T40: 掲載（広域：八戸圏域）
A41: 38 | B41: 南部町 | C41: =IF(OR(D41="◎",E41="◎"),"◎ 営業",IF(OR(D41="△",E41="△"),"△ 着手済・要確認",IF(OR(D41="？",E41="？"),"？ 期間要確認","✕ 対象外"))) | D41: =IF(J41="計画なし","－",IF(J41="策定済","✕",IF(H41="","？",IF(AND(H41>=TGT_MIN,H41<=TGT_MAX),IF(J41="着手済","△","◎"),"✕")))) | E41: =IF(P41="計画なし","－",IF(P41="策定済","✕",IF(N41="","？",IF(AND(N41>=TGT_MIN,N41<=TGT_MAX),IF(P41="着手済","△","◎"),"✕")))) | F41: 八戸圏域地域公共交通計画（八戸圏域8市町村共同） | G41: R5〜R10 | H41: 10 | I41: 確認済 | J41: 未確認 | K41: https://wwwtb.mlit.go.jp/tohoku/content/000181287.pdf | M41: 不明 | O41: 不明 | P41: 未確認 | R41: 交通計画は八戸圏域8市町村の圏域共同計画（R5〜R10）。青森県三戸郡南部町。環境基本計画・温暖化対策実行計画とも検索でヒットせず（地域再生計画のみ）。 【追加調査 2026-10】環境：青森県三戸郡南部町（山梨・鳥取の南部町と別）。町サイト(town.aomori-nanbu.lg.jp)限定検索で環境基本計画・区域施策編はヒットせず（議会会議録、公共施設等総合管理計画の脱炭素記載、第2次総合振興計画進捗報告のみ）。（確認日2026-10-02） | S41: 交通のみ調査 | T41: 掲載（広域：八戸圏域）
A42: 39 | B42: 階上町 | C42: =IF(OR(D42="◎",E42="◎"),"◎ 営業",IF(OR(D42="△",E42="△"),"△ 着手済・要確認",IF(OR(D42="？",E42="？"),"？ 期間要確認","✕ 対象外"))) | D42: =IF(J42="計画なし","－",IF(J42="策定済","✕",IF(H42="","？",IF(AND(H42>=TGT_MIN,H42<=TGT_MAX),IF(J42="着手済","△","◎"),"✕")))) | E42: =IF(P42="計画なし","－",IF(P42="策定済","✕",IF(N42="","？",IF(AND(N42>=TGT_MIN,N42<=TGT_MAX),IF(P42="着手済","△","◎"),"✕")))) | F42: 八戸圏域地域公共交通計画（八戸圏域8市町村共同） | G42: R5〜R10 | H42: 10 | I42: 確認済 | J42: 未確認 | K42: https://wwwtb.mlit.go.jp/tohoku/content/000181287.pdf | M42: 不明 | O42: 不明 | P42: 未確認 | R42: 交通計画は八戸圏域8市町村の圏域共同計画（R5〜R10）。環境基本計画・温暖化対策実行計画・ゼロカーボン関連とも検索でヒットせず。 【追加調査 2026-10】環境：環境基本計画は町名検索・町サイト限定検索ともヒットせず。町サイトでは第2次階上町環境保全率先行動計画（階上町地球温暖化対策推進実行計画、H26.12）https://www.town.hashikami.lg.jp/index.cfm/9,2212,c,html/2212/20200316-154455.pdf と自家消費型太陽光補助のみ。（確認日2026-10-02） | S42: 交通のみ調査 | T42: 掲載（広域：八戸圏域）
A43: 40 | B43: 新郷村 | C43: =IF(OR(D43="◎",E43="◎"),"◎ 営業",IF(OR(D43="△",E43="△"),"△ 着手済・要確認",IF(OR(D43="？",E43="？"),"？ 期間要確認","✕ 対象外"))) | D43: =IF(J43="計画なし","－",IF(J43="策定済","✕",IF(H43="","？",IF(AND(H43>=TGT_MIN,H43<=TGT_MAX),IF(J43="着手済","△","◎"),"✕")))) | E43: =IF(P43="計画なし","－",IF(P43="策定済","✕",IF(N43="","？",IF(AND(N43>=TGT_MIN,N43<=TGT_MAX),IF(P43="着手済","△","◎"),"✕")))) | F43: 八戸圏域地域公共交通計画（八戸圏域8市町村共同） | G43: R5〜R10 | H43: 10 | I43: 確認済 | J43: 未確認 | K43: https://wwwtb.mlit.go.jp/tohoku/content/000181287.pdf | M43: 不明 | O43: 不明 | P43: 計画なし | R43: 交通計画は八戸圏域8市町村の圏域共同計画（R5〜R10）。環境基本計画・温暖化対策実行計画とも検索でヒットせず。 【追加調査 2026-10】環境：村サイトの「ゴミ・リサイクル・環境」ページ https://www.vill.shingo.aomori.jp/public/anzeneisei/ に掲載の計画はごみ減量・分別収集・一般廃棄物処理基本計画・地球温暖化対策実行計画（事務事業編）・災害廃棄物処理計画で、環境基本計画は無し（検索要約ベース）。村名検索でもヒットせず。（確認日2026-10-02） | S43: 調査済 | T43: 掲載（広域：八戸圏域）

Sheet 岩手県
A1: 岩手県 地域公共交通計画・環境基本計画の終期一覧（2026年9月30日時点の調査）
A2: ="営業判定の対象：終期 R"&TGT_MIN&"〜R"&TGT_MAX&"年度 →◎（着手済は△、期間不明は？）。終期セルの色：緑＝対象年度／橙＝その翌年度（次の候補）。対象年度は「集計・設定」シートのC4・C5のプルダウンで切替。"
A3: No | B3: 市町村 | C3: 営業判定 | D3: 交通判定 | E3: 環境判定 | F3: 地域公共交通計画 | G3: 交通 計画期間 | H3: 交通 終期(令和年度) | I3: 交通 確度 | J3: 交通 改定状況 | K3: 交通 計画リンク（エビデンス） | L3: 環境基本計画 | M3: 環境 計画期間 | N3: 環境 終期(令和年度) | O3: 環境 確度 | P3: 環境 改定状況 | Q3: 環境 計画リンク（エビデンス） | R3: 注釈（改定作業の状況など） | S3: 調査状況 | T3: 国交省一覧(R8.5末)
A4: 1 | B4: 盛岡市 | C4: =IF(OR(D4="◎",E4="◎"),"◎ 営業",IF(OR(D4="△",E4="△"),"△ 着手済・要確認",IF(OR(D4="？",E4="？"),"？ 期間要確認","✕ 対象外"))) | D4: =IF(J4="計画なし","－",IF(J4="策定済","✕",IF(H4="","？",IF(AND(H4>=TGT_MIN,H4<=TGT_MAX),IF(J4="着手済","△","◎"),"✕")))) | E4: =IF(P4="計画なし","－",IF(P4="策定済","✕",IF(N4="","？",IF(AND(N4>=TGT_MIN,N4<=TGT_MAX),IF(P4="着手済","△","◎"),"✕")))) | F4: 盛岡都市圏地域公共交通計画（盛岡市・滝沢市・矢巾町共同） | G4: R8〜R12 | H4: 12 | I4: 確認済 | J4: 策定済 | K4: https://www.city.morioka.iwate.jp/_res/projects/default_project/_page_/001/043/162/R7honpen.pdf | L4: 盛岡市環境基本計画（第三次） | M4: R3〜R12 | N4: 12 | O4: 確認済 | P4: 未確認 | Q4: https://www.city.morioka.iwate.jp/_res/projects/default_project/_page_/001/010/054/kihonntekizikou.pdf | R4: 交通：3市町共同の都市圏計画をR7.9.30公表（R8〜R12）。環境：R3〜R12の10年計画、改定作業は未確認。 | S4: 調査済 | T4: 掲載（広域：盛岡市・滝沢市・矢巾町）
A5: 2 | B5: 宮古市 | C5: =IF(OR(D5="◎",E5="◎"),"◎ 営業",IF(OR(D5="△",E5="△"),"△ 着手済・要確認",IF(OR(D5="？",E5="？"),"？ 期間要確認","✕ 対象外"))) | D5: =IF(J5="計画なし","－",IF(J5="策定済","✕",IF(H5="","？",IF(AND(H5>=TGT_MIN,H5<=TGT_MAX),IF(J5="着手済","△","◎"),"✕")))) | E5: =IF(P5="計画なし","－",IF(P5="策定済","✕",IF(N5="","？",IF(AND(N5>=TGT_MIN,N5<=TGT_MAX),IF(P5="着手済","△","◎"),"✕")))) | F5: 宮古市地域公共交通計画 | G5: R5〜R11 | H5: 11 | I5: 確認済 | J5: 未確認 | K5: https://www.city.miyako.iwate.jp/material/files/group/8/miyakositiikikoukyoukoutuukeikaku.pdf | L5: 宮古市環境基本計画（R7.3策定） | M5: R7〜R12 | N5: 12 | O5: 確認済 | P5: 策定済 | Q5: https://www.city.miyako.iwate.jp/material/files/group/14/kihonkeikaku.pdf | R5: 交通：2023〜2029年度の7年計画。利便増進実施計画あり https://www.city.miyako.iwate.jp/material/files/group/8/miyakosiribennzousinnjissikeikaku.pdf 。三陸鉄道沿線の広域計画 https://www.city.miyako.iwate.jp/material/files/group/8/sanntetsukoutuukeikaku2024.pdf もあり。環境：前計画R2〜R6、R7.3に新計画策定（R7〜R12）。 三陸鉄道沿線地域等公共交通計画の策定ページ https://www.city.miyako.iwate.jp/gyosei/soshiki/kokyokotsuusuishin/2/1/605.html 。 | S5: 調査済 | T5: 掲載（広域：三陸鉄道沿線地域等）
A6: 3 | B6: 大船渡市 | C6: =IF(OR(D6="◎",E6="◎"),"◎ 営業",IF(OR(D6="△",E6="△"),"△ 着手済・要確認",IF(OR(D6="？",E6="？"),"？ 期間要確認","✕ 対象外"))) | D6: =IF(J6="計画なし","－",IF(J6="策定済","✕",IF(H6="","？",IF(AND(H6>=TGT_MIN,H6<=TGT_MAX),IF(J6="着手済","△","◎"),"✕")))) | E6: =IF(P6="計画なし","－",IF(P6="策定済","✕",IF(N6="","？",IF(AND(N6>=TGT_MIN,N6<=TGT_MAX),IF(P6="着手済","△","◎"),"✕")))) | F6: 大船渡市地域公共交通計画 | G6: R8〜R12 | H6: 12 | I6: 確認済 | J6: 策定済 | K6: https://www.city.ofunato.iwate.jp/archive/contents-5125 | L6: 第3次大船渡市環境基本計画 | M6: R5〜R14 | N6: 14 | O6: 確認済 | P6: 未確認 | Q6: https://www.city.ofunato.iwate.jp/site/kankyokeikaku/ | R6: 交通：旧計画R4〜R7（R6.9第一次改定 https://www.city.ofunato.iwate.jp/uploads/contents/archive_0000000476_00/38921.pdf ）の後継として、計画ページ上の期間はR8〜R12（検索結果本文）。R8.7に持続可能な鉄道接続型地域交通モデル調査業務プロポーザル https://www.city.ofunato.iwate.jp/archive/p20260721171526 。三陸鉄道沿線地域等公共交通計画（岩手県・沿線12市町村の広域計画、2024策定） https://www.city.miyako.iwate.jp/gyosei/soshiki/kokyokotsuusuishin/2/1/605.html もカバー。環境：R5年度から10年間（パブコメR5.1）。 | S6: 調査済 | T6: 掲載（広域：三陸鉄道沿線地域等）
A7: 4 | B7: 花巻市 | C7: =IF(OR(D7="◎",E7="◎"),"◎ 営業",IF(OR(D7="△",E7="△"),"△ 着手済・要確認",IF(OR(D7="？",E7="？"),"？ 期間要確認","✕ 対象外"))) | D7: =IF(J7="計画なし","－",IF(J7="策定済","✕",IF(H7="","？",IF(AND(H7>=TGT_MIN,H7<=TGT_MAX),IF(J7="着手済","△","◎"),"✕")))) | E7: =IF(P7="計画なし","－",IF(P7="策定済","✕",IF(N7="","？",IF(AND(N7>=TGT_MIN,N7<=TGT_MAX),IF(P7="着手済","△","◎"),"✕")))) | F7: 花巻市地域公共交通計画 | G7: R6〜R10 | H7: 10 | I7: 確認済 | J7: 未確認 | K7: https://www.city.hanamaki.iwate.jp/_res/projects/default_project/_page_/001/021/245/keikaku.pdf | L7: 第3次花巻市環境基本計画 | M7: R6〜R13 | N7: 13 | O7: 確認済 | P7: 未確認 | Q7: https://www.city.hanamaki.iwate.jp/shisei/shisei/keikaku/1002782.html | R7: 交通：R6.3策定、R6〜R10の5年。環境：第2次（H28.3〜R6.3満了）の後継としてR6.3に第3次策定（R6〜R13の8年）、区域施策編を別冊で同時策定。 | S7: 調査済 | T7: 掲載
A8: 5 | B8: 北上市 | C8: =IF(OR(D8="◎",E8="◎"),"◎ 営業",IF(OR(D8="△",E8="△"),"△ 着手済・要確認",IF(OR(D8="？",E8="？"),"？ 期間要確認","✕ 対象外"))) | D8: =IF(J8="計画なし","－",IF(J8="策定済","✕",IF(H8="","？",IF(AND(H8>=TGT_MIN,H8<=TGT_MAX),IF(J8="着手済","△","◎"),"✕")))) | E8: =IF(P8="計画なし","－",IF(P8="策定済","✕",IF(N8="","？",IF(AND(N8>=TGT_MIN,N8<=TGT_MAX),IF(P8="着手済","△","◎"),"✕")))) | F8: 北上市地域公共交通計画2026-2030 | G8: R8〜R12 | H8: 12 | I8: 確認済 | J8: 策定済 | K8: https://www.city.kitakami.iwate.jp/life/soshikikarasagasu/toshisaiseisuishin/koutsuuseisaku/1_1/21919.html | L8: 北上市環境基本計画（第三次、R8.3改定） | M8: R3〜R12 | N8: 12 | O8: 確認済 | P8: 未確認 | Q8: https://www.city.kitakami.iwate.jp/material/files/group/14/kankyokeikaku_0803.pdf | R8: 交通：R8〜R12の新計画を策定（案 R8.3.13会議資料 https://www.city.kitakami.iwate.jp/material/files/group/56/260313_siryou.pdf ）。環境：第三次R3〜R12、R8.3中間改定（区域施策編も改定）。 | S8: 調査済 | T8: 掲載
A9: 6 | B9: 久慈市 | C9: =IF(OR(D9="◎",E9="◎"),"◎ 営業",IF(OR(D9="△",E9="△"),"△ 着手済・要確認",IF(OR(D9="？",E9="？"),"？ 期間要確認","✕ 対象外"))) | D9: =IF(J9="計画なし","－",IF(J9="策定済","✕",IF(H9="","？",IF(AND(H9>=TGT_MIN,H9<=TGT_MAX),IF(J9="着手済","△","◎"),"✕")))) | E9: =IF(P9="計画なし","－",IF(P9="策定済","✕",IF(N9="","？",IF(AND(N9>=TGT_MIN,N9<=TGT_MAX),IF(P9="着手済","△","◎"),"✕")))) | F9: 久慈市地域公共交通計画（R6.3策定） | G9: H30〜R9 | H9: 9 | I9: 推定 | J9: 未確認 | K9: https://www.city.kuji.lg.jp/material/files/group/19/keikaku.pdf | L9: 第2次久慈市環境基本計画 | M9: H30〜R9 | N9: 9 | O9: 確認済 | P9: 未確認 | Q9: https://www.city.kuji.lg.jp/material/files/group/19/2021_kuji_kankyou_1.pdf | R9: 交通：網形成計画（H30〜）をR6.3に地域公共交通計画として策定、計画期間は2018〜2027年度（R9終期）とする検索結果が1回のみで、2026.10の再検索では裏付けが得られず推定、2028年度以降に見直し予定。計画ページ https://www.city.kuji.lg.jp/soshiki/chiikizukurishinko/1/6/1/1835.html 。次期計画の委託等は未確認。三陸鉄道沿線地域等公共交通計画（岩手県・沿線12市町村の広域計画、2024策定） https://www.city.miyako.iwate.jp/gyosei/soshiki/kokyokotsuusuishin/2/1/605.html もカバー。環境：10年計画（R10以降に見直しとの記載あり）、正確な期間未確認。区域施策編改訂支援業務プロポーザルあり https://www.city.kuji.iwate.jp/assets/fukushi/siyousyo_ondankapropo.pdf 。 【ファクトチェック 2026-10-01: 確認できず】確認期間: None／次期: 確認できず／根拠: https://www.city.kuji.lg.jp/soshiki/chiikizukurishinko/1/6/1/1835.html 【追加調査 2026-10】【2026-10-02調査】検索3回で計画ページ https://www.city.kuji.lg.jp/soshiki/chiikizukurishinko/1/6/1/1835.html は確認できたが、計画期間（H30〜R9=2018〜2027年度）を示す本文抜粋は得られず推定のまま。市サイトはWebFetch不可（egress blocked）。次期計画の委託等も検索で見当たらず。 【追加調査 2026-10】環境：市サイト限定検索2回で『第1章 計画の基本的事項』(2021_kuji_kankyou_1.pdf)の本文として「2018年度から2027年度までの10年間」を確認（PDF直接取得は不可）。前回メモの『R10以降に見直し』と整合。R9終期のため次期（第3次）計画の策定委託・審議会・パブコメを検索したが見当たらず（着手未確認）。確認日2026-10-02。 根拠: 計画の期間は…2018年度から2027年度までの10年間とします | S9: 調査済 | T9: 掲載（広域：三陸鉄道沿線地域等）
A10: 7 | B10: 遠野市 | C10: =IF(OR(D10="◎",E10="◎"),"◎ 営業",IF(OR(D10="△",E10="△"),"△ 着手済・要確認",IF(OR(D10="？",E10="？"),"？ 期間要確認","✕ 対象外"))) | D10: =IF(J10="計画なし","－",IF(J10="策定済","✕",IF(H10="","？",IF(AND(H10>=TGT_MIN,H10<=TGT_MAX),IF(J10="着手済","△","◎"),"✕")))) | E10: =IF(P10="計画なし","－",IF(P10="策定済","✕",IF(N10="","？",IF(AND(N10>=TGT_MIN,N10<=TGT_MAX),IF(P10="着手済","△","◎"),"✕")))) | F10: 遠野市地域公共交通計画 | G10: R7〜R12 | H10: 12 | I10: 確認済 | J10: 策定済 | K10: https://www.city.tono.iwate.jp/index.cfm/50,13281,311,html | L10: 第5次遠野市環境基本計画 | M10: R8〜R12 | N10: 12 | O10: 確認済 | P10: 策定済 | Q10: https://www.city.tono.iwate.jp/index.cfm/45,34797,247,html | R10: 交通：R7〜R12（R7年度開始の新計画）。環境：第5次計画を公開、期間は検索結果で未確認。 【追加調査 2026-10】環境：市サイト限定検索2回（別クエリ）で環境基本計画ページの本文として「第５次遠野市環境基本計画の期間は令和8年から令和12年度まで」を確認。R8開始の新計画（第3次遠野市総合計画R8〜R17と同時期）のため策定済と判断（策定月・パブコメは未確認）。市サイトはWebFetchブロック。確認日2026-10-02。URL https://www.city.tono.iwate.jp/index.cfm/45,34797,247,html 根拠: 第５次遠野市環境基本計画…令和8年から令和12年度まで | S10: 調査済 | T10: 掲載
A11: 8 | B11: 一関市 | C11: =IF(OR(D11="◎",E11="◎"),"◎ 営業",IF(OR(D11="△",E11="△"),"△ 着手済・要確認",IF(OR(D11="？",E11="？"),"？ 期間要確認","✕ 対象外"))) | D11: =IF(J11="計画なし","－",IF(J11="策定済","✕",IF(H11="","？",IF(AND(H11>=TGT_MIN,H11<=TGT_MAX),IF(J11="着手済","△","◎"),"✕")))) | E11: =IF(P11="計画なし","－",IF(P11="策定済","✕",IF(N11="","？",IF(AND(N11>=TGT_MIN,N11<=TGT_MAX),IF(P11="着手済","△","◎"),"✕")))) | F11: 一関市地域公共交通計画 | G11: R6〜R10 | H11: 10 | I11: 確認済 | J11: 未確認 | K11: https://www.city.ichinoseki.iwate.jp/index.cfm/7,166695,c,html/166695/20240410-160623.pdf | L11: 一関市環境基本計画（R3.3改定） | M11: H29〜R8 | N11: 8 | O11: 確認済 | P11: 未確認 | Q11: https://www.city.ichinoseki.iwate.jp/index.cfm/7,90284,125,html | R11: 交通：R6〜R10、一部改訂あり https://www.city.ichinoseki.iwate.jp/index.cfm/7,175828,125,html 。環境：H29〜R8の10年計画でR8年度終期。次期計画の策定作業（委託・パブコメ）は検索で確認できず。要注視。 | S11: 調査済 | T11: 掲載
A12: 9 | B12: 陸前高田市 | C12: =IF(OR(D12="◎",E12="◎"),"◎ 営業",IF(OR(D12="△",E12="△"),"△ 着手済・要確認",IF(OR(D12="？",E12="？"),"？ 期間要確認","✕ 対象外"))) | D12: =IF(J12="計画なし","－",IF(J12="策定済","✕",IF(H12="","？",IF(AND(H12>=TGT_MIN,H12<=TGT_MAX),IF(J12="着手済","△","◎"),"✕")))) | E12: =IF(P12="計画なし","－",IF(P12="策定済","✕",IF(N12="","？",IF(AND(N12>=TGT_MIN,N12<=TGT_MAX),IF(P12="着手済","△","◎"),"✕")))) | F12: 陸前高田市地域公共交通計画 | G12: R6〜R10 | H12: 10 | I12: 確認済 | J12: 未確認 | K12: https://www.city.rikuzentakata.iwate.jp/material/files/group/19/20231124_4-2.pdf | M12: 不明 | O12: 不明 | P12: 計画なし | R12: 交通：2024〜2028年度の5年。計画ページ https://www.city.rikuzentakata.iwate.jp/soshiki/machizukurisuishinka/seikatsukankyokakari/3/8100.html 。環境：環境基本計画は検索で確認できず（まちづくり総合計画・SDGs未来都市計画で代替か）。 | S12: 調査済 | T12: 掲載（広域：三陸鉄道沿線地域等）
A13: 10 | B13: 釜石市 | C13: =IF(OR(D13="◎",E13="◎"),"◎ 営業",IF(OR(D13="△",E13="△"),"△ 着手済・要確認",IF(OR(D13="？",E13="？"),"？ 期間要確認","✕ 対象外"))) | D13: =IF(J13="計画なし","－",IF(J13="策定済","✕",IF(H13="","？",IF(AND(H13>=TGT_MIN,H13<=TGT_MAX),IF(J13="着手済","△","◎"),"✕")))) | E13: =IF(P13="計画なし","－",IF(P13="策定済","✕",IF(N13="","？",IF(AND(N13>=TGT_MIN,N13<=TGT_MAX),IF(P13="着手済","△","◎"),"✕")))) | F13: 釜石市地域公共交通計画（R6.1一部改訂） | G13: R3〜R7 | H13: 7 | I13: 確認済 | J13: 未確認 | K13: https://www.city.kamaishi.iwate.jp/docs/2021040500020/file_contents/001.pdf | L13: 第二次釜石市環境基本計画 | M13: R5〜R12 | N13: 12 | O13: 確認済 | P13: 未確認 | Q13: https://www.city.kamaishi.iwate.jp/docs/2023110200014/ | R13: 交通：R3〜R7で終期経過。R8.2施政方針でも現計画に基づく取組を記載、次期計画の策定・延長は検索で確認できず。環境：2023〜2030の8年、中間見直し予定。 | S13: 調査済 | T13: 掲載（広域：三陸鉄道沿線地域等）
A14: 11 | B14: 二戸市 | C14: =IF(OR(D14="◎",E14="◎"),"◎ 営業",IF(OR(D14="△",E14="△"),"△ 着手済・要確認",IF(OR(D14="？",E14="？"),"？ 期間要確認","✕ 対象外"))) | D14: =IF(J14="計画なし","－",IF(J14="策定済","✕",IF(H14="","？",IF(AND(H14>=TGT_MIN,H14<=TGT_MAX),IF(J14="着手済","△","◎"),"✕")))) | E14: =IF(P14="計画なし","－",IF(P14="策定済","✕",IF(N14="","？",IF(AND(N14>=TGT_MIN,N14<=TGT_MAX),IF(P14="着手済","△","◎"),"✕")))) | F14: 二戸市地域公共交通計画 | G14: 不明 | I14: 不明 | J14: 未確認 | K14: https://www.city.ninohe.lg.jp/info/2661 | M14: 不明 | O14: 不明 | P14: 計画なし | R14: 交通：計画ページ（2021.6.30掲載）あり、期間は検索結果で確認できず（R3策定なら5年でR7終期の可能性）。環境：環境基本計画は検索で確認できず。 | S14: 調査済 | T14: 掲載
A15: 12 | B15: 八幡平市 | C15: =IF(OR(D15="◎",E15="◎"),"◎ 営業",IF(OR(D15="△",E15="△"),"△ 着手済・要確認",IF(OR(D15="？",E15="？"),"？ 期間要確認","✕ 対象外"))) | D15: =IF(J15="計画なし","－",IF(J15="策定済","✕",IF(H15="","？",IF(AND(H15>=TGT_MIN,H15<=TGT_MAX),IF(J15="着手済","△","◎"),"✕")))) | E15: =IF(P15="計画なし","－",IF(P15="策定済","✕",IF(N15="","？",IF(AND(N15>=TGT_MIN,N15<=TGT_MAX),IF(P15="着手済","△","◎"),"✕")))) | F15: 八幡平市地域公共交通計画 | G15: R6〜R12 | H15: 12 | I15: 確認済 | J15: 未確認 | K15: https://www.city.hachimantai.lg.jp/soshiki/machi/1517.html | L15: 第2次八幡平市環境基本計画 | M15: R4〜R13 | N15: 13 | O15: 確認済 | P15: 未確認 | Q15: https://www.city.hachimantai.lg.jp/uploaded/attachment/13185.pdf | R15: 交通：2024年3月策定、R6〜R12の7年。環境：R4.7策定、R4〜R13、区域施策編を内包。e_urlは案段階PDF。 | S15: 調査済 | T15: 掲載
A16: 13 | B16: 奥州市 | C16: =IF(OR(D16="◎",E16="◎"),"◎ 営業",IF(OR(D16="△",E16="△"),"△ 着手済・要確認",IF(OR(D16="？",E16="？"),"？ 期間要確認","✕ 対象外"))) | D16: =IF(J16="計画なし","－",IF(J16="策定済","✕",IF(H16="","？",IF(AND(H16>=TGT_MIN,H16<=TGT_MAX),IF(J16="着手済","△","◎"),"✕")))) | E16: =IF(P16="計画なし","－",IF(P16="策定済","✕",IF(N16="","？",IF(AND(N16>=TGT_MIN,N16<=TGT_MAX),IF(P16="着手済","△","◎"),"✕")))) | F16: 奥州市地域公共交通計画（第4次奥州市バス交通計画） | G16: R6〜R10 | H16: 10 | I16: 確認済 | J16: 未確認 | K16: https://www.city.oshu.iwate.jp/soshiki/2/1004/12523.html | L16: 第2次奥州市環境基本計画（R4.3改定） | M16: H29〜R8 | N16: 8 | O16: 確認済 | P16: 着手済 | Q16: https://www.city.oshu.iwate.jp/material/files/group/183/dai2jikankyoukihonnkeikaku_GX.pdf | R16: 交通：R6.3策定、変更あり https://www.city.oshu.iwate.jp/soshiki/2/1004/17684.html 。R6〜R10（県計画との整合）。県利便増進実施計画（奥州市版）R8.2 https://www.city.oshu.iwate.jp/soshiki/2/1004/17721.html 。環境：R8年度終期。R7年度に基礎調査委託、R8年度素案策定、R9.4から第3次計画（区域施策編含む）開始予定（市議会建設環境常任委員会R6.10.8会議録 https://www.city.oshu.iwate.jp/material/files/group/76/202410080000001.pdf ）。 | S16: 調査済 | T16: 掲載
A17: 14 | B17: 滝沢市 | C17: =IF(OR(D17="◎",E17="◎"),"◎ 営業",IF(OR(D17="△",E17="△"),"△ 着手済・要確認",IF(OR(D17="？",E17="？"),"？ 期間要確認","✕ 対象外"))) | D17: =IF(J17="計画なし","－",IF(J17="策定済","✕",IF(H17="","？",IF(AND(H17>=TGT_MIN,H17<=TGT_MAX),IF(J17="着手済","△","◎"),"✕")))) | E17: =IF(P17="計画なし","－",IF(P17="策定済","✕",IF(N17="","？",IF(AND(N17>=TGT_MIN,N17<=TGT_MAX),IF(P17="着手済","△","◎"),"✕")))) | F17: 盛岡都市圏地域公共交通計画（盛岡市・滝沢市・矢巾町共同） | G17: R8〜R12 | H17: 12 | I17: 確認済 | J17: 策定済 | K17: https://www.city.morioka.iwate.jp/_res/projects/default_project/_page_/001/043/162/R7honpen.pdf | L17: 第1次滝沢市環境基本計画 | M17: R5〜R12 | N17: 12 | O17: 確認済 | P17: 未確認 | Q17: https://www.city.takizawa.iwate.jp/kurashi/kankyo/contents-12768/p20241204162009 | R17: 交通：3市町共同の都市圏計画（R7.9公表）。滝沢市側資料 https://www.city.takizawa.iwate.jp/uploads/contents/pages_0000002369_00/【資料3】次期地域公共交通計画の検討状況及び現行計画の変更等について.pdf 。環境：R5.3策定、R5〜R12の8年。 | S17: 調査済 | T17: 掲載（広域：盛岡市・滝沢市・矢巾町）
A18: 15 | B18: 雫石町 | C18: =IF(OR(D18="◎",E18="◎"),"◎ 営業",IF(OR(D18="△",E18="△"),"△ 着手済・要確認",IF(OR(D18="？",E18="？"),"？ 期間要確認","✕ 対象外"))) | D18: =IF(J18="計画なし","－",IF(J18="策定済","✕",IF(H18="","？",IF(AND(H18>=TGT_MIN,H18<=TGT_MAX),IF(J18="着手済","△","◎"),"✕")))) | E18: =IF(P18="計画なし","－",IF(P18="策定済","✕",IF(N18="","？",IF(AND(N18>=TGT_MIN,N18<=TGT_MAX),IF(P18="着手済","△","◎"),"✕")))) | F18: 第2次雫石町地域公共交通計画 | G18: R7〜R11 | H18: 11 | I18: 確認済 | J18: 策定済 | K18: https://www.town.shizukuishi.iwate.jp/docs/2021101200012/file_contents/honpen.pdf | L18: 第二期雫石町環境基本計画 | M18: R3〜R10 | N18: 10 | O18: 確認済 | P18: 未確認 | Q18: https://www.town.shizukuishi.iwate.jp/docs/2016050600013/file_contents/kankyoukihonkeikaku.pdf | R18: 交通：第1次R3.5〜R6.3、第2次（R7〜R11）はパブコメR7.3.17締切で策定 https://www.town.shizukuishi.iwate.jp/docs/2025021300036/ 。環境：R3.5策定、終期は検索で未確認（10年ならR12）。 【追加調査 2026-10】環境：第二期雫石町環境基本計画（R3.5策定）、計画期間R3〜R10（2021〜2028年度、8年間）。町サイト限定検索2回の取得本文で一致して確認。中間見直し規定あり。終期R10のため次期計画の着手状況は未調査。確認日2026-10-02。URL: https://www.town.shizukuishi.iwate.jp/docs/2016050600013/file_contents/kankyoukihonkeikaku.pdf 根拠: 計画期間は2021年度（令和3年度）から2028年度（令和10年度）までの8年間（検索取得本文の要約） | S18: 調査済 | T18: 掲載
A19: 16 | B19: 葛巻町 | C19: =IF(OR(D19="◎",E19="◎"),"◎ 営業",IF(OR(D19="△",E19="△"),"△ 着手済・要確認",IF(OR(D19="？",E19="？"),"？ 期間要確認","✕ 対象外"))) | D19: =IF(J19="計画なし","－",IF(J19="策定済","✕",IF(H19="","？",IF(AND(H19>=TGT_MIN,H19<=TGT_MAX),IF(J19="着手済","△","◎"),"✕")))) | E19: =IF(P19="計画なし","－",IF(P19="策定済","✕",IF(N19="","？",IF(AND(N19>=TGT_MIN,N19<=TGT_MAX),IF(P19="着手済","△","◎"),"✕")))) | G19: 不明 | I19: 不明 | J19: 計画なし | M19: 不明 | O19: 不明 | P19: 計画なし | R19: 交通・環境とも町サイト検索で計画を確認できず（公共交通マップのみ https://www.town.kuzumaki.iwate.jp/docs/2015102200249/ ）。県の地域公共交通計画でカバーされる可能性。 | S19: 環境のみ調査 | T19: 未掲載
A20: 17 | B20: 岩手町 | C20: =IF(OR(D20="◎",E20="◎"),"◎ 営業",IF(OR(D20="△",E20="△"),"△ 着手済・要確認",IF(OR(D20="？",E20="？"),"？ 期間要確認","✕ 対象外"))) | D20: =IF(J20="計画なし","－",IF(J20="策定済","✕",IF(H20="","？",IF(AND(H20>=TGT_MIN,H20<=TGT_MAX),IF(J20="着手済","△","◎"),"✕")))) | E20: =IF(P20="計画なし","－",IF(P20="策定済","✕",IF(N20="","？",IF(AND(N20>=TGT_MIN,N20<=TGT_MAX),IF(P20="着手済","△","◎"),"✕")))) | F20: 岩手町地域公共交通計画 | G20: R4〜R8 | H20: 8 | I20: 確認済 | J20: 未確認 | K20: https://town.iwate.iwate.jp/town/gyosei/koutsuumoukeisei2017-2021/ | M20: 不明 | O20: 不明 | P20: 計画なし | R20: 交通：R4.4策定、2022〜2026年度でR8終期。県協議会資料に「令和8年度から令和12年度」との記載があり https://www.pref.iwate.jp/_res/projects/default_project/_page_/001/032/597/1127siryou5.pdf 、次期計画との関係は要確認。環境：環境基本計画は確認できず（SDGs未来都市計画あり）。 | S20: 調査済 | T20: 掲載
A21: 18 | B21: 紫波町 | C21: =IF(OR(D21="◎",E21="◎"),"◎ 営業",IF(OR(D21="△",E21="△"),"△ 着手済・要確認",IF(OR(D21="？",E21="？"),"？ 期間要確認","✕ 対象外"))) | D21: =IF(J21="計画なし","－",IF(J21="策定済","✕",IF(H21="","？",IF(AND(H21>=TGT_MIN,H21<=TGT_MAX),IF(J21="着手済","△","◎"),"✕")))) | E21: =IF(P21="計画なし","－",IF(P21="策定済","✕",IF(N21="","？",IF(AND(N21>=TGT_MIN,N21<=TGT_MAX),IF(P21="着手済","△","◎"),"✕")))) | F21: 紫波町地域公共交通計画 | G21: R6〜R10 | H21: 10 | I21: 確認済 | J21: 未確認 | K21: https://www.town.shiwa.iwate.jp/shiwatown/cms/soshiki/4/2_99/koukyoukoutsukeikaku.pdf | L21: 紫波2100 2026環境・循環基本計画（2021環境・循環基本計画の中間見直し版） | M21: R8〜R12 | N21: 12 | O21: 確認済 | P21: 策定済 | Q21: https://www.town.shiwa.iwate.jp/shiwatown/cms/soshiki/2_1/2_3/2026%E7%92%B0%E5%A2%83%E3%83%BB%E5%BE%AA%E7%92%B0%E5%9F%BA%E6%9C%AC%E8%A8%88%E7%94%BB%EF%BC%88%E6%9C%80%E7%B5%82%E8%AA%BF%E6%95%B4%EF%BC%89_20260316_%E7%A2%BA%E5%AE%9A.pdf | R21: 交通：R6.3策定、R6〜R10。環境：環境・循環基本計画（2021年関連）の存在は示唆されるが期間・URLは確認できず。 【追加調査 2026-10】環境：2021環境・循環基本計画（R3.3策定、R3〜R12）の中間見直しとして2026版を策定。意見公募R7.11.14〜R7.12.3（https://www.town.shiwa.iwate.jp/soshiki/2_1/2_3/173492829222563-2/ ）、確定版PDF（20260316確定）。計画期間R8〜R12（5年間）。計画一覧 https://www.town.shiwa.iwate.jp/soshiki/2_1/2_3/452.html/ に2011版(H23〜R2)・2016版・2021版(R3〜R12)・2026版(R8〜R12)。確認日2026-10-02。 根拠: 計画期間は5年間とし、令和8（2026）年度を初年度、令和12（2030）年度を目標年度とします（意見公募ページ取得本文の要約） | S21: 調査済 | T21: 掲載
A22: 19 | B22: 矢巾町 | C22: =IF(OR(D22="◎",E22="◎"),"◎ 営業",IF(OR(D22="△",E22="△"),"△ 着手済・要確認",IF(OR(D22="？",E22="？"),"？ 期間要確認","✕ 対象外"))) | D22: =IF(J22="計画なし","－",IF(J22="策定済","✕",IF(H22="","？",IF(AND(H22>=TGT_MIN,H22<=TGT_MAX),IF(J22="着手済","△","◎"),"✕")))) | E22: =IF(P22="計画なし","－",IF(P22="策定済","✕",IF(N22="","？",IF(AND(N22>=TGT_MIN,N22<=TGT_MAX),IF(P22="着手済","△","◎"),"✕")))) | F22: 盛岡都市圏地域公共交通計画（盛岡市・滝沢市・矢巾町共同） | G22: R8〜R12 | H22: 12 | I22: 確認済 | J22: 策定済 | K22: https://www.city.morioka.iwate.jp/_res/projects/default_project/_page_/001/043/162/R7honpen.pdf | M22: 不明 | O22: 不明 | P22: 計画なし | R22: 交通：3市町共同の都市圏計画（R7.9公表）。環境：環境基本計画は確認できず（人と自然にやさしい環境基本条例、新エネルギービジョンR3改訂版 https://www.town.yahaba.iwate.jp/yahabatown/switch/2022/2022060800015/yahaba_newenergyvision.pdf ）。 | S22: 調査済 | T22: 掲載（広域：盛岡市・滝沢市・矢巾町）
A23: 20 | B23: 西和賀町 | C23: =IF(OR(D23="◎",E23="◎"),"◎ 営業",IF(OR(D23="△",E23="△"),"△ 着手済・要確認",IF(OR(D23="？",E23="？"),"？ 期間要確認","✕ 対象外"))) | D23: =IF(J23="計画なし","－",IF(J23="策定済","✕",IF(H23="","？",IF(AND(H23>=TGT_MIN,H23<=TGT_MAX),IF(J23="着手済","△","◎"),"✕")))) | E23: =IF(P23="計画なし","－",IF(P23="策定済","✕",IF(N23="","？",IF(AND(N23>=TGT_MIN,N23<=TGT_MAX),IF(P23="着手済","△","◎"),"✕")))) | F23: 西和賀町地域公共交通計画 | G23: R5〜（終期不明） | I23: 不明 | J23: 未確認 | K23: https://www.town.nishiwaga.lg.jp/material/files/group/1/2306nishiwagakotsukeikaku.pdf | M23: 不明 | O23: 不明 | P23: 計画なし | R23: 交通：R5.6策定、R7.1.24協議会で一部改正。期間は検索結果で未確認（5年ならR5〜R9の可能性、要確認）。環境：環境基本計画は確認できず。 | S23: 調査済 | T23: 掲載
A24: 21 | B24: 金ケ崎町 | C24: =IF(OR(D24="◎",E24="◎"),"◎ 営業",IF(OR(D24="△",E24="△"),"△ 着手済・要確認",IF(OR(D24="？",E24="？"),"？ 期間要確認","✕ 対象外"))) | D24: =IF(J24="計画なし","－",IF(J24="策定済","✕",IF(H24="","？",IF(AND(H24>=TGT_MIN,H24<=TGT_MAX),IF(J24="着手済","△","◎"),"✕")))) | E24: =IF(P24="計画なし","－",IF(P24="策定済","✕",IF(N24="","？",IF(AND(N24>=TGT_MIN,N24<=TGT_MAX),IF(P24="着手済","△","◎"),"✕")))) | F24: 金ケ崎町地域公共交通網形成計画 | G24: R2〜R8 | H24: 8 | I24: 確認済 | J24: 未確認 | K24: https://www.town.kanegasaki.iwate.jp/articles/2020032900015/file_contents/keikaku.pdf | M24: 不明 | O24: 不明 | P24: 計画なし | R24: 交通：網形成計画R2〜R8の7年でR8終期、次期計画の委託等は検索で確認できず。環境：環境基本計画は確認できず。代替として地球温暖化対策実行計画（区域施策編）R7〜R12（R6.12策定） https://www.town.kanegasaki.iwate.jp/articles/2025012900047/file_contents/kuikisisakuhen.pdf 。 | S24: 調査済 | T24: 掲載
A25: 22 | B25: 平泉町 | C25: =IF(OR(D25="◎",E25="◎"),"◎ 営業",IF(OR(D25="△",E25="△"),"△ 着手済・要確認",IF(OR(D25="？",E25="？"),"？ 期間要確認","✕ 対象外"))) | D25: =IF(J25="計画なし","－",IF(J25="策定済","✕",IF(H25="","？",IF(AND(H25>=TGT_MIN,H25<=TGT_MAX),IF(J25="着手済","△","◎"),"✕")))) | E25: =IF(P25="計画なし","－",IF(P25="策定済","✕",IF(N25="","？",IF(AND(N25>=TGT_MIN,N25<=TGT_MAX),IF(P25="着手済","△","◎"),"✕")))) | F25: 平泉町地域公共交通計画 | G25: R7〜R11 | H25: 11 | I25: 確認済 | J25: 策定済 | K25: https://www.town.hiraizumi.iwate.jp/%E5%B9%B3%E6%B3%89%E7%94%BA%E5%9C%B0%E5%9F%9F%E5%85%AC%E5%85%B1%E4%BA%A4%E9%80%9A%E8%A8%88%E7%94%BB%E3%82%92%E7%AD%96%E5%AE%9A%E3%81%97%E3%81%BE%E3%81%97%E3%81%9F-25574/ | M25: 不明 | O25: 不明 | P25: 計画なし | R25: 交通：R6年度策定支援業務プロポーザルを経てR7年度から5年の計画を策定。環境：環境基本計画は確認できず。 | S25: 調査済 | T25: 掲載
A26: 23 | B26: 住田町 | C26: =IF(OR(D26="◎",E26="◎"),"◎ 営業",IF(OR(D26="△",E26="△"),"△ 着手済・要確認",IF(OR(D26="？",E26="？"),"？ 期間要確認","✕ 対象外"))) | D26: =IF(J26="計画なし","－",IF(J26="策定済","✕",IF(H26="","？",IF(AND(H26>=TGT_MIN,H26<=TGT_MAX),IF(J26="着手済","△","◎"),"✕")))) | E26: =IF(P26="計画なし","－",IF(P26="策定済","✕",IF(N26="","？",IF(AND(N26>=TGT_MIN,N26<=TGT_MAX),IF(P26="着手済","△","◎"),"✕")))) | F26: 住田町地域公共交通計画 | G26: R7〜R11 | H26: 11 | I26: 確認済 | J26: 策定済 | K26: https://www.town.sumita.iwate.jp/docs/2025040400014/files/tiikikoukyoukoutuukeikaku2025.pdf | L26: 第5次住田町環境基本計画 | M26: R4〜R8 | N26: 8 | O26: 推定 | P26: 未確認 | Q26: https://www.town.sumita.iwate.jp/docs/2023061500010/files/04_dai4syou.pdf | R26: 交通：2025〜2029年度。環境：R5.6策定、期間は未確認。区域施策編策定支援業務（R7.5）あり https://www.town.sumita.iwate.jp/docs/2025052000011/files/shinsakijun.pdf 。 【追加調査 2026-10】環境：第5次住田町環境基本計画、町の計画・方針一覧（https://www.town.sumita.iwate.jp/docs/2016050600013/ ）の検索要約で『R5.3策定、計画期間R4〜R8』と3回一致して出たが原文スニペットは未取得。計画書公開はR5.6（docs/2023061500010）で、策定時期と始期の整合に疑問が残るため推定（R5〜R9の可能性も残る）。5年計画。次期（第6次）計画の策定業務委託・審議会・パブコメは町サイト検索で見当たらず（未着手か未公表）。関連：地球温暖化対策実行計画（区域施策編）作成支援業務プロポーザルR7.5 https://www.town.sumita.iwate.jp/docs/2025052000011/ 。町HPへの直接取得はプロキシでブロック。確認日2026-10-02。 | S26: 調査済 | T26: 掲載
A27: 24 | B27: 大槌町 | C27: =IF(OR(D27="◎",E27="◎"),"◎ 営業",IF(OR(D27="△",E27="△"),"△ 着手済・要確認",IF(OR(D27="？",E27="？"),"？ 期間要確認","✕ 対象外"))) | D27: =IF(J27="計画なし","－",IF(J27="策定済","✕",IF(H27="","？",IF(AND(H27>=TGT_MIN,H27<=TGT_MAX),IF(J27="着手済","△","◎"),"✕")))) | E27: =IF(P27="計画なし","－",IF(P27="策定済","✕",IF(N27="","？",IF(AND(N27>=TGT_MIN,N27<=TGT_MAX),IF(P27="着手済","△","◎"),"✕")))) | F27: 大槌町地域公共交通計画 | G27: R4〜R8 | H27: 8 | I27: 確認済 | J27: 着手済 | K27: https://www.town.otsuchi.iwate.jp/fs/2/3/0/5/0/9/_/___________.pdf | M27: 不明 | O27: 不明 | P27: 計画なし | R27: 交通：R4〜R8でR8終期、R7.3変更 https://www.town.otsuchi.iwate.jp/gyosei/docs/453169.html 。次期計画の策定支援業務委託の見積合わせを実施（提出期限R8.6.5） https://www.town.otsuchi.iwate.jp/gyosei/docs/462503.html 。三陸鉄道沿線地域等公共交通計画（岩手県・沿線12市町村の広域計画、2024策定） https://www.city.miyako.iwate.jp/gyosei/soshiki/kokyokotsuusuishin/2/1/605.html もカバー。環境：環境基本計画は確認できず。 | S27: 調査済 | T27: 掲載（広域：三陸鉄道沿線地域等）
A28: 25 | B28: 山田町 | C28: =IF(OR(D28="◎",E28="◎"),"◎ 営業",IF(OR(D28="△",E28="△"),"△ 着手済・要確認",IF(OR(D28="？",E28="？"),"？ 期間要確認","✕ 対象外"))) | D28: =IF(J28="計画なし","－",IF(J28="策定済","✕",IF(H28="","？",IF(AND(H28>=TGT_MIN,H28<=TGT_MAX),IF(J28="着手済","△","◎"),"✕")))) | E28: =IF(P28="計画なし","－",IF(P28="策定済","✕",IF(N28="","？",IF(AND(N28>=TGT_MIN,N28<=TGT_MAX),IF(P28="着手済","△","◎"),"✕")))) | F28: 山田町地域公共交通計画 | G28: 不明 | I28: 不明 | J28: 未確認 | K28: https://www.town.yamada.iwate.jp/fs/1/2/1/7/4/5/_/___________.pdf | M28: 不明 | O28: 不明 | P28: 計画なし | R28: 交通：網形成計画（2019.3）の後継として策定、期間未確認。県利便増進実施計画（宮古市・山田町版）あり https://www.town.yamada.iwate.jp/docs/10513.html 。三陸鉄道沿線地域等公共交通計画（岩手県・沿線12市町村の広域計画、2024策定） https://www.city.miyako.iwate.jp/gyosei/soshiki/kokyokotsuusuishin/2/1/605.html もカバー。環境：確認できず。 | S28: 調査済 | T28: 掲載（広域：三陸鉄道沿線地域等）
A29: 26 | B29: 岩泉町 | C29: =IF(OR(D29="◎",E29="◎"),"◎ 営業",IF(OR(D29="△",E29="△"),"△ 着手済・要確認",IF(OR(D29="？",E29="？"),"？ 期間要確認","✕ 対象外"))) | D29: =IF(J29="計画なし","－",IF(J29="策定済","✕",IF(H29="","？",IF(AND(H29>=TGT_MIN,H29<=TGT_MAX),IF(J29="着手済","△","◎"),"✕")))) | E29: =IF(P29="計画なし","－",IF(P29="策定済","✕",IF(N29="","？",IF(AND(N29>=TGT_MIN,N29<=TGT_MAX),IF(P29="着手済","△","◎"),"✕")))) | F29: 岩泉町地域公共交通計画 | G29: R6〜R8 | H29: 8 | I29: 確認済 | J29: 未確認 | K29: https://www.town.iwaizumi.lg.jp/docs/2024032500015/ | M29: 不明 | O29: 不明 | P29: 計画なし | R29: 交通：R6〜R8の3年計画でR8終期、次期計画の委託等は検索で未確認。三陸鉄道沿線地域等公共交通計画（岩手県・沿線12市町村の広域計画、2024策定） https://www.city.miyako.iwate.jp/gyosei/soshiki/kokyokotsuusuishin/2/1/605.html もカバー。環境：環境基本計画は確認できず（R4.2ゼロカーボンシティ宣言）。 | S29: 調査済 | T29: 掲載（広域：三陸鉄道沿線地域等）
A30: 27 | B30: 田野畑村 | C30: =IF(OR(D30="◎",E30="◎"),"◎ 営業",IF(OR(D30="△",E30="△"),"△ 着手済・要確認",IF(OR(D30="？",E30="？"),"？ 期間要確認","✕ 対象外"))) | D30: =IF(J30="計画なし","－",IF(J30="策定済","✕",IF(H30="","？",IF(AND(H30>=TGT_MIN,H30<=TGT_MAX),IF(J30="着手済","△","◎"),"✕")))) | E30: =IF(P30="計画なし","－",IF(P30="策定済","✕",IF(N30="","？",IF(AND(N30>=TGT_MIN,N30<=TGT_MAX),IF(P30="着手済","△","◎"),"✕")))) | F30: 田野畑村地域公共交通計画 | G30: 不明 | I30: 不明 | J30: 未確認 | K30: https://www.vill.tanohata.iwate.jp/bunya/keikaku/tanohata/ | L30: 田野畑村環境基本計画 | M30: 不明 | O30: 不明 | P30: 未確認 | Q30: https://www.vill.tanohata.iwate.jp/docs/2015081800027/ | R30: 交通：R5.9.15公開、期間は検索で確認できず（5年ならR5〜R9の可能性）。三陸鉄道沿線地域等公共交通計画（岩手県・沿線12市町村の広域計画、2024策定） https://www.city.miyako.iwate.jp/gyosei/soshiki/kokyokotsuusuishin/2/1/605.html もカバー。環境：H16策定の計画ページあり、期間・改定状況不明。 【追加調査 2026-10】環境：村サイト限定検索で『田野畑村環境基本計画』ページ（https://www.vill.tanohata.iwate.jp/docs/2015081800027/ 、ページ更新2017-02-08）を確認。『環境の保全と創造に関する基本条例』に基づきH16.11策定と記載。計画期間・改定（第2次等）の記載は検索結果で確認できず、改定・次期策定の動きも見当たらない（H16策定のまま期間不明）。各種計画一覧 https://www.vill.tanohata.iwate.jp/bunya/keikaku/tanohata/ 。村HP直接取得はブロック。確認日2026-10-02。 | S30: 調査済 | T30: 掲載（広域：三陸鉄道沿線地域等）
A31: 28 | B31: 普代村 | C31: =IF(OR(D31="◎",E31="◎"),"◎ 営業",IF(OR(D31="△",E31="△"),"△ 着手済・要確認",IF(OR(D31="？",E31="？"),"？ 期間要確認","✕ 対象外"))) | D31: =IF(J31="計画なし","－",IF(J31="策定済","✕",IF(H31="","？",IF(AND(H31>=TGT_MIN,H31<=TGT_MAX),IF(J31="着手済","△","◎"),"✕")))) | E31: =IF(P31="計画なし","－",IF(P31="策定済","✕",IF(N31="","？",IF(AND(N31>=TGT_MIN,N31<=TGT_MAX),IF(P31="着手済","△","◎"),"✕")))) | F31: 三陸鉄道沿線地域等公共交通計画（岩手県・沿線市町村の広域計画） | G31: R6〜R10 | H31: 10 | I31: 確認済 | J31: 未確認 | K31: https://www.city.miyako.iwate.jp/material/files/group/8/sanntetsukoutuukeikaku2024.pdf | M31: 不明 | O31: 不明 | P31: 計画なし | R31: 交通：村独自の地域公共交通計画は確認できず（村営バス無料運行 https://www.vill.fudai.iwate.jp/lifescene/koutsu.html ）。三陸鉄道沿線地域等公共交通計画（岩手県・沿線12市町村の広域計画、2024策定） https://www.city.miyako.iwate.jp/gyosei/soshiki/kokyokotsuusuishin/2/1/605.html もカバー。環境：確認できず。 【追加調査 2026-10】交通(2026-10調査)：国交省一覧(R8.5末)の広域計画「三陸鉄道沿線地域等」＝三陸鉄道沿線地域等公共交通計画。検索結果本文で計画期間「令和６年度（2024年度）から令和10年度（2028年度）」を確認（前身の三陸鉄道沿線地域等公共交通網形成計画をR6.3中間評価を踏まえ改定、岩手県地域公共交通計画R6〜R10と整合）。PDF https://www.city.miyako.iwate.jp/material/files/group/8/sanntetsukoutuukeikaku2024.pdf 。終期R10のため次期計画の着手情報なし。普代村独自の地域公共交通計画は引き続き見当たらず。 根拠: 三陸鉄道沿線地域等公共交通計画の計画期間は令和６年度（2024年度）から令和10年度（2028年度） | S31: 調査済 | T31: 掲載（広域：三陸鉄道沿線地域等）
A32: 29 | B32: 軽米町 | C32: =IF(OR(D32="◎",E32="◎"),"◎ 営業",IF(OR(D32="△",E32="△"),"△ 着手済・要確認",IF(OR(D32="？",E32="？"),"？ 期間要確認","✕ 対象外"))) | D32: =IF(J32="計画なし","－",IF(J32="策定済","✕",IF(H32="","？",IF(AND(H32>=TGT_MIN,H32<=TGT_MAX),IF(J32="着手済","△","◎"),"✕")))) | E32: =IF(P32="計画なし","－",IF(P32="策定済","✕",IF(N32="","？",IF(AND(N32>=TGT_MIN,N32<=TGT_MAX),IF(P32="着手済","△","◎"),"✕")))) | G32: 不明 | I32: 不明 | J32: 計画なし | M32: 不明 | O32: 不明 | P32: 計画なし | R32: 交通：地域公共交通計画は確認できず。R8.4からコミュニティバス（円子線・大野線）運行、デマンド交通導入を検討中（R7.3議会一般質問）。環境：確認できず。 | S32: 環境のみ調査 | T32: 未掲載
A33: 30 | B33: 野田村 | C33: =IF(OR(D33="◎",E33="◎"),"◎ 営業",IF(OR(D33="△",E33="△"),"△ 着手済・要確認",IF(OR(D33="？",E33="？"),"？ 期間要確認","✕ 対象外"))) | D33: =IF(J33="計画なし","－",IF(J33="策定済","✕",IF(H33="","？",IF(AND(H33>=TGT_MIN,H33<=TGT_MAX),IF(J33="着手済","△","◎"),"✕")))) | E33: =IF(P33="計画なし","－",IF(P33="策定済","✕",IF(N33="","？",IF(AND(N33>=TGT_MIN,N33<=TGT_MAX),IF(P33="着手済","△","◎"),"✕")))) | F33: 三陸鉄道沿線地域等公共交通計画（岩手県・沿線市町村の広域計画） | G33: R6〜R10 | H33: 10 | I33: 確認済 | J33: 未確認 | K33: https://www.city.miyako.iwate.jp/material/files/group/8/sanntetsukoutuukeikaku2024.pdf | M33: 不明 | O33: 不明 | P33: 計画なし | R33: 交通：村独自の計画は確認できず（村営バス https://www.vill.noda.iwate.jp/soshiki/miraizukurisuishinka/miraizukurisuishinhan/doro_kotsu/642.html ）。三陸鉄道沿線地域等公共交通計画（岩手県・沿線12市町村の広域計画、2024策定） https://www.city.miyako.iwate.jp/gyosei/soshiki/kokyokotsuusuishin/2/1/605.html もカバー。環境：確認できず。 【追加調査 2026-10】交通(2026-10調査)：国交省一覧(R8.5末)の広域計画「三陸鉄道沿線地域等」＝三陸鉄道沿線地域等公共交通計画。検索結果本文で計画期間「令和６年度（2024年度）から令和10年度（2028年度）」を確認（前身の三陸鉄道沿線地域等公共交通網形成計画をR6.3中間評価を踏まえ改定、岩手県地域公共交通計画R6〜R10と整合）。PDF https://www.city.miyako.iwate.jp/material/files/group/8/sanntetsukoutuukeikaku2024.pdf 。終期R10のため次期計画の着手情報なし。野田村独自の地域公共交通計画は引き続き見当たらず。 根拠: 三陸鉄道沿線地域等公共交通計画の計画期間は令和６年度（2024年度）から令和10年度（2028年度） | S33: 調査済 | T33: 掲載（広域：三陸鉄道沿線地域等）
A34: 31 | B34: 九戸村 | C34: =IF(OR(D34="◎",E34="◎"),"◎ 営業",IF(OR(D34="△",E34="△"),"△ 着手済・要確認",IF(OR(D34="？",E34="？"),"？ 期間要確認","✕ 対象外"))) | D34: =IF(J34="計画なし","－",IF(J34="策定済","✕",IF(H34="","？",IF(AND(H34>=TGT_MIN,H34<=TGT_MAX),IF(J34="着手済","△","◎"),"✕")))) | E34: =IF(P34="計画なし","－",IF(P34="策定済","✕",IF(N34="","？",IF(AND(N34>=TGT_MIN,N34<=TGT_MAX),IF(P34="着手済","△","◎"),"✕")))) | F34: 九戸村地域公共交通計画 | G34: 不明 | I34: 不明 | J34: 未確認 | K34: https://vill.kunohe.iwate.jp/fs/9/5/9/5/_/%E4%B9%9D%E6%88%B8%E6%9D%91%E5%9C%B0%E5%9F%9F%E5%85%AC%E5%85%B1%E4%BA%A4%E9%80%9A%E8%A8%88%E7%94%BB.pdf | M34: 不明 | O34: 不明 | P34: 計画なし | R34: 交通：計画書PDFの存在を確認、期間は検索で確認できず。環境：確認できず。 | S34: 調査済 | T34: 掲載
A35: 32 | B35: 洋野町 | C35: =IF(OR(D35="◎",E35="◎"),"◎ 営業",IF(OR(D35="△",E35="△"),"△ 着手済・要確認",IF(OR(D35="？",E35="？"),"？ 期間要確認","✕ 対象外"))) | D35: =IF(J35="計画なし","－",IF(J35="策定済","✕",IF(H35="","？",IF(AND(H35>=TGT_MIN,H35<=TGT_MAX),IF(J35="着手済","△","◎"),"✕")))) | E35: =IF(P35="計画なし","－",IF(P35="策定済","✕",IF(N35="","？",IF(AND(N35>=TGT_MIN,N35<=TGT_MAX),IF(P35="着手済","△","◎"),"✕")))) | F35: 洋野町地域公共交通計画（策定中） | G35: R9〜R13 | H35: 13 | I35: 確認済 | J35: 着手済 | K35: https://www.town.hirono.iwate.jp/doc/2026070700013 | M35: 不明 | O35: 不明 | P35: 計画なし | R35: 交通：R9〜R13を期間とする初の地域公共交通計画の策定業務を公募型プロポーザルで募集（R8.7.7公告、8月契約予定）。現行計画は確認できず。三陸鉄道沿線地域等公共交通計画（岩手県・沿線12市町村の広域計画、2024策定） https://www.city.miyako.iwate.jp/gyosei/soshiki/kokyokotsuusuishin/2/1/605.html もカバー。環境：環境基本計画は確認できず（第5次地球温暖化対策実行計画を策定中）。 | S35: 調査済 | T35: 掲載（広域：三陸鉄道沿線地域等）
A36: 33 | B36: 一戸町 | C36: =IF(OR(D36="◎",E36="◎"),"◎ 営業",IF(OR(D36="△",E36="△"),"△ 着手済・要確認",IF(OR(D36="？",E36="？"),"？ 期間要確認","✕ 対象外"))) | D36: =IF(J36="計画なし","－",IF(J36="策定済","✕",IF(H36="","？",IF(AND(H36>=TGT_MIN,H36<=TGT_MAX),IF(J36="着手済","△","◎"),"✕")))) | E36: =IF(P36="計画なし","－",IF(P36="策定済","✕",IF(N36="","？",IF(AND(N36>=TGT_MIN,N36<=TGT_MAX),IF(P36="着手済","△","◎"),"✕")))) | G36: 不明 | I36: 不明 | J36: 計画なし | M36: 不明 | O36: 不明 | P36: 計画なし | R36: 交通：地域公共交通計画は確認できず（デマンド交通いくべ号、R8.4運賃改定案パブコメ https://www.town.ichinohe.iwate.jp/soshikikarasagasu/seisakukikakuka/kokyokotsu/6744.html ）。環境：確認できず。 | S36: 環境のみ調査 | T36: 未掲載

Sheet 宮城県
A1: 宮城県 地域公共交通計画・環境基本計画の終期一覧（2026年9月30日時点の調査）
A2: ="営業判定の対象：終期 R"&TGT_MIN&"〜R"&TGT_MAX&"年度 →◎（着手済は△、期間不明は？）。終期セルの色：緑＝対象年度／橙＝その翌年度（次の候補）。対象年度は「集計・設定」シートのC4・C5のプルダウンで切替。"
A3: No | B3: 市町村 | C3: 営業判定 | D3: 交通判定 | E3: 環境判定 | F3: 地域公共交通計画 | G3: 交通 計画期間 | H3: 交通 終期(令和年度) | I3: 交通 確度 | J3: 交通 改定状況 | K3: 交通 計画リンク（エビデンス） | L3: 環境基本計画 | M3: 環境 計画期間 | N3: 環境 終期(令和年度) | O3: 環境 確度 | P3: 環境 改定状況 | Q3: 環境 計画リンク（エビデンス） | R3: 注釈（改定作業の状況など） | S3: 調査状況 | T3: 国交省一覧(R8.5末)
A4: 1 | B4: 仙台市 | C4: =IF(OR(D4="◎",E4="◎"),"◎ 営業",IF(OR(D4="△",E4="△"),"△ 着手済・要確認",IF(OR(D4="？",E4="？"),"？ 期間要確認","✕ 対象外"))) | D4: =IF(J4="計画なし","－",IF(J4="策定済","✕",IF(H4="","？",IF(AND(H4>=TGT_MIN,H4<=TGT_MAX),IF(J4="着手済","△","◎"),"✕")))) | E4: =IF(P4="計画なし","－",IF(P4="策定済","✕",IF(N4="","？",IF(AND(N4>=TGT_MIN,N4<=TGT_MAX),IF(P4="着手済","△","◎"),"✕")))) | F4: 仙台市地域公共交通計画 | G4: R4〜R8 | H4: 8 | I4: 確認済 | J4: 着手済 | K4: https://www.city.sendai.jp/kokyo/kurashi/machi/kotsu/kekakunado/chikoukei.html | L4: 杜の都環境プラン（仙台市環境基本計画） | M4: R3〜R12 | N4: 12 | O4: 確認済 | P4: 策定済 | Q4: https://www.city.sendai.jp/kankyo-chose/kurashi/machi/kankyohozen/chosa/morinomiyako/documents/01_moripura_honpen.pdf | R4: 交通：R8終期、次期計画（R9〜R13）策定中。R7策定調査業務は日本工営系（契約R7.4.21〜R8.3.31、12,749千円）、R8策定委託はCTI(建設技術研究所)東北支社にR8.5.13契約（4,950千円、〜R9.3.31）。R8.11中間案→12月頃パブコメ→R9.3策定予定（推進協議会資料 https://www.city.sendai.jp/kotsu-kekaku/suishinkyogikai/documents/siryou2_r8_1.pdf ）。利便増進実施計画もR8末終了。環境：R7中間評価を経てR8.3に中間改定版公表（策定済は中間改定の意）。 | S4: 調査済 | T4: 掲載
A5: 2 | B5: 石巻市 | C5: =IF(OR(D5="◎",E5="◎"),"◎ 営業",IF(OR(D5="△",E5="△"),"△ 着手済・要確認",IF(OR(D5="？",E5="？"),"？ 期間要確認","✕ 対象外"))) | D5: =IF(J5="計画なし","－",IF(J5="策定済","✕",IF(H5="","？",IF(AND(H5>=TGT_MIN,H5<=TGT_MAX),IF(J5="着手済","△","◎"),"✕")))) | E5: =IF(P5="計画なし","－",IF(P5="策定済","✕",IF(N5="","？",IF(AND(N5>=TGT_MIN,N5<=TGT_MAX),IF(P5="着手済","△","◎"),"✕")))) | F5: 石巻市総合交通計画（地域公共交通計画） | G5: R4〜R8 | H5: 8 | I5: 確認済 | J5: 着手済 | K5: https://www.city.ishinomaki.lg.jp:443/cont/10053500/issks/dai1shou.pdf | L5: 第2次石巻市環境基本計画 | M5: R8〜R17 | N5: 17 | O5: 確認済 | P5: 策定済 | Q5: https://www.city.ishinomaki.lg.jp/cont/10301000/3253/1.pdf | R5: 交通：R8終期。改定作業中：R8.5〜R9.1にWG・地域公共交通活性化協議会で検討、R9.1パブコメ予定（庁議資料 https://www.city.ishinomaki.lg.jp/cont/10181000/0070/reiwahatinendotyougikannkei/daisannkaityougi/sougoukoutuukeikaku.pdf ）。改定支援業務仕様書あり https://www.city.ishinomaki.lg.jp/cont/10053500/siyousyokoutuusennryakukaiteisienn.pdf 。環境：第2次計画R8〜R17（R7庁議資料 https://www.city.ishinomaki.lg.jp/cont/10181000/0070/R7tyougi/17/17-siryou1-1.pdf ）。e_urlは検索結果中の候補で内容未精査。 | S5: 調査済 | T5: 掲載
A6: 3 | B6: 塩竈市 | C6: =IF(OR(D6="◎",E6="◎"),"◎ 営業",IF(OR(D6="△",E6="△"),"△ 着手済・要確認",IF(OR(D6="？",E6="？"),"？ 期間要確認","✕ 対象外"))) | D6: =IF(J6="計画なし","－",IF(J6="策定済","✕",IF(H6="","？",IF(AND(H6>=TGT_MIN,H6<=TGT_MAX),IF(J6="着手済","△","◎"),"✕")))) | E6: =IF(P6="計画なし","－",IF(P6="策定済","✕",IF(N6="","？",IF(AND(N6>=TGT_MIN,N6<=TGT_MAX),IF(P6="着手済","△","◎"),"✕")))) | G6: 不明 | I6: 不明 | J6: 未確認 | L6: 第3次塩竈市環境基本計画 | M6: R7〜R16 | N6: 16 | O6: 確認済 | P6: 策定済 | Q6: https://www.city.shiogama.miyagi.jp/soshiki/18/50557.html | R6: 交通：市の地域公共交通計画は検索（市サイト内含む）で見つからず（計画なしの可能性、要確認）。環境：第3次計画R7〜R16、素案パブコメ https://www.city.shiogama.miyagi.jp/soshiki/18/49050.html を経て策定（ページ更新R7.4.18）。参考：循環型社会形成推進地域計画 R5.4〜R10.3。 | S6: 環境のみ調査 | T6: 未掲載
A7: 4 | B7: 気仙沼市 | C7: =IF(OR(D7="◎",E7="◎"),"◎ 営業",IF(OR(D7="△",E7="△"),"△ 着手済・要確認",IF(OR(D7="？",E7="？"),"？ 期間要確認","✕ 対象外"))) | D7: =IF(J7="計画なし","－",IF(J7="策定済","✕",IF(H7="","？",IF(AND(H7>=TGT_MIN,H7<=TGT_MAX),IF(J7="着手済","△","◎"),"✕")))) | E7: =IF(P7="計画なし","－",IF(P7="策定済","✕",IF(N7="","？",IF(AND(N7>=TGT_MIN,N7<=TGT_MAX),IF(P7="着手済","△","◎"),"✕")))) | F7: 第2次気仙沼市総合交通計画（2次改定版） | G7: H30〜R8（目標年次R8） | H7: 8 | I7: 推定 | J7: 着手済 | K7: https://www.kesennuma.miyagi.jp/li/shisei/150/020/index.html | M7: 不明 | O7: 不明 | P7: 未確認 | R7: 交通：第2次はH30.2策定・R3.6.28二次改定、目標年次R8（県の市町村計画一覧 https://www.pref.miyagi.jp/documents/7752/02_r8_sityousonkeikaku.pdf の検索要約より）。同資料で第3次気仙沼市総合交通計画を策定中と記載あり→着手済と判断（要確認）。法定地域公共交通計画としての位置付けは未確認。R8.7にAIデマンド交通導入業務プロポーザル https://www.kesennuma.miyagi.jp/sec/s023/020/010/010/20260706170359.html 。環境：市公式サイト内検索で環境基本計画ヒットせず（計画なしの可能性、要確認）。WebFetchは市サイトblocked。 地球温暖化対策実行計画（区域施策編）のパブコメ実績・気仙沼市持続可能なまち推進計画（R7.7）あり https://www.kesennuma.miyagi.jp/li/life/020/080/070/index.html 。 【追加調査 2026-10】環境：『気仙沼市環境基本計画』の名称での計画ページ・PDFは検索（一般・市ドメイン限定・完全一致、計5回）でヒットせず。一方、市ドメイン検索の要約で、気仙沼市地球温暖化対策実行計画（区域施策編、2025〜2030年度）は『市環境基本計画における地球温暖化対策を推進するための個別計画』と記載との情報あり（要約のみ・URL特定できず、一般論の混入の可能性）。存在有無は判断保留（計画なしとは断定できず）。計画・施策一覧 https://www.kesennuma.miyagi.jp/li/shisei/060/index.html の確認を推奨。 | S7: 交通のみ調査 | T7: 掲載
A8: 5 | B8: 白石市 | C8: =IF(OR(D8="◎",E8="◎"),"◎ 営業",IF(OR(D8="△",E8="△"),"△ 着手済・要確認",IF(OR(D8="？",E8="？"),"？ 期間要確認","✕ 対象外"))) | D8: =IF(J8="計画なし","－",IF(J8="策定済","✕",IF(H8="","？",IF(AND(H8>=TGT_MIN,H8<=TGT_MAX),IF(J8="着手済","△","◎"),"✕")))) | E8: =IF(P8="計画なし","－",IF(P8="策定済","✕",IF(N8="","？",IF(AND(N8>=TGT_MIN,N8<=TGT_MAX),IF(P8="着手済","△","◎"),"✕")))) | F8: 白石市地域公共交通計画 | G8: R5〜R9（推定） | H8: 9 | I8: 確認済 | J8: 着手済 | K8: https://www.city.shiroishi.miyagi.jp/uploaded/attachment/22013.pdf | L8: 第3次白石市環境基本計画 | M8: H31(R1)〜R10（10年間） | N8: 10 | O8: 確認済 | P8: 未確認 | Q8: https://www.city.shiroishi.miyagi.jp/soshiki/18/ | R8: 交通：R5.3策定（前身の網形成計画はH29.6）、計画ページ https://www.city.shiroishi.miyagi.jp/soshiki/17/27078.html 。期間は検索で確認できず5年と仮定しR9終期を推定→R9終期なら次期策定はR8〜R9着手見込み（有望・要確認）。環境：第3次計画と第3次温暖化対策実行計画をH31.4.23掲載、期間不明（10年ならR10頃終期）。広域：宮城県地域公共交通計画R8〜R14あり（県計画、検索要約より）。佐賀県白石町・千葉県白井市とは別。 【ファクトチェック 2026-10-01: 正しい】確認期間: R5〜R9（令和5年度〜令和9年度の5年間、R5.3策定）／次期: 着手済の可能性高：「白石市地域公共交通計画策定調査に係る公募型プロポーザル」（2026-07-14更新、募集終了）が市サイト まちづくり推進課/入札・契約情報に掲載（https://www.city.shiroishi.miyagi.jp/／根拠: https://www.city.shiroishi.miyagi.jp/soshiki/17/27078.html 【追加調査 2026-10】環境：第3次白石市環境基本計画は平成31年度（令和元年度）から10年間＝R10終期。市サイト内検索（環境課ページ https://www.city.shiroishi.miyagi.jp/soshiki/18/ 、令和2年度施政方針 https://www.city.shiroishi.miyagi.jp/site/mayor/16031.html ）の結果本文で2回一致。次期はR9〜R10着手見込み（現時点未確認）。 根拠: 第３次白石市環境基本計画は令和元年度から10年間を計画期間 | S8: 調査済 | T8: 掲載
A9: 6 | B9: 名取市 | C9: =IF(OR(D9="◎",E9="◎"),"◎ 営業",IF(OR(D9="△",E9="△"),"△ 着手済・要確認",IF(OR(D9="？",E9="？"),"？ 期間要確認","✕ 対象外"))) | D9: =IF(J9="計画なし","－",IF(J9="策定済","✕",IF(H9="","？",IF(AND(H9>=TGT_MIN,H9<=TGT_MAX),IF(J9="着手済","△","◎"),"✕")))) | E9: =IF(P9="計画なし","－",IF(P9="策定済","✕",IF(N9="","？",IF(AND(N9>=TGT_MIN,N9<=TGT_MAX),IF(P9="着手済","△","◎"),"✕")))) | F9: 名取市地域公共交通計画 | G9: R5〜R9 | H9: 9 | I9: 確認済 | J9: 未確認 | K9: https://www.city.natori.miyagi.jp/uploaded/attachment/9510.pdf | L9: 第二次名取市環境基本計画 | M9: R2〜R12（11年間） | N9: 12 | O9: 確認済 | P9: 未確認 | Q9: https://www.city.natori.miyagi.jp/page/4721.html | R9: 交通：R5.3.28策定、R9終期。次期計画の策定業務・プロポーザルは検索で未確認。R8.8.25にR8年度名取市地域公共交通活性化推進協議会開催 https://www.city.natori.miyagi.jp/page/45227.html （次期計画の議題か要確認・有望）。計画ページ https://www.city.natori.miyagi.jp/page/4327.html 。環境：第二次計画の期間は検索で確認できず（R2開始10年ならR11終期と推定）。 【ファクトチェック 2026-10-01: 正しい】確認期間: R5〜R9（令和5年度～令和9年度の5ヶ年、R5.3.28策定）／次期: 確認できず（令和8年度協議会 R8.8.25開催の議題は『計画の取組状況について』のみ／https://www.city.natori.miyagi.jp/page/45227.html）／根拠: https://www.city.natori.miyagi.jp/page/4327.html 【追加調査 2026-10】環境：第二次名取市環境基本計画の計画期間は令和2（2020）年度〜令和12（2030）年度の11年間。計画ページ https://www.city.natori.miyagi.jp/page/4721.html 、本編PDF https://www.city.natori.miyagi.jp/uploaded/attachment/10172.pdf 。R7.?に環境に関する市民・事業者意識調査実施 https://www.city.natori.miyagi.jp/page/39371.html （中間見直し等の可能性）。 根拠: 計画期間は令和2（2020）年度から令和12（2030）年度までの11年間 | S9: 調査済 | T9: 掲載
A10: 7 | B10: 角田市 | C10: =IF(OR(D10="◎",E10="◎"),"◎ 営業",IF(OR(D10="△",E10="△"),"△ 着手済・要確認",IF(OR(D10="？",E10="？"),"？ 期間要確認","✕ 対象外"))) | D10: =IF(J10="計画なし","－",IF(J10="策定済","✕",IF(H10="","？",IF(AND(H10>=TGT_MIN,H10<=TGT_MAX),IF(J10="着手済","△","◎"),"✕")))) | E10: =IF(P10="計画なし","－",IF(P10="策定済","✕",IF(N10="","？",IF(AND(N10>=TGT_MIN,N10<=TGT_MAX),IF(P10="着手済","△","◎"),"✕")))) | F10: 角田市地域公共交通計画 | G10: 不明 | I10: 不明 | J10: 着手済 | K10: https://www.city.kakuda.lg.jp/soshiki/4/25038.html | L10: 角田市第3次環境基本計画 | M10: R5〜R14（10年間） | N10: 14 | O10: 推定 | P10: 未確認 | R10: 交通：市単独の地域公共交通計画（初策定）を策定中、案のパブコメ実施 https://www.city.kakuda.lg.jp/soshiki/4/25038.html 、R8.1.23に第3回活性化協議会 https://www.city.kakuda.lg.jp/uploaded/life/24126_87553_misc.pdf 。R8.3頃策定の可能性（策定完了・期間は未確認）。広域：阿武隈急行線地域公共交通計画（案）パブコメ https://www.city.kakuda.lg.jp/soshiki/4/24148.html 。環境：第3次環境基本計画R5策定（期間不明）、角田市地球温暖化対策総合計画 R6.3策定・R8.3修正 https://www.city.kakuda.lg.jp/uploaded/life/17642_48417_misc.pdf 。 【追加調査 2026-10】環境：角田市第3次環境基本計画（2023年策定、環境像『「緑・水・人」調和のとれた環境都市』）。市サイト内検索の要約で『計画期間は2023年度から2032年度までの10年間』（出典は角田市地球温暖化対策総合計画 https://www.city.kakuda.lg.jp/uploaded/life/17642_48417_misc.pdf と思われる）。別検索では同PDF中の表から2020〜2030年度との要約もあり不一致のため推定扱い。計画単独ページURLは未発見。 根拠: 計画期間は2023年度から2032年度までの10年間 | S10: 調査済 | T10: 掲載（広域：阿武隈急行線地域）
A11: 8 | B11: 多賀城市 | C11: =IF(OR(D11="◎",E11="◎"),"◎ 営業",IF(OR(D11="△",E11="△"),"△ 着手済・要確認",IF(OR(D11="？",E11="？"),"？ 期間要確認","✕ 対象外"))) | D11: =IF(J11="計画なし","－",IF(J11="策定済","✕",IF(H11="","？",IF(AND(H11>=TGT_MIN,H11<=TGT_MAX),IF(J11="着手済","△","◎"),"✕")))) | E11: =IF(P11="計画なし","－",IF(P11="策定済","✕",IF(N11="","？",IF(AND(N11>=TGT_MIN,N11<=TGT_MAX),IF(P11="着手済","△","◎"),"✕")))) | F11: 多賀城市地域公共交通計画 | G11: R8〜R12 | H11: 12 | I11: 確認済 | J11: 着手済 | K11: https://www.city.tagajo.miyagi.jp/toshike/kurashi/kotsu/documents/keikaku.pdf | L11: 第三次多賀城市環境基本計画（R8.3改定） | M11: 不明 | O11: 不明 | P11: 策定済 | R11: 交通：新計画（R8〜R12）の案「令和8年 月 閲覧用」を確認（旧：多賀城市生活交通ネットワーク計画）。策定完了（R8.3頃か）は未確認のため着手済扱い、実質策定済の可能性大。協議会 https://www.city.tagajo.miyagi.jp/toshike/kurashi/kotsu/kokyo.html 。環境：第三次環境基本計画がR8.3改定と検索要約で確認、計画本体URL・期間は未取得。温暖化対策実行計画（区域施策編）https://www.city.tagajo.miyagi.jp/kankyo/shise/shisaku/kekaku/ondanka.html 。 | S11: 調査済 | T11: 掲載
A12: 9 | B12: 岩沼市 | C12: =IF(OR(D12="◎",E12="◎"),"◎ 営業",IF(OR(D12="△",E12="△"),"△ 着手済・要確認",IF(OR(D12="？",E12="？"),"？ 期間要確認","✕ 対象外"))) | D12: =IF(J12="計画なし","－",IF(J12="策定済","✕",IF(H12="","？",IF(AND(H12>=TGT_MIN,H12<=TGT_MAX),IF(J12="着手済","△","◎"),"✕")))) | E12: =IF(P12="計画なし","－",IF(P12="策定済","✕",IF(N12="","？",IF(AND(N12>=TGT_MIN,N12<=TGT_MAX),IF(P12="着手済","△","◎"),"✕")))) | F12: 岩沼市民バス運行計画 | G12: R6〜R12 | H12: 12 | I12: 確認済 | J12: 未確認 | K12: https://www.city.iwanuma.miyagi.jp/kurashi/kotsu/shimin-bus/documents/shinbuskeikaku.pdf | L12: 岩沼市環境基本計画 | M12: H28〜R7 | N12: 7 | O12: 確認済 | P12: 未確認 | Q12: https://www.city.iwanuma.miyagi.jp/kurashi/kankyo-eisei/kankyo-eisei/kankyo-keikaku.html | R12: 交通：法定の地域公共交通計画は検索で確認できず、市民バス運行計画（R4.11策定、R6〜R12）が実質的な交通計画。環境：R7(2025)で期間満了だが次期（第2次）計画の策定・パブコメ・審議会情報は検索で見つからず（要確認・有望）。宮城県岩沼市（他県の類似名に注意）。 | S12: 調査済 | T12: 未掲載【当方は計画あり】
A13: 10 | B13: 登米市 | C13: =IF(OR(D13="◎",E13="◎"),"◎ 営業",IF(OR(D13="△",E13="△"),"△ 着手済・要確認",IF(OR(D13="？",E13="？"),"？ 期間要確認","✕ 対象外"))) | D13: =IF(J13="計画なし","－",IF(J13="策定済","✕",IF(H13="","？",IF(AND(H13>=TGT_MIN,H13<=TGT_MAX),IF(J13="着手済","△","◎"),"✕")))) | E13: =IF(P13="計画なし","－",IF(P13="策定済","✕",IF(N13="","？",IF(AND(N13>=TGT_MIN,N13<=TGT_MAX),IF(P13="着手済","△","◎"),"✕")))) | F13: 登米市地域公共交通計画 | G13: R7〜R11 | H13: 11 | I13: 確認済 | J13: 策定済 | K13: https://www.city.tome.miyagi.jp/shiminkyodo/koukyoukoutsuu/documents/tomechikikoukyokotsukeikakuan.pdf | L13: 第3次登米市環境基本計画 | M13: R8〜R17 | N13: 17 | O13: 確認済 | P13: 策定済 | Q13: https://www.city.tome.miyagi.jp/kankyo/shisejoho/gyose/sogokekaku/documents/3rdenviplan.pdf | R13: 交通：R7〜R11の新計画（前身は第二次公共交通再編計画）。概要 https://www.city.tome.miyagi.jp/shiminkyodo/documents/tomeptp-gaiyou.pdf 。環境：第2次(H28〜R7)の後継として第3次(R8〜R17、前期/後期5年)を策定、パブコメ意見公表 https://www.city.tome.miyagi.jp/koshitu/shisejoho/kohokocho/publiccomment/ikenkobo/documents/080130_iken.pdf 。両計画とも更新済みで直近の改定需要は低い。 | S13: 調査済 | T13: 掲載
A14: 11 | B14: 栗原市 | C14: =IF(OR(D14="◎",E14="◎"),"◎ 営業",IF(OR(D14="△",E14="△"),"△ 着手済・要確認",IF(OR(D14="？",E14="？"),"？ 期間要確認","✕ 対象外"))) | D14: =IF(J14="計画なし","－",IF(J14="策定済","✕",IF(H14="","？",IF(AND(H14>=TGT_MIN,H14<=TGT_MAX),IF(J14="着手済","△","◎"),"✕")))) | E14: =IF(P14="計画なし","－",IF(P14="策定済","✕",IF(N14="","？",IF(AND(N14>=TGT_MIN,N14<=TGT_MAX),IF(P14="着手済","△","◎"),"✕")))) | F14: 栗原市地域公共交通計画（前身：栗原市地域公共交通網形成計画） | G14: 不明 | I14: 不明 | J14: 未確認 | K14: https://www.kuriharacity.jp/li/010/020/120/index.html | L14: 第2次栗原市環境基本計画 | M14: H30〜R9（10年間） | N14: 9 | O14: 確認済 | P14: 着手済 | Q14: https://www.kuriharacity.jp/w012/010/010/020/120/51193.html | R14: 交通：市企画部所管の地域公共交通計画の存在は市サイトで確認、期間は検索で確認できず。広報くりはら2024『特集 生まれ変わる地域公共交通』 https://www.kuriharacity.jp/w009/030/010/2024/379/kurihara379_02.pdf 。環境：第2次計画の存在のみ確認、期間不明（第2次総合計画がH29〜R8のため連動していればR8終期の可能性、要確認）。 【追加調査 2026-10】環境：第2次栗原市環境基本計画はH30（2018）〜R9（2027）年度の10年間（計画ページ https://www.kuriharacity.jp/w012/010/010/020/120/51193.html の検索結果）。次期：『第3次栗原市環境基本計画策定支援業務』が市の2026年6月入札結果に掲載（R8.6.3執行）https://www.kuriharacity.jp/w004/030/010/030/20260114/202606/PAGE000000000000015506.html →着手済。第3次総合計画（R9〜）も並行策定中。 根拠: 第2次栗原市環境基本計画…2018年度から2027年度までの10年間 | S14: 調査済 | T14: 掲載
A15: 12 | B15: 東松島市 | C15: =IF(OR(D15="◎",E15="◎"),"◎ 営業",IF(OR(D15="△",E15="△"),"△ 着手済・要確認",IF(OR(D15="？",E15="？"),"？ 期間要確認","✕ 対象外"))) | D15: =IF(J15="計画なし","－",IF(J15="策定済","✕",IF(H15="","？",IF(AND(H15>=TGT_MIN,H15<=TGT_MAX),IF(J15="着手済","△","◎"),"✕")))) | E15: =IF(P15="計画なし","－",IF(P15="策定済","✕",IF(N15="","？",IF(AND(N15>=TGT_MIN,N15<=TGT_MAX),IF(P15="着手済","△","◎"),"✕")))) | F15: 東松島市地域公共交通網形成計画（+再編実施計画 H30.12） | G15: H29〜R3 | H15: 3 | I15: 確認済 | J15: 未確認 | K15: https://www.city.higashimatsushima.miyagi.jp/shisei/shisaku-keikaku/kihonkeikaku/kokyokotsumo-keisei.html | L15: 東松島市第2次環境基本計画 | M15: H29〜R8 | N15: 8 | O15: 確認済 | P15: 未確認 | Q15: https://www.city.higashimatsushima.miyagi.jp/shisei/shisaku-keikaku/kihonkeikaku/index.html | R15: 交通：網形成計画はH29.11策定・H29〜R3。後継の地域公共交通計画は検索で確認できず（期間満了後の更新状況要確認、有望）。環境：第2次はFY2017〜2026(R8)で本年度終期、第3次策定作業はR8中に進行しているはずだが検索では未確認（有望）。関連：地球温暖化対策総合計画 https://www.city.higashimatsushima.miyagi.jp/shisei/shisaku-keikaku/kihonkeikaku/chikyuuonndannka.html 、第3次総合計画も策定中。 | S15: 調査済 | T15: 掲載／期間満了
A16: 13 | B16: 大崎市 | C16: =IF(OR(D16="◎",E16="◎"),"◎ 営業",IF(OR(D16="△",E16="△"),"△ 着手済・要確認",IF(OR(D16="？",E16="？"),"？ 期間要確認","✕ 対象外"))) | D16: =IF(J16="計画なし","－",IF(J16="策定済","✕",IF(H16="","？",IF(AND(H16>=TGT_MIN,H16<=TGT_MAX),IF(J16="着手済","△","◎"),"✕")))) | E16: =IF(P16="計画なし","－",IF(P16="策定済","✕",IF(N16="","？",IF(AND(N16>=TGT_MIN,N16<=TGT_MAX),IF(P16="着手済","△","◎"),"✕")))) | F16: 大崎市地域公共交通計画（都市・地域総合交通戦略と一体） | G16: R3〜R12 | H16: 12 | I16: 確認済 | J16: 未確認 | K16: https://www.city.osaki.miyagi.jp/shisei/soshikikarasagasu/shiminkyodousuishimbu/machizukurisuishinka/3/2/1/3214.html | L16: 第2次大崎市環境基本計画 | M16: R2〜R11 | N16: 11 | O16: 確認済 | P16: 未確認 | Q16: https://www.city.osaki.miyagi.jp/material/files/group/12/20200421-200432.pdf | R16: 交通：前身は網形成計画。中間案パブコメR4.1.7〜1.26（https://www.city.osaki.miyagi.jp/shisei/soshikikarasagasu/shiminkyodousuishimbu/machizukurisuishinka/3/1/1/3215.html）、期間は中間案記載の10年(R3〜R12)。広域：大崎定住自立圏（大崎市・色麻・加美・涌谷・美里）第3次共生ビジョン https://www.city.osaki.miyagi.jp/material/files/group/10/3rd_vision_20220331.pdf （交通専用の広域計画は未確認）。第3次大崎市総合計画策定支援プロポ実施 https://www.city.osaki.miyagi.jp/shisei/soshikikarasagasu/shiminkyodousuishimbu/seisakuka/2_1/20665.html 。環境：R2〜R11、次期作業なし。 | S16: 調査済 | T16: 掲載
A17: 14 | B17: 富谷市 | C17: =IF(OR(D17="◎",E17="◎"),"◎ 営業",IF(OR(D17="△",E17="△"),"△ 着手済・要確認",IF(OR(D17="？",E17="？"),"？ 期間要確認","✕ 対象外"))) | D17: =IF(J17="計画なし","－",IF(J17="策定済","✕",IF(H17="","？",IF(AND(H17>=TGT_MIN,H17<=TGT_MAX),IF(J17="着手済","△","◎"),"✕")))) | E17: =IF(P17="計画なし","－",IF(P17="策定済","✕",IF(N17="","？",IF(AND(N17>=TGT_MIN,N17<=TGT_MAX),IF(P17="着手済","△","◎"),"✕")))) | F17: 富谷市地域公共交通計画 | G17: R7〜R11 | H17: 11 | I17: 確認済 | J17: 策定済 | K17: https://www.tomiya-city.miyagi.jp/uploads/pdf/b4883b320d97c8ac81041749b47dad0a9397ae5e.pdf | M17: 不明 | O17: 不明 | P17: 未確認 | R17: 交通：R7.3策定（R6年度）、t_urlはR7.3協議会資料の計画（案）。都市・地域総合交通戦略 https://www.tomiya-city.miyagi.jp/shisei/keikaku/keikaku/nek5ga2.html 。環境：単独の環境基本計画は検索で確認できず（計画なしの可能性、市HP計画一覧 https://www.tomiya-city.miyagi.jp/shisei/keikaku/ 要確認）。温暖化対策実行計画は存在。第2次富谷市総合計画をR8年度開始で策定。 【追加調査 2026-10】環境：市ドメイン検索・計画一覧系検索（計2回）で環境基本計画はヒットせず。総合計画の関連計画として地球温暖化対策実行計画・2050年ゼロカーボン戦略 https://www.tomiya-city.miyagi.jp/kurashi/kankyou/zerocarbon/zero2050.html は挙がるが環境基本計画の記載は見当たらない（要約ベース）。計画なしの可能性が高いが公式一覧での確認ができず未断定。 | S17: 交通のみ調査 | T17: 掲載
A18: 15 | B18: 蔵王町 | C18: =IF(OR(D18="◎",E18="◎"),"◎ 営業",IF(OR(D18="△",E18="△"),"△ 着手済・要確認",IF(OR(D18="？",E18="？"),"？ 期間要確認","✕ 対象外"))) | D18: =IF(J18="計画なし","－",IF(J18="策定済","✕",IF(H18="","？",IF(AND(H18>=TGT_MIN,H18<=TGT_MAX),IF(J18="着手済","△","◎"),"✕")))) | E18: =IF(P18="計画なし","－",IF(P18="策定済","✕",IF(N18="","？",IF(AND(N18>=TGT_MIN,N18<=TGT_MAX),IF(P18="着手済","△","◎"),"✕")))) | F18: 蔵王町地域公共交通計画 | G18: R4〜R8 | H18: 8 | I18: 確認済 | J18: 未確認 | K18: https://www.town.zao.miyagi.jp/kurashi_guide/seikatsu_kankyo/koutuu/koukyoukoutsuu.html | L18: 第2次蔵王町環境基本計画 | M18: R5〜R14 | N18: 14 | O18: 確認済 | P18: 未確認 | Q18: https://town.zao.miyagi.jp/section/kankyo/kankyou/kihonkeikaku.files/kankyoukeikaku2.pdf | R18: 交通：R8(2026)年度終期。R8施政方針（R8.3.2）で次期計画策定に向けた準備に言及との検索要約あり https://www.town.zao.miyagi.jp/section/oshirase/hiroba/message.files/R8shisei.pdf 。交通計画策定支援業務の公告は未確認（町HP公募型プロポ一覧 https://town.zao.miyagi.jp/kurashi_guide/sangyo_kensetsu/nyuusatu/puropo.html 要確認・最有望）。概要版 https://www.town.zao.miyagi.jp/kurashi_guide/seikatsu_kankyo/koutuu/koukyoukoutsuu.files/koukyoukoutsuu_gaiyou0330.pdf 。関連：第六次長期総合計画策定支援プロポ（R8.6.5）https://www.town.zao.miyagi.jp/kurashi_guide/sangyo_kensetsu/nyuusatu/koukoku/soumu20260605.html 。広域の仙南地域公共交通計画は検索で確認できず。 | S18: 調査済 | T18: 掲載
A19: 16 | B19: 七ヶ宿町 | C19: =IF(OR(D19="◎",E19="◎"),"◎ 営業",IF(OR(D19="△",E19="△"),"△ 着手済・要確認",IF(OR(D19="？",E19="？"),"？ 期間要確認","✕ 対象外"))) | D19: =IF(J19="計画なし","－",IF(J19="策定済","✕",IF(H19="","？",IF(AND(H19>=TGT_MIN,H19<=TGT_MAX),IF(J19="着手済","△","◎"),"✕")))) | E19: =IF(P19="計画なし","－",IF(P19="策定済","✕",IF(N19="","？",IF(AND(N19>=TGT_MIN,N19<=TGT_MAX),IF(P19="着手済","△","◎"),"✕")))) | G19: 不明 | I19: 不明 | J19: 未確認 | M19: 不明 | O19: 不明 | P19: 計画なし | R19: 交通：町営バス3路線を運行（https://town.shichikashuku.miyagi.jp/life/bus.html）が、地域公共交通計画は町の計画一覧（https://town.shichikashuku.miyagi.jp/town/plan/）の検索結果に見当たらず。環境：環境基本計画は確認できず（計画なしと推定）、代替として再生可能エネルギー発電基本計画あり。広域の仙南地域計画も未確認。 | S19: 環境のみ調査 | T19: 未掲載
A20: 17 | B20: 大河原町 | C20: =IF(OR(D20="◎",E20="◎"),"◎ 営業",IF(OR(D20="△",E20="△"),"△ 着手済・要確認",IF(OR(D20="？",E20="？"),"？ 期間要確認","✕ 対象外"))) | D20: =IF(J20="計画なし","－",IF(J20="策定済","✕",IF(H20="","？",IF(AND(H20>=TGT_MIN,H20<=TGT_MAX),IF(J20="着手済","△","◎"),"✕")))) | E20: =IF(P20="計画なし","－",IF(P20="策定済","✕",IF(N20="","？",IF(AND(N20>=TGT_MIN,N20<=TGT_MAX),IF(P20="着手済","△","◎"),"✕")))) | G20: 不明 | I20: 不明 | J20: 未確認 | K20: https://www.town.ogawara.miyagi.jp/1292.htm | L20: 第2次大河原町環境基本計画 | M20: R7〜（終期不明） | O20: 推定 | P20: 策定済 | Q20: https://www.town.ogawara.miyagi.jp/7882.htm | R20: 交通：大河原町地域公共交通協議会（https://www.town.ogawara.miyagi.jp/1292.htm）とデマンド型乗合タクシー（H24〜）は確認、法定の地域公共交通計画の名称・期間は検索で確認できず。広域の仙南地域公共交通計画も未確認。環境：第1次はH23〜R6、後継の第2次の策定ページあり（期間は検索結果に記載なし、R7開始と推定・採択時期要確認）。 | S20: 調査済 | T20: 未掲載【当方は計画あり】
A21: 18 | B21: 村田町 | C21: =IF(OR(D21="◎",E21="◎"),"◎ 営業",IF(OR(D21="△",E21="△"),"△ 着手済・要確認",IF(OR(D21="？",E21="？"),"？ 期間要確認","✕ 対象外"))) | D21: =IF(J21="計画なし","－",IF(J21="策定済","✕",IF(H21="","？",IF(AND(H21>=TGT_MIN,H21<=TGT_MAX),IF(J21="着手済","△","◎"),"✕")))) | E21: =IF(P21="計画なし","－",IF(P21="策定済","✕",IF(N21="","？",IF(AND(N21>=TGT_MIN,N21<=TGT_MAX),IF(P21="着手済","△","◎"),"✕")))) | G21: 不明 | I21: 不明 | J21: 未確認 | M21: 不明 | O21: 不明 | P21: 計画なし | R21: 交通：村田町地域公共交通会議（道路運送法）設置要綱 https://www.town.murata.miyagi.jp/cyosei/on-line/reiki_int/reiki_honbun/c215RG00000781.html 、町民バス等運行 https://www.town.murata.miyagi.jp/kurashi/kostu/bus/index.html 。法定の地域公共交通計画は検索で確認できず（未策定の可能性）。環境：環境基本計画は町HP検索で見当たらず（計画なしと推定）。広域の仙南地域計画も未確認。 | S21: 環境のみ調査 | T21: 未掲載
A22: 19 | B22: 柴田町 | C22: =IF(OR(D22="◎",E22="◎"),"◎ 営業",IF(OR(D22="△",E22="△"),"△ 着手済・要確認",IF(OR(D22="？",E22="？"),"？ 期間要確認","✕ 対象外"))) | D22: =IF(J22="計画なし","－",IF(J22="策定済","✕",IF(H22="","？",IF(AND(H22>=TGT_MIN,H22<=TGT_MAX),IF(J22="着手済","△","◎"),"✕")))) | E22: =IF(P22="計画なし","－",IF(P22="策定済","✕",IF(N22="","？",IF(AND(N22>=TGT_MIN,N22<=TGT_MAX),IF(P22="着手済","△","◎"),"✕")))) | F22: 阿武隈急行線地域公共交通計画（福島市・伊達市・角田市・柴田町・丸森町・両県共同） | G22: R7〜（詳細不明） | I22: 不明 | J22: 策定済 | K22: https://www.pref.miyagi.jp/soshiki/soukou/abukumakyougikai-keikaku2.html | L22: 第3次柴田町環境基本計画 | M22: R5〜R14（推定） | N22: 14 | O22: 推定 | P22: 未確認 | Q22: https://www.town.shibata.miyagi.jp/index.cfm/82,54128,c,html/54128/20230329-105154.pdf | R22: 交通：町単独の地域公共交通計画は検索で見当たらず（デマンド型乗合タクシー「はなみちゃんGO」運行）。阿武隈急行線沿線協議会が旧網形成計画（2019〜2028）の後継として新計画を策定、パブコメR7.11.7〜11.27、結果公表R7.12.22。宮城県地域公共交通計画（R8〜R14）も町域を含む https://www.pref.miyagi.jp/soshiki/soukou/20240520.html 。環境：R5.3策定の第3次計画、R5〜R14の10年間（検索要約で言及、本文未検証のため推定）。 | S22: 調査済 | T22: 掲載（広域：阿武隈急行線地域）
A23: 20 | B23: 川崎町 | C23: =IF(OR(D23="◎",E23="◎"),"◎ 営業",IF(OR(D23="△",E23="△"),"△ 着手済・要確認",IF(OR(D23="？",E23="？"),"？ 期間要確認","✕ 対象外"))) | D23: =IF(J23="計画なし","－",IF(J23="策定済","✕",IF(H23="","？",IF(AND(H23>=TGT_MIN,H23<=TGT_MAX),IF(J23="着手済","△","◎"),"✕")))) | E23: =IF(P23="計画なし","－",IF(P23="策定済","✕",IF(N23="","？",IF(AND(N23>=TGT_MIN,N23<=TGT_MAX),IF(P23="着手済","△","◎"),"✕")))) | F23: 川崎町地域公共交通総合連携計画（旧制度計画） | G23: 不明 | I23: 不明 | J23: 未確認 | K23: https://www.town.kawasaki.miyagi.jp/soshiki/chishin/484.html | M23: 不明 | O23: 不明 | P23: 計画なし | R23: 交通：町の計画は旧法の総合連携計画のみ確認（期間不明、失効の可能性大）。地域公共交通計画（活性化再生法改正後）は未確認。ミヤコーバス川崎線（村田〜川崎）がR8.10.1廃止予定との県資料あり https://www.pref.miyagi.jp/documents/66328/09_siryou09_.pdf ―公共交通再編・計画策定ニーズあり。宮城県地域公共交通計画（R8〜R14）が町域を含む。環境：環境基本計画は検索で見当たらず。代替として川崎町地球温暖化対策実行計画（各種計画ページ、R7.4.1更新） https://www.town.kawasaki.miyagi.jp/life/6/30/124/ 。 | S23: 調査済 | T23: 未掲載【当方は計画あり】
A24: 21 | B24: 丸森町 | C24: =IF(OR(D24="◎",E24="◎"),"◎ 営業",IF(OR(D24="△",E24="△"),"△ 着手済・要確認",IF(OR(D24="？",E24="？"),"？ 期間要確認","✕ 対象外"))) | D24: =IF(J24="計画なし","－",IF(J24="策定済","✕",IF(H24="","？",IF(AND(H24>=TGT_MIN,H24<=TGT_MAX),IF(J24="着手済","△","◎"),"✕")))) | E24: =IF(P24="計画なし","－",IF(P24="策定済","✕",IF(N24="","？",IF(AND(N24>=TGT_MIN,N24<=TGT_MAX),IF(P24="着手済","△","◎"),"✕")))) | F24: 丸森町地域公共交通計画 | G24: R6〜R10（推定） | H24: 10 | I24: 推定 | J24: 未確認 | K24: http://www.town.marumori.miyagi.jp/common/img/content/content_20240411_180249.pdf | M24: 不明 | O24: 不明 | P24: 計画なし | R24: 交通：R5年度第4回地域公共交通会議でパブコメ結果報告、R6.4公表（計画ページ https://www.town.marumori.miyagi.jp/life/detail.php?content=1312 ）。期間は5年と推定。阿武隈急行線地域公共交通計画（共同、R7年度策定、パブコメR7.11）も町域を含む https://www.pref.miyagi.jp/soshiki/soukou/abukumakyougikai-keikaku2.html 。環境：環境基本計画は町サイト検索で見当たらず（第六次総合計画2025-2034等のみ）。 | S24: 調査済 | T24: 掲載（広域：阿武隈急行線地域）
A25: 22 | B25: 亘理町 | C25: =IF(OR(D25="◎",E25="◎"),"◎ 営業",IF(OR(D25="△",E25="△"),"△ 着手済・要確認",IF(OR(D25="？",E25="？"),"？ 期間要確認","✕ 対象外"))) | D25: =IF(J25="計画なし","－",IF(J25="策定済","✕",IF(H25="","？",IF(AND(H25>=TGT_MIN,H25<=TGT_MAX),IF(J25="着手済","△","◎"),"✕")))) | E25: =IF(P25="計画なし","－",IF(P25="策定済","✕",IF(N25="","？",IF(AND(N25>=TGT_MIN,N25<=TGT_MAX),IF(P25="着手済","△","◎"),"✕")))) | F25: 亘理町地域公共交通計画 | G25: R6〜R10 | H25: 10 | I25: 確認済 | J25: 未確認 | K25: https://www.town.watari.miyagi.jp/town/detail.php?content=1730 | L25: 第2次亘理町環境基本計画 | M25: 不明（R4.1頃公表） | O25: 不明 | P25: 未確認 | Q25: https://www.town.watari.miyagi.jp/common/img/content/content_20220126_163920.pdf | R25: 交通：パブコメR6.2.2〜2.16（https://www.town.watari.miyagi.jp/town/detail.php?content=1686 ）、R6.3策定、R6〜R10（5年）。本編PDF https://www.town.watari.miyagi.jp/common/img/content/content_20240405_084913.pdf 。環境：第2次計画の存在は検索で確認、期間は未確認（e_urlは環境基本計画関連と思われるPDF、町サイトはWebFetch遮断で未検証）。地球温暖化対策実行計画（区域施策編）も策定済 https://www.town.watari.miyagi.jp/town/detail.php?content=1811 。亘理・山元の共同交通計画は見当たらず（各町単独）。 【追加調査 2026-10】環境：第2次亘理町環境基本計画の存在は再確認（e_urlのPDF content_20220126_163920 が上位ヒット、R4.1頃公表）が、期間は検索3回とも本文に出ず不明のまま（R4開始10年ならR13終期の可能性）。町の環境・ごみカテゴリ https://www.town.watari.miyagi.jp/life/category/?category=124 。 | S25: 調査済 | T25: 掲載
A26: 23 | B26: 山元町 | C26: =IF(OR(D26="◎",E26="◎"),"◎ 営業",IF(OR(D26="△",E26="△"),"△ 着手済・要確認",IF(OR(D26="？",E26="？"),"？ 期間要確認","✕ 対象外"))) | D26: =IF(J26="計画なし","－",IF(J26="策定済","✕",IF(H26="","？",IF(AND(H26>=TGT_MIN,H26<=TGT_MAX),IF(J26="着手済","△","◎"),"✕")))) | E26: =IF(P26="計画なし","－",IF(P26="策定済","✕",IF(N26="","？",IF(AND(N26>=TGT_MIN,N26<=TGT_MAX),IF(P26="着手済","△","◎"),"✕")))) | F26: 山元町地域公共交通計画（R7.7変更） | G26: R6〜R10 | H26: 10 | I26: 確認済 | J26: 未確認 | K26: https://www.town.yamamoto.miyagi.jp/uploaded/attachment/19314.pdf | M26: 不明 | O26: 不明 | P26: 計画なし | R26: 交通：H30.3網形成計画の後継としてR6.3策定、R7.7一部変更、計画ページ https://www.town.yamamoto.miyagi.jp/soshiki/9/24881.html 。パブコメR6.2.27〜3.11。町民バス「ぐるりん号」R7.1運行改正。環境：町サイト検索で環境基本計画は見当たらず。 | S26: 調査済 | T26: 掲載
A27: 24 | B27: 松島町 | C27: =IF(OR(D27="◎",E27="◎"),"◎ 営業",IF(OR(D27="△",E27="△"),"△ 着手済・要確認",IF(OR(D27="？",E27="？"),"？ 期間要確認","✕ 対象外"))) | D27: =IF(J27="計画なし","－",IF(J27="策定済","✕",IF(H27="","？",IF(AND(H27>=TGT_MIN,H27<=TGT_MAX),IF(J27="着手済","△","◎"),"✕")))) | E27: =IF(P27="計画なし","－",IF(P27="策定済","✕",IF(N27="","？",IF(AND(N27>=TGT_MIN,N27<=TGT_MAX),IF(P27="着手済","△","◎"),"✕")))) | F27: 松島町の交通関係計画（H29年度策定、正式名称未確認・期間満了） | G27: 不明 | I27: 不明 | J27: 未確認 | M27: 不明 | O27: 不明 | P27: 計画なし | R27: 交通・環境とも町独自計画は検索で確認できず（町サイトの検索インデックスが薄く、存在しない確証はない＝要確認）。宮城県地域公共交通計画（R8〜R14）が町域を含む https://www.pref.miyagi.jp/soshiki/soukou/20240520.html 。 【追加調査 2026-10】交通(2026-10調査)：国交省一覧(R8.5末)では町単独計画あり・期間満了（灰色）。R7.3.4第1回定例会会議録（https://www.town.miyagi-matsushima.lg.jp/uploaded/attachment/2895.pdf ）の検索要約で、町当局が「交通関係の計画はH29年度に策定、現時点で見直しの具体的予定なし」と答弁（北部地区デマンド交通実証H30〜R1は利用低迷で導入見送り）。計画名・期間は検索で特定できず（町サイトに計画書の掲載見当たらず）。次期計画の着手（委託・パブコメ等）も確認できず。宮城県地域公共交通計画（R8〜R14）が町域をカバー。 根拠: （検索要約）a transportation-related plan was formulated in fiscal year 2017 ... no specific plans for revision | S27: 調査済 | T27: 掲載／期間満了
A28: 25 | B28: 七ヶ浜町 | C28: =IF(OR(D28="◎",E28="◎"),"◎ 営業",IF(OR(D28="△",E28="△"),"△ 着手済・要確認",IF(OR(D28="？",E28="？"),"？ 期間要確認","✕ 対象外"))) | D28: =IF(J28="計画なし","－",IF(J28="策定済","✕",IF(H28="","？",IF(AND(H28>=TGT_MIN,H28<=TGT_MAX),IF(J28="着手済","△","◎"),"✕")))) | E28: =IF(P28="計画なし","－",IF(P28="策定済","✕",IF(N28="","？",IF(AND(N28>=TGT_MIN,N28<=TGT_MAX),IF(P28="着手済","△","◎"),"✕")))) | G28: 不明 | I28: 不明 | J28: 計画なし | M28: 不明 | O28: 不明 | P28: 計画なし | R28: 交通：町独自の地域公共交通計画は検索で確認できず。町民バス「ぐるりんこ」についてR7.7にアンケート調査を実施し、運行計画見直しに活用予定 https://www.shichigahama.com/benricho/oshirase/sanka3-100-12175.html 。R8.4.1ダイヤ改正。計画策定に発展する可能性あり（要確認・有望）。宮城県地域公共交通計画（R8〜R14）が町域を含む。環境：環境基本計画は町サイト検索で見当たらず。 | S28: 環境のみ調査 | T28: 未掲載
A29: 26 | B29: 利府町 | C29: =IF(OR(D29="◎",E29="◎"),"◎ 営業",IF(OR(D29="△",E29="△"),"△ 着手済・要確認",IF(OR(D29="？",E29="？"),"？ 期間要確認","✕ 対象外"))) | D29: =IF(J29="計画なし","－",IF(J29="策定済","✕",IF(H29="","？",IF(AND(H29>=TGT_MIN,H29<=TGT_MAX),IF(J29="着手済","△","◎"),"✕")))) | E29: =IF(P29="計画なし","－",IF(P29="策定済","✕",IF(N29="","？",IF(AND(N29>=TGT_MIN,N29<=TGT_MAX),IF(P29="着手済","△","◎"),"✕")))) | F29: 利府町地域公共交通計画（改定版） | G29: R5〜（期間不明） | I29: 不明 | J29: 未確認 | K29: https://www.town.rifu.miyagi.jp/gyosei/soshikikarasagasu/seikatu/koukyoukoutu/1/1162.html | M29: 不明 | O29: 不明 | P29: 計画なし | R29: 交通：2023年策定、AIデマンド「利府町版mobi」（R5.11.27実証開始→本格運行）を受けて改定。期間は検索で確認できず（2023年策定・5年なら R9終期の可能性あり＝要確認）。協議会 https://www.town.rifu.miyagi.jp/gyosei/soshikikarasagasu/seikatu/koukyoukoutu/1/779.html 。環境：環境基本計画は見当たらず。代替として地球温暖化対策実行計画（事務事業編）第3期（2018〜2030） https://www.town.rifu.miyagi.jp/gyosei/soshikikarasagasu/seikatu/kankyou/4/669.html 。 | S29: 調査済 | T29: 掲載
A30: 27 | B30: 大和町 | C30: =IF(OR(D30="◎",E30="◎"),"◎ 営業",IF(OR(D30="△",E30="△"),"△ 着手済・要確認",IF(OR(D30="？",E30="？"),"？ 期間要確認","✕ 対象外"))) | D30: =IF(J30="計画なし","－",IF(J30="策定済","✕",IF(H30="","？",IF(AND(H30>=TGT_MIN,H30<=TGT_MAX),IF(J30="着手済","△","◎"),"✕")))) | E30: =IF(P30="計画なし","－",IF(P30="策定済","✕",IF(N30="","？",IF(AND(N30>=TGT_MIN,N30<=TGT_MAX),IF(P30="着手済","△","◎"),"✕")))) | F30: 大和町地域公共交通計画 | G30: R6〜R10 | H30: 10 | I30: 確認済 | J30: 未確認 | K30: https://www.town.taiwa.miyagi.jp/soshiki/machizukuriseisaku/machizukuri_suishin/bustaxi/3547.html | L30: 大和町第三次環境基本計画 | M30: R6〜R15 | N30: 15 | O30: 確認済 | P30: 未確認 | Q30: https://www.town.taiwa.miyagi.jp/soshiki/chominseikatsu/seikatsukankyo/3718.html | R30: 交通：R6〜R10の5年計画。協議会 https://www.town.taiwa.miyagi.jp/soshiki/machizukuriseisaku/machizukuri_suishin/taiwatownkaigi/4244.html 。環境：第五次総合計画の分野計画、R6〜R15。改定作業は両計画とも未確認（時期的に未着手が自然）。 | S30: 調査済 | T30: 掲載
A31: 28 | B31: 大郷町 | C31: =IF(OR(D31="◎",E31="◎"),"◎ 営業",IF(OR(D31="△",E31="△"),"△ 着手済・要確認",IF(OR(D31="？",E31="？"),"？ 期間要確認","✕ 対象外"))) | D31: =IF(J31="計画なし","－",IF(J31="策定済","✕",IF(H31="","？",IF(AND(H31>=TGT_MIN,H31<=TGT_MAX),IF(J31="着手済","△","◎"),"✕")))) | E31: =IF(P31="計画なし","－",IF(P31="策定済","✕",IF(N31="","？",IF(AND(N31>=TGT_MIN,N31<=TGT_MAX),IF(P31="着手済","△","◎"),"✕")))) | G31: 不明 | I31: 不明 | J31: 未確認 | M31: 不明 | O31: 不明 | P31: 未確認 | R31: 交通：町単独・黒川地域共同の地域公共交通計画は検索で確認できず（町民バス運行のみの可能性）。宮城県地域公共交通計画（次期R8〜R14、7年間）が県全域を対象 https://www.pref.miyagi.jp/documents/59495/07thedraftplanoflptp.pdf。環境：町独自の環境基本計画は検索で確認できず。 【追加調査 2026-10】環境：一般検索・町ドメイン限定検索（town.miyagi-osato.lg.jp）とも環境基本計画はヒットせず。総合計画 https://www.town.miyagi-osato.lg.jp/soshiki/machidukuri/sougoukeikaku2025.html の環境分野で対応している模様。計画なしの可能性が高いが、計画一覧での明確な根拠はなく未断定。 | S31: 未調査 | T31: 未掲載
A32: 29 | B32: 大衡村 | C32: =IF(OR(D32="◎",E32="◎"),"◎ 営業",IF(OR(D32="△",E32="△"),"△ 着手済・要確認",IF(OR(D32="？",E32="？"),"？ 期間要確認","✕ 対象外"))) | D32: =IF(J32="計画なし","－",IF(J32="策定済","✕",IF(H32="","？",IF(AND(H32>=TGT_MIN,H32<=TGT_MAX),IF(J32="着手済","△","◎"),"✕")))) | E32: =IF(P32="計画なし","－",IF(P32="策定済","✕",IF(N32="","？",IF(AND(N32>=TGT_MIN,N32<=TGT_MAX),IF(P32="着手済","△","◎"),"✕")))) | G32: 不明 | I32: 不明 | J32: 未確認 | M32: 不明 | O32: 不明 | P32: 計画なし | R32: 交通：村単独・黒川地域共同の地域公共交通計画は検索で確認できず。宮城県地域公共交通計画（次期R8〜R14、7年間）が県全域を対象 https://www.pref.miyagi.jp/documents/59495/07thedraftplanoflptp.pdf。環境：環境基本計画は確認できず。代替として第5次大衡村地球温暖化対策実行計画（事務事業編、R5〜R12）あり。 | S32: 環境のみ調査 | T32: 未掲載
A33: 30 | B33: 色麻町 | C33: =IF(OR(D33="◎",E33="◎"),"◎ 営業",IF(OR(D33="△",E33="△"),"△ 着手済・要確認",IF(OR(D33="？",E33="？"),"？ 期間要確認","✕ 対象外"))) | D33: =IF(J33="計画なし","－",IF(J33="策定済","✕",IF(H33="","？",IF(AND(H33>=TGT_MIN,H33<=TGT_MAX),IF(J33="着手済","△","◎"),"✕")))) | E33: =IF(P33="計画なし","－",IF(P33="策定済","✕",IF(N33="","？",IF(AND(N33>=TGT_MIN,N33<=TGT_MAX),IF(P33="着手済","△","◎"),"✕")))) | G33: 不明 | I33: 不明 | J33: 未確認 | M33: 不明 | O33: 不明 | P33: 未確認 | R33: 交通：町単独計画は確認できず。大崎定住自立圏（大崎市・色麻・加美・涌谷・美里）で大崎圏域公共交通検討研究会を開催し圏域交通を検討 https://www.pref.miyagi.jp/site/tiikisinnkou/teizyu.html 。宮城県地域公共交通計画（次期R8〜R14、7年間）が県全域を対象 https://www.pref.miyagi.jp/documents/59495/07thedraftplanoflptp.pdf。環境：環境基本計画は検索で確認できず。 【追加調査 2026-10】環境：一般検索・町ドメイン限定検索とも環境基本計画はヒットせず。町議会会議録で地球温暖化対策実行計画・ゼロカーボン関連の言及のみ。町の政策・施策一覧 https://www.town.shikama.miyagi.jp/chosei/seisaku_shisaku/index.html で要確認。計画なしの可能性が高いが未断定。 | S33: 未調査 | T33: 未掲載
A34: 31 | B34: 加美町 | C34: =IF(OR(D34="◎",E34="◎"),"◎ 営業",IF(OR(D34="△",E34="△"),"△ 着手済・要確認",IF(OR(D34="？",E34="？"),"？ 期間要確認","✕ 対象外"))) | D34: =IF(J34="計画なし","－",IF(J34="策定済","✕",IF(H34="","？",IF(AND(H34>=TGT_MIN,H34<=TGT_MAX),IF(J34="着手済","△","◎"),"✕")))) | E34: =IF(P34="計画なし","－",IF(P34="策定済","✕",IF(N34="","？",IF(AND(N34>=TGT_MIN,N34<=TGT_MAX),IF(P34="着手済","△","◎"),"✕")))) | G34: 不明 | I34: 不明 | J34: 着手済 | L34: 加美町環境基本計画（改定版） | M34: R5〜R14 | N34: 14 | O34: 確認済 | P34: 未確認 | Q34: https://www.town.kami.miyagi.jp/soshikikarasagasu/chominka/kankyoeisei/3689.html | R34: 交通：町の地域公共交通計画は未策定とみられ、第三次加美町総合計画策定の経緯資料に「地域公共交通計画」の策定が言及されている（策定作業中の可能性、要確認）https://www.town.kami.miyagi.jp/material/files/group/6/2-keii.pdf 。住民バスはR7.4.1から新体系で運行。大崎定住自立圏で圏域公共交通検討研究会あり。環境：H19.3初版、R5.3改定版策定（10年間）。地球温暖化対策実行計画（区域施策編・事務事業編）R7.1策定 https://www.town.kami.miyagi.jp/material/files/group/60/gaiyou2.pdf | S34: 環境のみ調査 | T34: 未掲載
A35: 32 | B35: 涌谷町 | C35: =IF(OR(D35="◎",E35="◎"),"◎ 営業",IF(OR(D35="△",E35="△"),"△ 着手済・要確認",IF(OR(D35="？",E35="？"),"？ 期間要確認","✕ 対象外"))) | D35: =IF(J35="計画なし","－",IF(J35="策定済","✕",IF(H35="","？",IF(AND(H35>=TGT_MIN,H35<=TGT_MAX),IF(J35="着手済","△","◎"),"✕")))) | E35: =IF(P35="計画なし","－",IF(P35="策定済","✕",IF(N35="","？",IF(AND(N35>=TGT_MIN,N35<=TGT_MAX),IF(P35="着手済","△","◎"),"✕")))) | F35: 涌谷町地域公共交通計画 | G35: R7〜R12 | H35: 12 | I35: 確認済 | J35: 策定済 | K35: https://www.town.wakuya.miyagi.jp/documents/honpen.pdf | M35: 不明 | O35: 不明 | P35: 計画なし | R35: 交通：R7(2025)年度開始の新計画（策定ページ https://www.town.wakuya.miyagi.jp/koutukeikaku1.html ）。地域公共交通会議R7.5.28、R8.1開催。環境：環境基本計画は町サイト検索で確認できず（計画なしとみられる）。第六次涌谷町総合計画（R8〜）策定済。 | S35: 調査済 | T35: 掲載
A36: 33 | B36: 美里町 | C36: =IF(OR(D36="◎",E36="◎"),"◎ 営業",IF(OR(D36="△",E36="△"),"△ 着手済・要確認",IF(OR(D36="？",E36="？"),"？ 期間要確認","✕ 対象外"))) | D36: =IF(J36="計画なし","－",IF(J36="策定済","✕",IF(H36="","？",IF(AND(H36>=TGT_MIN,H36<=TGT_MAX),IF(J36="着手済","△","◎"),"✕")))) | E36: =IF(P36="計画なし","－",IF(P36="策定済","✕",IF(N36="","？",IF(AND(N36>=TGT_MIN,N36<=TGT_MAX),IF(P36="着手済","△","◎"),"✕")))) | G36: 不明 | I36: 不明 | J36: 未確認 | M36: 不明 | O36: 不明 | P36: 計画なし | R36: 交通：地域公共交通計画は町サイト検索で確認できず。美里町地域公共交通会議は活動中（R8.2.13会議録あり）https://www.town.misato.miyagi.jp/16bus/ 。大崎定住自立圏の圏域公共交通検討研究会に参加。環境：環境基本計画は確認できず、代替として美里町再生可能エネルギー導入推進計画（R4.4）https://www.town.misato.miyagi.jp/08kankyo/pdf/saiseikanou.pdf 。 | S36: 環境のみ調査 | T36: 未掲載
A37: 34 | B37: 女川町 | C37: =IF(OR(D37="◎",E37="◎"),"◎ 営業",IF(OR(D37="△",E37="△"),"△ 着手済・要確認",IF(OR(D37="？",E37="？"),"？ 期間要確認","✕ 対象外"))) | D37: =IF(J37="計画なし","－",IF(J37="策定済","✕",IF(H37="","？",IF(AND(H37>=TGT_MIN,H37<=TGT_MAX),IF(J37="着手済","△","◎"),"✕")))) | E37: =IF(P37="計画なし","－",IF(P37="策定済","✕",IF(N37="","？",IF(AND(N37>=TGT_MIN,N37<=TGT_MAX),IF(P37="着手済","△","◎"),"✕")))) | F37: 女川町地域公共交通計画 | G37: R6〜R10 | H37: 10 | I37: 確認済 | J37: 未確認 | K37: https://www.town.onagawa.miyagi.jp/pdf/koutsuu/koutsu_keikaku_gaiyou.pdf | M37: 不明 | O37: 不明 | P37: 計画なし | R37: 交通：R6.3策定（5年間）。本編 https://town.onagawa.miyagi.jp/pdf/koutsuu/kokyo_koutsu_keikaku.pdf 。R8年度第1回地域公共交通会議資料あり https://www.town.onagawa.miyagi.jp/pdf/koutsuu/r08koutsuukaigi01_siryo1.pdf 。次期計画作業は未確認（R10終期）。環境：環境基本計画は確認できず。代替として女川町地球温暖化対策実行計画（事務事業編、R6.3）https://town.onagawa.miyagi.jp/pdf/kankyo/2024_ondanka_taisaku.pdf | S37: 調査済 | T37: 掲載
A38: 35 | B38: 南三陸町 | C38: =IF(OR(D38="◎",E38="◎"),"◎ 営業",IF(OR(D38="△",E38="△"),"△ 着手済・要確認",IF(OR(D38="？",E38="？"),"？ 期間要確認","✕ 対象外"))) | D38: =IF(J38="計画なし","－",IF(J38="策定済","✕",IF(H38="","？",IF(AND(H38>=TGT_MIN,H38<=TGT_MAX),IF(J38="着手済","△","◎"),"✕")))) | E38: =IF(P38="計画なし","－",IF(P38="策定済","✕",IF(N38="","？",IF(AND(N38>=TGT_MIN,N38<=TGT_MAX),IF(P38="着手済","△","◎"),"✕")))) | F38: 南三陸町地域公共交通計画 | G38: R8〜（終期不明） | I38: 推定 | J38: 策定済 | K38: https://www.town.minamisanriku.miyagi.jp/material/files/group/3/202602042.pdf | L38: 第2次南三陸町環境基本計画 | M38: R8〜R17 | N38: 17 | O38: 確認済 | P38: 策定済 | Q38: https://www.town.minamisanriku.miyagi.jp/material/files/group/7/keikakusyo.pdf | R38: 交通：前計画は南三陸町地域公共交通網形成計画（H31.3策定）。後継の地域公共交通計画（案）令和8年3月版の資料がR8.2.4頃公開（t_urlは案の資料編）。R8.3策定とみられるが最終版・期間は未確認。環境：第2次計画R8〜R17（R7年度中に策定）。 | S38: 調査済 | T38: 掲載

Sheet 秋田県
A1: 秋田県 地域公共交通計画・環境基本計画の終期一覧（2026年9月30日時点の調査）
A2: ="営業判定の対象：終期 R"&TGT_MIN&"〜R"&TGT_MAX&"年度 →◎（着手済は△、期間不明は？）。終期セルの色：緑＝対象年度／橙＝その翌年度（次の候補）。対象年度は「集計・設定」シートのC4・C5のプルダウンで切替。"
A3: No | B3: 市町村 | C3: 営業判定 | D3: 交通判定 | E3: 環境判定 | F3: 地域公共交通計画 | G3: 交通 計画期間 | H3: 交通 終期(令和年度) | I3: 交通 確度 | J3: 交通 改定状況 | K3: 交通 計画リンク（エビデンス） | L3: 環境基本計画 | M3: 環境 計画期間 | N3: 環境 終期(令和年度) | O3: 環境 確度 | P3: 環境 改定状況 | Q3: 環境 計画リンク（エビデンス） | R3: 注釈（改定作業の状況など） | S3: 調査状況 | T3: 国交省一覧(R8.5末)
A4: 1 | B4: 秋田市 | C4: =IF(OR(D4="◎",E4="◎"),"◎ 営業",IF(OR(D4="△",E4="△"),"△ 着手済・要確認",IF(OR(D4="？",E4="？"),"？ 期間要確認","✕ 対象外"))) | D4: =IF(J4="計画なし","－",IF(J4="策定済","✕",IF(H4="","？",IF(AND(H4>=TGT_MIN,H4<=TGT_MAX),IF(J4="着手済","△","◎"),"✕")))) | E4: =IF(P4="計画なし","－",IF(P4="策定済","✕",IF(N4="","？",IF(AND(N4>=TGT_MIN,N4<=TGT_MAX),IF(P4="着手済","△","◎"),"✕")))) | F4: 第4次秋田市公共交通政策ビジョン（秋田市地域公共交通計画） | G4: R8〜R12 | H4: 12 | I4: 確認済 | J4: 策定済 | K4: https://www.city.akita.lg.jp/_res/projects/default_project/_page_/001/049/732/koukyoukoutuuseisakubijonn080306.pdf | L4: 秋田市環境基本計画（R5.3中間見直し版） | M4: H30〜R9 | N4: 9 | O4: 確認済 | P4: 着手済 | Q4: https://www.city.akita.lg.jp/_res/projects/default_project/_page_/001/006/108/keikaku23.pdf | R4: 交通：前計画（第3次公共交通政策ビジョン R3〜R7）の後継として第4次ビジョン（地域公共交通計画）R8.3策定。関連ページ https://www.city.akita.lg.jp/kurashi/kotsu/1007422/1028662.html 。環境：H30〜R9の10年計画、R4〜R5に中間見直し（パブコメR4.12〜R5.1）。R9終期のため次期計画はR8〜R9に策定見込みだが、着手（審議会・委託等）は検索で未確認（有望）。計画ページ https://www.city.akita.lg.jp/shisei/hoshin-keikaku/1009930/1006108.html 【ファクトチェック 2026-10-01: 正しい】確認期間: H30〜R9（平成30年度〜令和9年度の10年間、R5.3中間見直し）／次期: 着手済：第45回秋田市環境審議会（令和8年3月24日）議題「秋田市環境基本計画の改定について」（資料1あり）https://www.city.akita.lg.jp/kurashi/recycle/1016631/1006116.html／根拠: https://www.city.akita.lg.jp/_res/projects/default_project/_page_/001/006/108/r2-1nenhoukoku.pdf | S4: 調査済 | T4: 掲載
A5: 2 | B5: 能代市 | C5: =IF(OR(D5="◎",E5="◎"),"◎ 営業",IF(OR(D5="△",E5="△"),"△ 着手済・要確認",IF(OR(D5="？",E5="？"),"？ 期間要確認","✕ 対象外"))) | D5: =IF(J5="計画なし","－",IF(J5="策定済","✕",IF(H5="","？",IF(AND(H5>=TGT_MIN,H5<=TGT_MAX),IF(J5="着手済","△","◎"),"✕")))) | E5: =IF(P5="計画なし","－",IF(P5="策定済","✕",IF(N5="","？",IF(AND(N5>=TGT_MIN,N5<=TGT_MAX),IF(P5="着手済","△","◎"),"✕")))) | F5: 能代市地域公共交通計画 | G5: R6〜（終期不明） | I5: 不明 | J5: 未確認 | K5: https://www.city.noshiro.lg.jp/sangyo/kokyo-kotsu/kokyokoutsu-keikaku/24040 | L5: 第2次能代市環境基本計画（R5.3見直し） | M5: H30〜R9 | N5: 9 | O5: 確認済 | P5: 未確認 | Q5: https://www.city.noshiro.lg.jp/sangyo/kankyo/keikaku/22091 | R5: 交通：R6.3策定（前計画は能代市地域公共交通網形成計画 H31.3策定）。市単独計画で能代山本広域の共同計画は確認できず。終期は検索で確認できず。環境：H30〜R9の10年計画、R5.3中間見直し（PDF https://www.city.noshiro.lg.jp/up/files/www/sangyo/kankyo/keikaku/keikaku_minaoshi_2nd.pdf ）。R9終期のため第3次計画はR8〜R9策定見込み、着手は未確認（有望）。環境基本計画懇談会の資料あり https://www.city.noshiro.lg.jp/up/files/www/sangyo/kankyo/keikaku/kondankai/1st/shiryo2_jokyo-kongo.pdf （開催時期未確認）。 R8.6に市民意識調査実施（https://www.city.noshiro.lg.jp/city/koho/ishiki-chosa/27883 、総合計画向けで環境計画専用ではない）。 【ファクトチェック 2026-10-01: 正しい】確認期間: H30〜R9（平成30年度〜令和9年度の10年間、R5.3中間見直し）／次期: 確認できず／根拠: https://www.city.noshiro.lg.jp/sangyo/kankyo/keikaku/22091 | S5: 調査済 | T5: 掲載
A6: 3 | B6: 横手市 | C6: =IF(OR(D6="◎",E6="◎"),"◎ 営業",IF(OR(D6="△",E6="△"),"△ 着手済・要確認",IF(OR(D6="？",E6="？"),"？ 期間要確認","✕ 対象外"))) | D6: =IF(J6="計画なし","－",IF(J6="策定済","✕",IF(H6="","？",IF(AND(H6>=TGT_MIN,H6<=TGT_MAX),IF(J6="着手済","△","◎"),"✕")))) | E6: =IF(P6="計画なし","－",IF(P6="策定済","✕",IF(N6="","？",IF(AND(N6>=TGT_MIN,N6<=TGT_MAX),IF(P6="着手済","△","◎"),"✕")))) | F6: 横手市地域公共交通計画 | G6: R6〜R10 | H6: 10 | I6: 確認済 | J6: 未確認 | K6: https://www.city.yokote.lg.jp/shisei/1001179/1001469/1001472/1003840.html | L6: 第3次横手市環境基本計画 | M6: R8〜R17 | N6: 17 | O6: 確認済 | P6: 策定済 | Q6: https://www.city.yokote.lg.jp/shisei/1001179/1001469/1001471/1003346.html | R6: 交通：R6.3策定（概要版 https://www.city.yokote.lg.jp/_res/projects/default_project/_page_/001/003/596/20240219_1-2.pdf ）。R10終期で次期作業は未確認。環境：第2次（H28〜）の後継として第3次（R8〜R17）を策定済（概要 https://www.city.yokote.lg.jp/_res/projects/default_project/_page_/001/003/346/dai3jigaiyou.pdf ）。 | S6: 調査済 | T6: 掲載
A7: 4 | B7: 大館市 | C7: =IF(OR(D7="◎",E7="◎"),"◎ 営業",IF(OR(D7="△",E7="△"),"△ 着手済・要確認",IF(OR(D7="？",E7="？"),"？ 期間要確認","✕ 対象外"))) | D7: =IF(J7="計画なし","－",IF(J7="策定済","✕",IF(H7="","？",IF(AND(H7>=TGT_MIN,H7<=TGT_MAX),IF(J7="着手済","△","◎"),"✕")))) | E7: =IF(P7="計画なし","－",IF(P7="策定済","✕",IF(N7="","？",IF(AND(N7>=TGT_MIN,N7<=TGT_MAX),IF(P7="着手済","△","◎"),"✕")))) | F7: 大館市地域公共交通計画（旧・地域公共交通網形成計画、R7.8改定） | G7: H30〜R9 | H7: 9 | I7: 確認済 | J7: 未確認 | K7: https://www.city.odate.lg.jp/city/soshiki/koutsu/p11901 | L7: 第3次大館市環境基本計画 | M7: R3〜R12 | N7: 12 | O7: 推定 | P7: 未確認 | Q7: https://www.city.odate.lg.jp/city/soshiki/kankyokikaku/p7909 | R7: 交通：H30.3策定の網形成計画（H30〜R9）をR6年度に地域公共交通計画へ名称変更・改定（R6.5『大館市地域公共交通網形成計画見直し業務』入札 https://nsearch.jp/nyusatsu_ankens/664c662d6a90d97d72380dee ）、R7.3/R7.8改定版PDFあり。R9(2027)終期のため次期計画策定はR8〜R9に着手見込みだが、策定業務プロポーザル等は検索で未確認（有望）。環境：第3次はR3.3パブコメを経て策定、期間は第2次(H23〜R2)の10年サイクルから推定。 R7.8改定版には『概ね10年後に見直し』との記載あり（計画期間はH30〜R9）。関連：大館市地域公共交通利便増進実施計画 https://www.mlit.go.jp/sogoseisaku/transport/content/001911965.pdf 【ファクトチェック 2026-10-01: 正しい】確認期間: H30〜R9（2018年度～2027年度）／次期: 確認できず（R7に利便増進実施計画（2025～2027年度）を策定済。次期計画の策定業務・協議会審議は未確認）／根拠: https://www.city.odate.lg.jp/uploads/public/pages_0000011901_00/R07.8%E6%9C%88%E6%94%B9%E6%AD%A3.%E5%A4%A7%E9%A4%A8%E5%B8%82%E5%9C%B0%E5%9F%9F%E5%85%AC%E5%85%B1%E4%BA%A4%E8%A8%88%E7%94%BB_.pdf | S7: 調査済 | T7: 掲載
A8: 5 | B8: 男鹿市 | C8: =IF(OR(D8="◎",E8="◎"),"◎ 営業",IF(OR(D8="△",E8="△"),"△ 着手済・要確認",IF(OR(D8="？",E8="？"),"？ 期間要確認","✕ 対象外"))) | D8: =IF(J8="計画なし","－",IF(J8="策定済","✕",IF(H8="","？",IF(AND(H8>=TGT_MIN,H8<=TGT_MAX),IF(J8="着手済","△","◎"),"✕")))) | E8: =IF(P8="計画なし","－",IF(P8="策定済","✕",IF(N8="","？",IF(AND(N8>=TGT_MIN,N8<=TGT_MAX),IF(P8="着手済","△","◎"),"✕")))) | F8: 男鹿市地域公共交通計画 | G8: R6〜R10 | H8: 10 | I8: 確認済 | J8: 未確認 | K8: https://www.city.oga.akita.jp/soshik/kikakuseisakuka/kakushukeikaku/6608.html | M8: 不明 | O8: 不明 | P8: 計画なし | R8: 交通：前計画は男鹿市地域公共交通網形成計画（https://www.city.oga.akita.jp/soshik/kikakuseisakuka/kakushukeikaku/1012.html ）。R10終期で次期作業は未確認。環境：環境基本計画は検索で見つからず（計画なしと推定、要確認）。環境省策定状況ページ https://www.env.go.jp/policy/local_keikaku/sakutei2/05/05206.html 。次期男鹿市総合計画を策定中（https://www.city.oga.akita.jp/soshik/kikakuseisakuka/1/8055.html ）。 | S8: 調査済 | T8: 掲載
A9: 6 | B9: 湯沢市 | C9: =IF(OR(D9="◎",E9="◎"),"◎ 営業",IF(OR(D9="△",E9="△"),"△ 着手済・要確認",IF(OR(D9="？",E9="？"),"？ 期間要確認","✕ 対象外"))) | D9: =IF(J9="計画なし","－",IF(J9="策定済","✕",IF(H9="","？",IF(AND(H9>=TGT_MIN,H9<=TGT_MAX),IF(J9="着手済","△","◎"),"✕")))) | E9: =IF(P9="計画なし","－",IF(P9="策定済","✕",IF(N9="","？",IF(AND(N9>=TGT_MIN,N9<=TGT_MAX),IF(P9="着手済","△","◎"),"✕")))) | F9: 湯沢市地域公共交通計画 | G9: R6〜R10 | H9: 10 | I9: 確認済 | J9: 未確認 | K9: https://www.city-yuzawa.jp/soshiki/31/5581.html | M9: 不明 | O9: 不明 | P9: 計画なし | R9: 交通：市単独計画（前計画は第2次湯沢市地域公共交通網形成計画 R2.2 https://www.city-yuzawa.jp/uploaded/attachment/13134.pdf ）。湯沢雄勝広域の共同計画は確認できず。R10終期で次期作業は未確認。新潟県湯沢町と混同注意。環境：環境基本計画は検索で見つからず（計画なしと推定、要確認）。第2次地球温暖化対策実行計画（事務事業編）R3策定、R4.6ゼロカーボンシティ宣言。環境省策定状況 https://www.env.go.jp/policy/local_keikaku/sakutei2/05/05207.html 。 | S9: 調査済 | T9: 掲載
A10: 7 | B10: 鹿角市 | C10: =IF(OR(D10="◎",E10="◎"),"◎ 営業",IF(OR(D10="△",E10="△"),"△ 着手済・要確認",IF(OR(D10="？",E10="？"),"？ 期間要確認","✕ 対象外"))) | D10: =IF(J10="計画なし","－",IF(J10="策定済","✕",IF(H10="","？",IF(AND(H10>=TGT_MIN,H10<=TGT_MAX),IF(J10="着手済","△","◎"),"✕")))) | E10: =IF(P10="計画なし","－",IF(P10="策定済","✕",IF(N10="","？",IF(AND(N10>=TGT_MIN,N10<=TGT_MAX),IF(P10="着手済","△","◎"),"✕")))) | F10: 鹿角市地域公共交通計画（令和7年6月改訂版） | G10: R5〜R9 | H10: 9 | I10: 推定 | J10: 未確認 | K10: https://www.city.kazuno.lg.jp/soshiki/shiminkyodo/kankyoseikatsu/gyomu/2/3/10092.html | L10: 第3次鹿角市環境基本計画 | M10: R3〜R12 | N10: 12 | O10: 推定 | P10: 未確認 | Q10: https://www.city.kazuno.lg.jp/soshiki/shiminkyodo/kankyoseikatsu/gyomu/1/3/index.html | R10: 交通：R7.6改訂版（秋北バス一部路線廃止・八幡平地区再編 R7.10.1対応）。計画期間は検索結果で未確認だが、R4年度協議会で策定審議（資料 https://www.city.kazuno.lg.jp/material/files/group/8/shiryou3_R4_3.pdf ）→R5年度始期の5年計画（R5〜R9）と推定、要確認。協議会 https://www.city.kazuno.lg.jp/soshiki/shiminkyodo/kankyoseikatsu/gyomu/2/3/9297.html 。環境：エネルギービジョン（R4.2）が第3次環境基本計画と終期を整合、R13年3月まで（=R12年度末）https://www.city.kazuno.lg.jp/material/files/group/14/energyvision.pdf 。e_urlは市の環境ページ（計画直リンク未取得）。 【ファクトチェック 2026-10-01: 確認できず】確認期間: R5〜R9（要約のみ）／次期: 確認できず／根拠: https://realtime-nippon.com/archives/052094230123001/ 【追加調査 2026-10】【2026-10-02調査】検索3回の要約がいずれも「計画期間は令和5年度から令和9年度まで」と回答（出典候補: 計画ページ https://www.city.kazuno.lg.jp/soshiki/shiminkyodo/kankyoseikatsu/gyomu/2/3/10092.html 、協議会 https://www.city.kazuno.lg.jp/soshiki/shiminkyodo/kankyoseikatsu/gyomu/2/3/9297.html ）が、本文抜粋は表示されず要約のみのため推定のまま（R5〜R9の確度は高い）。市サイト・realtime-nipponはWebFetch不可。関連: R7.10.1八幡平地区公共交通再編 https://www.city.kazuno.lg.jp/soshiki/shiminkyodo/kankyoseikatsu/gyomu/2/3/13627.html 。次期計画の委託・審議は検索で見当たらず。 | S10: 調査済 | T10: 掲載
A11: 8 | B11: 由利本荘市 | C11: =IF(OR(D11="◎",E11="◎"),"◎ 営業",IF(OR(D11="△",E11="△"),"△ 着手済・要確認",IF(OR(D11="？",E11="？"),"？ 期間要確認","✕ 対象外"))) | D11: =IF(J11="計画なし","－",IF(J11="策定済","✕",IF(H11="","？",IF(AND(H11>=TGT_MIN,H11<=TGT_MAX),IF(J11="着手済","△","◎"),"✕")))) | E11: =IF(P11="計画なし","－",IF(P11="策定済","✕",IF(N11="","？",IF(AND(N11>=TGT_MIN,N11<=TGT_MAX),IF(P11="着手済","△","◎"),"✕")))) | F11: 由利本荘市地域公共交通計画 | G11: R6〜R10 | H11: 10 | I11: 確認済 | J11: 未確認 | K11: https://www.city.yurihonjo.lg.jp/1000006/1001990/1009868.html | L11: 第二次由利本荘市環境基本計画 | M11: R5〜R14 | N11: 14 | O11: 推定 | P11: 未確認 | Q11: https://www.city.yurihonjo.lg.jp/_res/projects/default_project/_page_/001/007/924/keikaku.pdf | R11: 交通：網形成計画（第二次 R2〜R6）の後継としてR5年度プロポーザルで策定、期間2024〜2028年度。改訂ページあり（1009868）。環境：R5年度開始、終期は検索で未確認（10年と推定）。 | S11: 調査済 | T11: 掲載
A12: 9 | B12: 潟上市 | C12: =IF(OR(D12="◎",E12="◎"),"◎ 営業",IF(OR(D12="△",E12="△"),"△ 着手済・要確認",IF(OR(D12="？",E12="？"),"？ 期間要確認","✕ 対象外"))) | D12: =IF(J12="計画なし","－",IF(J12="策定済","✕",IF(H12="","？",IF(AND(H12>=TGT_MIN,H12<=TGT_MAX),IF(J12="着手済","△","◎"),"✕")))) | E12: =IF(P12="計画なし","－",IF(P12="策定済","✕",IF(N12="","？",IF(AND(N12>=TGT_MIN,N12<=TGT_MAX),IF(P12="着手済","△","◎"),"✕")))) | F12: 潟上市地域公共交通計画 | G12: R4〜R8 | H12: 8 | I12: 確認済 | J12: 未確認 | K12: https://www.city.katagami.lg.jp/soshiki/shiminseikatsu/chiikidukurika/chiikishinko/bus/4006.html | L12: 第2次潟上市環境基本計画 | M12: R5〜R14 | N12: 14 | O12: 推定 | P12: 未確認 | Q12: https://www.city.katagami.lg.jp/material/files/group/6/kankyokihon2.pdf | R12: 交通：R8(2026)年度で終期。次期計画の策定業務・協議会審議は検索で確認できず（R8年度中に改定作業のはず、有望・要確認）。公共交通アンケート結果ページあり https://www.city.katagami.lg.jp/soshiki/shiminseikatsu/chiikidukurika/chiikishinko/bus/3900.html （時期未確認）。環境：R5.3策定・R5年度始期、終期は未確認（10年と推定）。 | S12: 調査済 | T12: 掲載
A13: 10 | B13: 大仙市 | C13: =IF(OR(D13="◎",E13="◎"),"◎ 営業",IF(OR(D13="△",E13="△"),"△ 着手済・要確認",IF(OR(D13="？",E13="？"),"？ 期間要確認","✕ 対象外"))) | D13: =IF(J13="計画なし","－",IF(J13="策定済","✕",IF(H13="","？",IF(AND(H13>=TGT_MIN,H13<=TGT_MAX),IF(J13="着手済","△","◎"),"✕")))) | E13: =IF(P13="計画なし","－",IF(P13="策定済","✕",IF(N13="","？",IF(AND(N13>=TGT_MIN,N13<=TGT_MAX),IF(P13="着手済","△","◎"),"✕")))) | F13: 大仙市地域公共交通計画マスタープラン | G13: R3〜R7 | H13: 7 | I13: 確認済 | J13: 未確認 | K13: https://www.city.daisen.lg.jp/archive/contents-12074 | L13: 第2次大仙市環境基本計画 | M13: R1〜R10 | N13: 10 | O13: 推定 | P13: 未確認 | Q13: https://www.city.daisen.lg.jp/genre/administration/plannning | R13: 交通：マスタープラン（R3〜R7）は期間満了。後継（R8〜）計画の策定・パブコメは検索で確認できず（要確認・有望）。旧網形成計画PDF https://www.city.daisen.lg.jp/docs/2013091900263/file_contents/plan1.pdf 。環境：第2次はR1策定、終期未確認（10年と推定）。区域施策編あり https://www.city.daisen.lg.jp/archive/contents-13811 。e_urlは方針・計画一覧ページ。 | S13: 調査済 | T13: 掲載
A14: 11 | B14: 北秋田市 | C14: =IF(OR(D14="◎",E14="◎"),"◎ 営業",IF(OR(D14="△",E14="△"),"△ 着手済・要確認",IF(OR(D14="？",E14="？"),"？ 期間要確認","✕ 対象外"))) | D14: =IF(J14="計画なし","－",IF(J14="策定済","✕",IF(H14="","？",IF(AND(H14>=TGT_MIN,H14<=TGT_MAX),IF(J14="着手済","△","◎"),"✕")))) | E14: =IF(P14="計画なし","－",IF(P14="策定済","✕",IF(N14="","？",IF(AND(N14>=TGT_MIN,N14<=TGT_MAX),IF(P14="着手済","△","◎"),"✕")))) | F14: 北秋田市地域公共交通計画 | G14: R5〜R9 | H14: 9 | I14: 確認済 | J14: 未確認 | K14: https://www.city.kitaakita.akita.jp/uploads/public/news_0000015700_00/koukyoukoutsukeikaku.pdf | L14: 北秋田市環境基本計画（R3改正版） | M14: 〜R8（H28またはH29〜R8の10年間） | N14: 8 | O14: 確認済 | P14: 未確認 | Q14: https://www.city.kitaakita.akita.jp/uploads/public/archive_0000014042_00/%E3%80%90R3%E6%94%B9%E6%AD%A3%E3%80%91%E5%8C%97%E7%A7%8B%E7%94%B0%E5%B8%82%E7%92%B0%E5%A2%83%E5%9F%BA%E6%9C%AC%E8%A8%88%E7%94%BB_(%E6%9C%80%E7%B5%82%E7%89%88).pdf | R14: 交通：R5.3（公表2024.3.29頃）策定、R5〜R9（網形成計画H30〜R4の後継）。市単独計画（上小阿仁村との共同計画は確認できず）。利便増進実施計画もあり https://www.city.kitaakita.akita.jp/news/p12935 。R9終期のため次期計画はR8〜R9に着手見込み、現時点で策定業務は未確認。R8年度県北地域部会資料あり https://www.pref.akita.lg.jp/uploads/public/archive_0000098833_00/R8活性化協議会①/令和８年度第１回秋田県地域公共交通活性化協議会県北地域部会_会議概要.pdf 。環境：H30.4.1始期・R3改正（10年間ならR9終期、推定・要確認）。区域施策編も策定中/策定済（ゼロカーボン宣言R6.2.15）。 【ファクトチェック 2026-10-01: 正しい】確認期間: R5〜R9／次期: 確認できず／根拠: https://www.city.kitaakita.akita.jp/news/p15700 【ファクトチェック 2026-10-01: 誤り】確認期間: 〜R8（「平成28年度から令和8年度までの10年間」と要約。10年間ならH29〜R8の可能性）／次期: 確認できず（終期R8＝今年度のため次期計画策定が進行中の可能性が高いが、策定業務公告・審議会・アンケートは検索で見つからず）／根拠: https://www.city.kitaakita.akita.jp/archive/p13109 | S14: 調査済 | T14: 掲載
A15: 12 | B15: にかほ市 | C15: =IF(OR(D15="◎",E15="◎"),"◎ 営業",IF(OR(D15="△",E15="△"),"△ 着手済・要確認",IF(OR(D15="？",E15="？"),"？ 期間要確認","✕ 対象外"))) | D15: =IF(J15="計画なし","－",IF(J15="策定済","✕",IF(H15="","？",IF(AND(H15>=TGT_MIN,H15<=TGT_MAX),IF(J15="着手済","△","◎"),"✕")))) | E15: =IF(P15="計画なし","－",IF(P15="策定済","✕",IF(N15="","？",IF(AND(N15>=TGT_MIN,N15<=TGT_MAX),IF(P15="着手済","△","◎"),"✕")))) | F15: にかほ市地域公共交通計画（R7.3修正） | G15: R4〜R8 | H15: 8 | I15: 確認済 | J15: 未確認 | K15: https://www.city.nikaho.akita.jp/material/files/group/5/koukyoukoutuukeikaku3.pdf | M15: 不明 | O15: 不明 | P15: 計画なし | R15: 交通：R4.3策定・R7.3修正、R8(2026)年度で終期。「にかほ市地域交通調査分析支援業務委託プロポーザル」実施（受託候補者：博報堂）https://www.city.nikaho.akita.jp/soshikikarasagasu/renkei/gyomuannai/1_1/6279.html ―次期計画に向けた調査の可能性大（時期・計画策定との関係は要確認）。AIオンデマンド交通実証も実施。環境：環境基本計画は検索で見つからず。代替としてにかほ市地球温暖化対策実行計画（区域施策編）R7.3策定・2027年度まで https://www.city.nikaho.akita.jp/material/files/group/8/kuikishisaku.pdf 。 | S15: 調査済 | T15: 掲載
A16: 13 | B16: 仙北市 | C16: =IF(OR(D16="◎",E16="◎"),"◎ 営業",IF(OR(D16="△",E16="△"),"△ 着手済・要確認",IF(OR(D16="？",E16="？"),"？ 期間要確認","✕ 対象外"))) | D16: =IF(J16="計画なし","－",IF(J16="策定済","✕",IF(H16="","？",IF(AND(H16>=TGT_MIN,H16<=TGT_MAX),IF(J16="着手済","△","◎"),"✕")))) | E16: =IF(P16="計画なし","－",IF(P16="策定済","✕",IF(N16="","？",IF(AND(N16>=TGT_MIN,N16<=TGT_MAX),IF(P16="着手済","△","◎"),"✕")))) | F16: 仙北市地域公共交通計画 | G16: R4〜R8 | H16: 8 | I16: 確認済 | J16: 着手済 | K16: https://www.city.semboku.akita.jp/government/keikaku/documents/220428_koukyoukoutsuu.pdf | M16: 不明 | O16: 不明 | P16: 計画なし | R16: 交通：R4.3策定、R8(2026)年度が最終年度。2026年度部局経営方針シートでR9年度からの新計画を市民意見を反映して準備（公共交通座談会拡充・乗車体験イベント・意見交換会）と記載 https://www.city.semboku.akita.jp/government/keikaku/documents/2026_hoshinsi-to.pdf 。策定支援業務の委託先は未確認（有望）。環境：環境基本計画は検索で見つからず（SDGs未来都市計画・一般廃棄物処理基本計画等のみ）。 | S16: 調査済 | T16: 掲載
A17: 14 | B17: 小坂町 | C17: =IF(OR(D17="◎",E17="◎"),"◎ 営業",IF(OR(D17="△",E17="△"),"△ 着手済・要確認",IF(OR(D17="？",E17="？"),"？ 期間要確認","✕ 対象外"))) | D17: =IF(J17="計画なし","－",IF(J17="策定済","✕",IF(H17="","？",IF(AND(H17>=TGT_MIN,H17<=TGT_MAX),IF(J17="着手済","△","◎"),"✕")))) | E17: =IF(P17="計画なし","－",IF(P17="策定済","✕",IF(N17="","？",IF(AND(N17>=TGT_MIN,N17<=TGT_MAX),IF(P17="着手済","△","◎"),"✕")))) | F17: 小坂町地域公共交通計画 | G17: R4〜R8 | H17: 8 | I17: 確認済 | J17: 未確認 | K17: https://www.town.kosaka.akita.jp/machinososhiki/somuka/kikakuzaiseihan/2_2/kokyokotsukeikaku/2497.html | L17: 第3次小坂町環境基本計画 | M17: R6〜（終期不明） | O17: 不明 | P17: 策定済 | Q17: https://www.town.kosaka.akita.jp/material/files/group/8/01.pdf | R17: 交通：R4.4.1〜R9.3.31（R8年度終期）。今年度が最終年度のため次期計画策定が必要だが、策定業務プロポーザル等は検索で確認できず（要確認・有望）。協議会ページ https://www.town.kosaka.akita.jp/machinososhiki/somuka/kikakuzaiseihan/2_2/kokyokotsukeikaku/2499.html 、R8.4に地域公共交通マップ作成。環境：第3次計画R6.3策定（期間は検索結果で未確認）。地球温暖化対策実行計画（区域施策編）をR8.1.5策定 https://www.town.kosaka.akita.jp/machinososhiki/chominka/chominseikatsuhan/1/2900.html 。参考：秋田県地域公共交通計画（R4.3策定、R4〜R8）が県全域を対象、R8終期のため次期計画はR8年度に策定作業中と見込まれる（R8第1回県活性化協議会 https://www.pref.akita.lg.jp/uploads/public/archive_0000098833_00/R8活性化協議会①/令和８年度第１回秋田県地域公共交通活性化協議会_会議概要.pdf ）。 | S17: 調査済 | T17: 掲載
A18: 15 | B18: 上小阿仁村 | C18: =IF(OR(D18="◎",E18="◎"),"◎ 営業",IF(OR(D18="△",E18="△"),"△ 着手済・要確認",IF(OR(D18="？",E18="？"),"？ 期間要確認","✕ 対象外"))) | D18: =IF(J18="計画なし","－",IF(J18="策定済","✕",IF(H18="","？",IF(AND(H18>=TGT_MIN,H18<=TGT_MAX),IF(J18="着手済","△","◎"),"✕")))) | E18: =IF(P18="計画なし","－",IF(P18="策定済","✕",IF(N18="","？",IF(AND(N18>=TGT_MIN,N18<=TGT_MAX),IF(P18="着手済","△","◎"),"✕")))) | G18: 不明 | I18: 不明 | J18: 未確認 | M18: 不明 | O18: 不明 | P18: 未確認 | R18: 交通：村単独の地域公共交通計画は確認できず。以前は北秋田市・上小阿仁村の地域公共交通網形成計画（H29〜H34）が検索要約に出たが未確証。現行の北秋田市地域公共交通計画（R5〜R9、R5.3策定 https://www.city.kitaakita.akita.jp/uploads/public/news_0000015700_00/koukyoukoutsukeikaku.pdf ）の計画区域に上小阿仁村が含まれるかは未確認（要確認、含まれればt_end=9）。環境：環境基本計画・温対計画とも村HP検索で確認できず（計画なしの可能性大）。参考：秋田県地域公共交通計画（R4.3策定、R4〜R8）が県全域を対象、R8終期のため次期計画はR8年度に策定作業中と見込まれる（R8第1回県活性化協議会 https://www.pref.akita.lg.jp/uploads/public/archive_0000098833_00/R8活性化協議会①/令和８年度第１回秋田県地域公共交通活性化協議会_会議概要.pdf ）。 【追加調査 2026-10】環境：村サイト限定検索で、村議会会議録（R6第6回12月 https://www.vill.kamikoani.akita.jp/div/gikai/pdf/R6-6-3.pdf 、R7第2回3月 https://www.vill.kamikoani.akita.jp/div/gikai/pdf/R7-2-1.pdf 等）に『上小阿仁村環境基本計画』を自然エネルギーによる脱炭素戦略の村全体の総合行動計画として策定する旨の言及が要約で出た（どの会議録かは原文未確認）。小水力発電可能性調査（2023）を踏まえ再エネ設備基本設計を進行中との記載。策定済の計画書・期間・URLは検索で見当たらず（策定中または未公表の可能性）。未確認のまま。確認日2026-10-02。 | S18: 未調査 | T18: 未掲載
A19: 16 | B19: 藤里町 | C19: =IF(OR(D19="◎",E19="◎"),"◎ 営業",IF(OR(D19="△",E19="△"),"△ 着手済・要確認",IF(OR(D19="？",E19="？"),"？ 期間要確認","✕ 対象外"))) | D19: =IF(J19="計画なし","－",IF(J19="策定済","✕",IF(H19="","？",IF(AND(H19>=TGT_MIN,H19<=TGT_MAX),IF(J19="着手済","△","◎"),"✕")))) | E19: =IF(P19="計画なし","－",IF(P19="策定済","✕",IF(N19="","？",IF(AND(N19>=TGT_MIN,N19<=TGT_MAX),IF(P19="着手済","△","◎"),"✕")))) | F19: 藤里町地域公共交通計画 | G19: R6〜R10 | H19: 10 | I19: 確認済 | J19: 策定済 | K19: http://www.town.fujisato.akita.jp/kotsu/c640/c643/2890 | L19: 藤里町環境基本計画 | M19: 不明（H12.3策定） | O19: 不明 | P19: 未確認 | Q19: https://www.env.go.jp/press/files/jp/3487.pdf | R19: 交通：R6.6.18作成、前計画は藤里町地域公共交通網形成計画（H27〜H31）。計画PDF http://www.town.fujisato.akita.jp/up/files/town/soshiki/c52/c74/%E8%97%A4%E9%87%8C%E7%94%BA%E5%9C%B0%E5%9F%9F%E5%85%AC%E5%85%B1%E4%BA%A4%E9%80%9A%E8%A8%88%E7%94%BB.pdf 。能代山本地域の広域計画は確認できず（R6.10秋北バス路線再編で町内デマンド拡充）。環境：環境省資料でH12.3策定の記載のみ、現行版・改定状況は町HPで確認できず（実質計画なしの可能性）。参考：秋田県地域公共交通計画（R4.3策定、R4〜R8）が県全域を対象、R8終期のため次期計画はR8年度に策定作業中と見込まれる（R8第1回県活性化協議会 https://www.pref.akita.lg.jp/uploads/public/archive_0000098833_00/R8活性化協議会①/令和８年度第１回秋田県地域公共交通活性化協議会_会議概要.pdf ）。 【追加調査 2026-10】環境：町サイト限定（town.fujisato.akita.jp）で『環境基本計画』検索→過疎計画・国土強靱化・総合戦略・まちづくり計画（H26.3）・公共施設等総合管理計画のみヒットし、環境基本計画（H12.3策定、環境省資料 https://www.env.go.jp/press/files/jp/3487.pdf ）の現行版・改定版は町HP上に見当たらず。計画が実質失効の可能性大だが計画なしの明示根拠はないため未確認のまま。確認日2026-10-02。 | S19: 調査済 | T19: 掲載
A20: 17 | B20: 三種町 | C20: =IF(OR(D20="◎",E20="◎"),"◎ 営業",IF(OR(D20="△",E20="△"),"△ 着手済・要確認",IF(OR(D20="？",E20="？"),"？ 期間要確認","✕ 対象外"))) | D20: =IF(J20="計画なし","－",IF(J20="策定済","✕",IF(H20="","？",IF(AND(H20>=TGT_MIN,H20<=TGT_MAX),IF(J20="着手済","△","◎"),"✕")))) | E20: =IF(P20="計画なし","－",IF(P20="策定済","✕",IF(N20="","？",IF(AND(N20>=TGT_MIN,N20<=TGT_MAX),IF(P20="着手済","△","◎"),"✕")))) | F20: 三種町地域公共交通計画 | G20: 不明（R3.6策定、R6.5改訂） | I20: 不明 | J20: 未確認 | K20: https://www.town.mitane.akita.jp/material/files/group/3/mitanekoukyoukoutuukeikaku.pdf | M20: 不明 | O20: 不明 | P20: 計画なし | R20: 交通：R3.6.18地域公共交通会議で承認、R6.5.23改訂。計画期間は検索結果で確認できず（要確認）。計画ページ https://www.town.mitane.akita.jp/soshikikarasagasu/kikakuseisakuka/1/143.html 。環境：環境基本計画は確認できず。代替として三種町地域脱炭素実行計画（R6〜R12、区域施策編・事務事業編・適応計画を一体化、変更あり） https://www.town.mitane.akita.jp/material/files/group/3/datutannso.pdf / https://www.town.mitane.akita.jp/soshikikarasagasu/kikakuseisakuka/1/3093.html 。参考：秋田県地域公共交通計画（R4.3策定、R4〜R8）が県全域を対象、R8終期のため次期計画はR8年度に策定作業中と見込まれる（R8第1回県活性化協議会 https://www.pref.akita.lg.jp/uploads/public/archive_0000098833_00/R8活性化協議会①/令和８年度第１回秋田県地域公共交通活性化協議会_会議概要.pdf ）。 | S20: 調査済 | T20: 掲載
A21: 18 | B21: 八峰町 | C21: =IF(OR(D21="◎",E21="◎"),"◎ 営業",IF(OR(D21="△",E21="△"),"△ 着手済・要確認",IF(OR(D21="？",E21="？"),"？ 期間要確認","✕ 対象外"))) | D21: =IF(J21="計画なし","－",IF(J21="策定済","✕",IF(H21="","？",IF(AND(H21>=TGT_MIN,H21<=TGT_MAX),IF(J21="着手済","△","◎"),"✕")))) | E21: =IF(P21="計画なし","－",IF(P21="策定済","✕",IF(N21="","？",IF(AND(N21>=TGT_MIN,N21<=TGT_MAX),IF(P21="着手済","△","◎"),"✕")))) | G21: 不明 | I21: 不明 | J21: 未確認 | M21: 不明 | O21: 不明 | P21: 計画なし | R21: 交通：八峰町単独の地域公共交通計画は町HP検索で確認できず。R2年度に住民アンケート、R3.10.1〜R4.9.30巡回バス試行運行 http://www.town.happou.akita.jp/docs/2021091400034/ 。能代山本地域の広域計画も確認できず（R6.10秋北バス能代山本路線再編で町の巡回バス・乗合タクシー拡充）https://www.sakigake.jp/news/article/20241006AK0019/ 。環境：環境基本計画は確認できず（町HP要約に地球温暖化防止対策実行計画・省エネビジョンの言及のみ、詳細不明）。参考：秋田県地域公共交通計画（R4.3策定、R4〜R8）が県全域を対象、R8終期のため次期計画はR8年度に策定作業中と見込まれる（R8第1回県活性化協議会 https://www.pref.akita.lg.jp/uploads/public/archive_0000098833_00/R8活性化協議会①/令和８年度第１回秋田県地域公共交通活性化協議会_会議概要.pdf ）。 | S21: 環境のみ調査 | T21: 未掲載
A22: 19 | B22: 五城目町 | C22: =IF(OR(D22="◎",E22="◎"),"◎ 営業",IF(OR(D22="△",E22="△"),"△ 着手済・要確認",IF(OR(D22="？",E22="？"),"？ 期間要確認","✕ 対象外"))) | D22: =IF(J22="計画なし","－",IF(J22="策定済","✕",IF(H22="","？",IF(AND(H22>=TGT_MIN,H22<=TGT_MAX),IF(J22="着手済","△","◎"),"✕")))) | E22: =IF(P22="計画なし","－",IF(P22="策定済","✕",IF(N22="","？",IF(AND(N22>=TGT_MIN,N22<=TGT_MAX),IF(P22="着手済","△","◎"),"✕")))) | F22: 南秋地域公共交通計画（五城目町・八郎潟町・大潟村共同） | G22: R5〜R9 | H22: 9 | I22: 確認済 | J22: 未確認 | K22: https://www.town.gojome.akita.jp/kurashi/koukyoukoutsu/2085 | M22: 不明 | O22: 不明 | P22: 計画なし | R22: 交通：南秋地域公共交通活性化協議会（五城目・八郎潟・大潟）が策定、R5〜R9でR9終期→次期はR8〜R9に着手見込み（着手情報は未確認）。計画案PDF https://www.town.gojome.akita.jp/up/files/town/machikeikaku/koutuukeikaku.pdf 。別途、町単独の五城目町地域公共交通計画（R4〜R8、R4.5策定）https://www.town.gojome.akita.jp/town/sosikiannai/machi/matiduku/1734 もあり、R8終期（次期は未確認）。環境：環境基本計画は確認できず。地球温暖化対策実行計画（事務事業編）のみ確認。参考：秋田県地域公共交通計画（R4.3策定、R4〜R8）が県全域を対象、R8終期のため次期計画はR8年度に策定作業中と見込まれる（R8第1回県活性化協議会 https://www.pref.akita.lg.jp/uploads/public/archive_0000098833_00/R8活性化協議会①/令和８年度第１回秋田県地域公共交通活性化協議会_会議概要.pdf ）。 【ファクトチェック 2026-10-01: 正しい】確認期間: R5〜R9（令和5年度～令和9年度、5年間）／次期: 確認できず（協議会での次期計画審議・策定業務の公告は検索で見つからず）／根拠: https://www.town.gojome.akita.jp/kurashi/koukyoukoutsu/2085 | S22: 調査済 | T22: 掲載（広域：南秋）
A23: 20 | B23: 八郎潟町 | C23: =IF(OR(D23="◎",E23="◎"),"◎ 営業",IF(OR(D23="△",E23="△"),"△ 着手済・要確認",IF(OR(D23="？",E23="？"),"？ 期間要確認","✕ 対象外"))) | D23: =IF(J23="計画なし","－",IF(J23="策定済","✕",IF(H23="","？",IF(AND(H23>=TGT_MIN,H23<=TGT_MAX),IF(J23="着手済","△","◎"),"✕")))) | E23: =IF(P23="計画なし","－",IF(P23="策定済","✕",IF(N23="","？",IF(AND(N23>=TGT_MIN,N23<=TGT_MAX),IF(P23="着手済","△","◎"),"✕")))) | F23: 南秋地域公共交通計画（五城目町・八郎潟町・大潟村共同、南秋地域公共交通活性化協議会） | G23: R5〜R9 | H23: 9 | I23: 確認済 | J23: 未確認 | K23: https://www.town.gojome.akita.jp/kurashi/koukyoukoutsu/2085 | M23: 不明 | O23: 不明 | P23: 計画なし | R23: 交通：南秋地域公共交通計画はR5.6策定（東北運輸局資料で確認）。井川町は含まれない。計画期間R5〜R9（五城目町サイトで確認、計画案PDF https://www.town.gojome.akita.jp/up/files/town/machikeikaku/koutuukeikaku.pdf ）。東北運輸局資料 https://wwwtb.mlit.go.jp/tohoku/content/000305851.pdf 。環境：町独自の環境基本計画は検索で見当たらず。【県計画】秋田県地域公共交通計画はR4〜R8（R4.3策定、R8＝今年度終期）。R8.6.23の令和8年度第1回秋田県地域公共交通活性化協議会で県計画の策定（次期計画）を議論 https://www.pref.akita.lg.jp/uploads/public/archive_0000098833_00/R8活性化協議会①/令和８年度第１回秋田県地域公共交通活性化協議会_会議概要.pdf 【ファクトチェック 2026-10-01: 正しい】確認期間: R5〜R9（令和5年度～令和9年度、5年間）／次期: 確認できず（協議会での次期計画審議・策定業務の公告は検索で見つからず）／根拠: https://www.town.gojome.akita.jp/kurashi/koukyoukoutsu/2085 | S23: 調査済 | T23: 掲載（広域：南秋）
A24: 21 | B24: 井川町 | C24: =IF(OR(D24="◎",E24="◎"),"◎ 営業",IF(OR(D24="△",E24="△"),"△ 着手済・要確認",IF(OR(D24="？",E24="？"),"？ 期間要確認","✕ 対象外"))) | D24: =IF(J24="計画なし","－",IF(J24="策定済","✕",IF(H24="","？",IF(AND(H24>=TGT_MIN,H24<=TGT_MAX),IF(J24="着手済","△","◎"),"✕")))) | E24: =IF(P24="計画なし","－",IF(P24="策定済","✕",IF(N24="","？",IF(AND(N24>=TGT_MIN,N24<=TGT_MAX),IF(P24="着手済","△","◎"),"✕")))) | F24: 秋田県地域公共交通計画（県計画、町独自計画は見当たらず） | G24: R4〜R8 | H24: 8 | I24: 確認済 | J24: 未確認 | K24: https://www.pref.akita.lg.jp/uploads/public/archive_0000062825_00/観スポ_所管事項関連 別冊２（秋田県地域公共交通計画（案）について）.pdf | M24: 不明 | O24: 不明 | P24: 計画なし | R24: 交通：町独自の地域公共交通計画は検索で確認できず（南秋地域公共交通計画は五城目・八郎潟・大潟の3町村で井川町は不参加）。t_urlは県計画（案）資料。県計画はR8終期で次期県計画を協議会で検討中（下記）。環境：環境基本計画・区域施策編とも検索で見当たらず。【県計画】秋田県地域公共交通計画はR4〜R8（R4.3策定、R8＝今年度終期）。R8.6.23の令和8年度第1回秋田県地域公共交通活性化協議会で県計画の策定（次期計画）を議論 https://www.pref.akita.lg.jp/uploads/public/archive_0000098833_00/R8活性化協議会①/令和８年度第１回秋田県地域公共交通活性化協議会_会議概要.pdf | S24: 調査済 | T24: 未掲載【当方は計画あり】
A25: 22 | B25: 大潟村 | C25: =IF(OR(D25="◎",E25="◎"),"◎ 営業",IF(OR(D25="△",E25="△"),"△ 着手済・要確認",IF(OR(D25="？",E25="？"),"？ 期間要確認","✕ 対象外"))) | D25: =IF(J25="計画なし","－",IF(J25="策定済","✕",IF(H25="","？",IF(AND(H25>=TGT_MIN,H25<=TGT_MAX),IF(J25="着手済","△","◎"),"✕")))) | E25: =IF(P25="計画なし","－",IF(P25="策定済","✕",IF(N25="","？",IF(AND(N25>=TGT_MIN,N25<=TGT_MAX),IF(P25="着手済","△","◎"),"✕")))) | F25: 南秋地域公共交通計画（五城目町・八郎潟町・大潟村共同、南秋地域公共交通活性化協議会） | G25: R5〜R9 | H25: 9 | I25: 確認済 | J25: 未確認 | K25: https://www.town.gojome.akita.jp/kurashi/koukyoukoutsu/2085 | M25: 不明 | O25: 不明 | P25: 計画なし | R25: 交通：八郎潟町と同じ南秋地域公共交通計画（R5.6策定）。期間R5〜R9（五城目町サイトで確認）。環境：村独自の環境基本計画は検索で見当たらず。大潟村は環境省の脱炭素先行地域（メガソーラー・地域エネルギー会社等） https://www.env.go.jp/content/900512579.pdf 。第3次大潟村振興計画に「自然にやさしい環境の創造」あり。 【ファクトチェック 2026-10-01: 正しい】確認期間: R5〜R9（令和5年度～令和9年度、5年間）／次期: 確認できず（協議会での次期計画審議・策定業務の公告は検索で見つからず）／根拠: https://www.town.gojome.akita.jp/kurashi/koukyoukoutsu/2085 | S25: 調査済 | T25: 掲載（広域：南秋）
A26: 23 | B26: 美郷町 | C26: =IF(OR(D26="◎",E26="◎"),"◎ 営業",IF(OR(D26="△",E26="△"),"△ 着手済・要確認",IF(OR(D26="？",E26="？"),"？ 期間要確認","✕ 対象外"))) | D26: =IF(J26="計画なし","－",IF(J26="策定済","✕",IF(H26="","？",IF(AND(H26>=TGT_MIN,H26<=TGT_MAX),IF(J26="着手済","△","◎"),"✕")))) | E26: =IF(P26="計画なし","－",IF(P26="策定済","✕",IF(N26="","？",IF(AND(N26>=TGT_MIN,N26<=TGT_MAX),IF(P26="着手済","△","◎"),"✕")))) | F26: 美郷町地域公共交通計画 | G26: R4〜R8?（R4.3策定） | H26: 8 | I26: 推定 | J26: 未確認 | K26: https://www.town.misato.akita.jp/up/files/madoguchi/kikaku/kikakuzaiseihan/koutukeikaku/%E7%BE%8E%E9%83%B7%E7%94%BA%E5%9C%B0%E5%9F%9F%E5%85%AC%E5%85%B1%E4%BA%A4%E9%80%9A%E8%A8%88%E7%94%BB.pdf | M26: 不明 | O26: 不明 | P26: 計画なし | R26: 交通：R4.3策定（乗合タクシー中心）。期間は検索結果で確認できず、県計画と同じ5年ならR4〜R8（今年度終期→次期計画の動きに注意、町の策定業務は未確認）。島根県美郷町と混同注意。環境：環境基本計画は見当たらず（事務事業編の美郷町役場地球温暖化対策実行計画（第2期、H27.3）等のみ https://www.town.misato.akita.jp/up/files/archives/jikkoukeikaku/6848download.pdf ）。【県計画】秋田県地域公共交通計画はR4〜R8（R4.3策定、R8＝今年度終期）。R8.6.23の令和8年度第1回秋田県地域公共交通活性化協議会で県計画の策定（次期計画）を議論 https://www.pref.akita.lg.jp/uploads/public/archive_0000098833_00/R8活性化協議会①/令和８年度第１回秋田県地域公共交通活性化協議会_会議概要.pdf | S26: 調査済 | T26: 掲載
A27: 24 | B27: 羽後町 | C27: =IF(OR(D27="◎",E27="◎"),"◎ 営業",IF(OR(D27="△",E27="△"),"△ 着手済・要確認",IF(OR(D27="？",E27="？"),"？ 期間要確認","✕ 対象外"))) | D27: =IF(J27="計画なし","－",IF(J27="策定済","✕",IF(H27="","？",IF(AND(H27>=TGT_MIN,H27<=TGT_MAX),IF(J27="着手済","△","◎"),"✕")))) | E27: =IF(P27="計画なし","－",IF(P27="策定済","✕",IF(N27="","？",IF(AND(N27>=TGT_MIN,N27<=TGT_MAX),IF(P27="着手済","△","◎"),"✕")))) | F27: 秋田県地域公共交通計画（県計画、町独自計画は見当たらず） | G27: R4〜R8 | H27: 8 | I27: 確認済 | J27: 未確認 | K27: https://www.pref.akita.lg.jp/uploads/public/archive_0000062825_00/観スポ_所管事項関連 別冊２（秋田県地域公共交通計画（案）について）.pdf | M27: 不明 | O27: 不明 | P27: 計画なし | R27: 交通：町独自の地域公共交通計画、湯沢雄勝広域の共同計画とも検索で確認できず（湯沢市は単独計画あり）。羽後交通路線は県計画（地域間幹線系統）で位置づけ。環境：環境基本計画・区域施策編とも見当たらず。【県計画】秋田県地域公共交通計画はR4〜R8（R4.3策定、R8＝今年度終期）。R8.6.23の令和8年度第1回秋田県地域公共交通活性化協議会で県計画の策定（次期計画）を議論 https://www.pref.akita.lg.jp/uploads/public/archive_0000098833_00/R8活性化協議会①/令和８年度第１回秋田県地域公共交通活性化協議会_会議概要.pdf | S27: 調査済 | T27: 未掲載【当方は計画あり】
A28: 25 | B28: 東成瀬村 | C28: =IF(OR(D28="◎",E28="◎"),"◎ 営業",IF(OR(D28="△",E28="△"),"△ 着手済・要確認",IF(OR(D28="？",E28="？"),"？ 期間要確認","✕ 対象外"))) | D28: =IF(J28="計画なし","－",IF(J28="策定済","✕",IF(H28="","？",IF(AND(H28>=TGT_MIN,H28<=TGT_MAX),IF(J28="着手済","△","◎"),"✕")))) | E28: =IF(P28="計画なし","－",IF(P28="策定済","✕",IF(N28="","？",IF(AND(N28>=TGT_MIN,N28<=TGT_MAX),IF(P28="着手済","△","◎"),"✕")))) | F28: 東成瀬村地域公共交通計画 | G28: R8〜R12 | H28: 12 | I28: 推定 | J28: 策定済 | K28: https://vill.higashinaruse.lg.jp/villager/lifework/post-36197/ | M28: 不明 | O28: 不明 | P28: 計画なし | R28: 交通：村独自の地域公共交通計画・湯沢雄勝広域共同計画とも検索で確認できず。環境：環境基本計画見当たらず（まち・ひと・しごと創生推進計画のみ確認）。【県計画】秋田県地域公共交通計画はR4〜R8（R4.3策定、R8＝今年度終期）。R8.6.23の令和8年度第1回秋田県地域公共交通活性化協議会で県計画の策定（次期計画）を議論 https://www.pref.akita.lg.jp/uploads/public/archive_0000098833_00/R8活性化協議会①/令和８年度第１回秋田県地域公共交通活性化協議会_会議概要.pdf 【追加調査 2026-10】交通(2026-10調査)：村単独の東成瀬村地域公共交通計画をR8.3策定（村HP「東成瀬村地域公共交通計画を策定しました」 https://vill.higashinaruse.lg.jp/villager/lifework/post-36197/ ）。計画期間 令和8年度〜令和12年度（2026〜2030年度）、検索結果本文で2回確認。東成瀬村地域公共交通活性化協議会を設置（R6年度第1回協議会R7.1.30 https://vill.higashinaruse.lg.jp/wp-content/uploads/2025/03/a47c589c-621f-42c3-b67e-b4f7bba572f4.pdf ）、「交通空白」解消に向けた調査・検討業務を公募（https://vill.higashinaruse.lg.jp/villager/news/post-33178/ ）。R8.10.1から公共ライドシェア実証開始（https://vill.higashinaruse.lg.jp/villager/post-38003/ ）。従来記載の秋田県計画は参考扱いに。 ※期間は英語の検索要約でのみ確認（本文未確認）のため推定に留める。 根拠: formulated in March 2026 (Reiwa 8). The plan covers the period from fiscal year 2026 to fiscal year 2030 (Reiwa 8 to Reiwa 12) | S28: 調査済 | T28: 掲載

Sheet 山形県
A1: 山形県 地域公共交通計画・環境基本計画の終期一覧（2026年9月30日時点の調査）
A2: ="営業判定の対象：終期 R"&TGT_MIN&"〜R"&TGT_MAX&"年度 →◎（着手済は△、期間不明は？）。終期セルの色：緑＝対象年度／橙＝その翌年度（次の候補）。対象年度は「集計・設定」シートのC4・C5のプルダウンで切替。"
A3: No | B3: 市町村 | C3: 営業判定 | D3: 交通判定 | E3: 環境判定 | F3: 地域公共交通計画 | G3: 交通 計画期間 | H3: 交通 終期(令和年度) | I3: 交通 確度 | J3: 交通 改定状況 | K3: 交通 計画リンク（エビデンス） | L3: 環境基本計画 | M3: 環境 計画期間 | N3: 環境 終期(令和年度) | O3: 環境 確度 | P3: 環境 改定状況 | Q3: 環境 計画リンク（エビデンス） | R3: 注釈（改定作業の状況など） | S3: 調査状況 | T3: 国交省一覧(R8.5末)
A4: 1 | B4: 山形市 | C4: =IF(OR(D4="◎",E4="◎"),"◎ 営業",IF(OR(D4="△",E4="△"),"△ 着手済・要確認",IF(OR(D4="？",E4="？"),"？ 期間要確認","✕ 対象外"))) | D4: =IF(J4="計画なし","－",IF(J4="策定済","✕",IF(H4="","？",IF(AND(H4>=TGT_MIN,H4<=TGT_MAX),IF(J4="着手済","△","◎"),"✕")))) | E4: =IF(P4="計画なし","－",IF(P4="策定済","✕",IF(N4="","？",IF(AND(N4>=TGT_MIN,N4<=TGT_MAX),IF(P4="着手済","△","◎"),"✕")))) | F4: 第2期山形市地域公共交通計画 | G4: R8〜R12 | H4: 12 | I4: 確認済 | J4: 策定済 | K4: https://www.city.yamagata-yamagata.lg.jp/_res/projects/default_project/_page_/001/002/654/keikaku2_honpen.pdf | L4: 第4次山形市環境基本計画 | M4: R3〜R12 | N4: 12 | O4: 推定 | P4: 未確認 | Q4: https://www.city.yamagata-yamagata.lg.jp/shiseijoho/keikaku/1006993/1002366.html | R4: 交通：第1期(R3.3策定)の後継として第2期をR8.3策定、計画期間R8.4〜R13.3。計画ページ https://www.city.yamagata-yamagata.lg.jp/shiseijoho/keikaku/1008370/1002654.html 。環境：第4次は令和12年度(2030)を目標年度とする10年計画（開始年度は推定）。 | S4: 調査済 | T4: 掲載
A5: 2 | B5: 米沢市 | C5: =IF(OR(D5="◎",E5="◎"),"◎ 営業",IF(OR(D5="△",E5="△"),"△ 着手済・要確認",IF(OR(D5="？",E5="？"),"？ 期間要確認","✕ 対象外"))) | D5: =IF(J5="計画なし","－",IF(J5="策定済","✕",IF(H5="","？",IF(AND(H5>=TGT_MIN,H5<=TGT_MAX),IF(J5="着手済","△","◎"),"✕")))) | E5: =IF(P5="計画なし","－",IF(P5="策定済","✕",IF(N5="","？",IF(AND(N5>=TGT_MIN,N5<=TGT_MAX),IF(P5="着手済","△","◎"),"✕")))) | F5: 米沢市地域公共交通計画 | G5: R4〜R8 | H5: 8 | I5: 確認済 | J5: 未確認 | K5: https://www.city.yonezawa.yamagata.jp/soshiki/2/1007/7/2367.html | L5: 第4期米沢市環境基本計画 | M5: R8〜不明 | O5: 推定 | P5: 策定済 | Q5: https://www.city.yonezawa.yamagata.jp/soshiki/3/kankyo/9_1/8300.html | R5: 交通：R8年度終期のため次期計画策定が今年度中に必要だが、策定支援業務・パブコメ等は検索で未確認（要確認・営業優先度高）。環境：第3期(H28〜R7)の後継として第4期案をR7.11.14環境審議会で審議（資料 https://www.city.yonezawa.yamagata.jp/material/files/group/47/02_setumeisiryou.pdf ）、R8.3策定とみられる。第4期地球温暖化対策実行計画もパブコメ実施。 | S5: 調査済 | T5: 掲載
A6: 3 | B6: 鶴岡市 | C6: =IF(OR(D6="◎",E6="◎"),"◎ 営業",IF(OR(D6="△",E6="△"),"△ 着手済・要確認",IF(OR(D6="？",E6="？"),"？ 期間要確認","✕ 対象外"))) | D6: =IF(J6="計画なし","－",IF(J6="策定済","✕",IF(H6="","？",IF(AND(H6>=TGT_MIN,H6<=TGT_MAX),IF(J6="着手済","△","◎"),"✕")))) | E6: =IF(P6="計画なし","－",IF(P6="策定済","✕",IF(N6="","？",IF(AND(N6>=TGT_MIN,N6<=TGT_MAX),IF(P6="着手済","△","◎"),"✕")))) | F6: 鶴岡市地域公共交通計画（R08-12） | G6: R8〜R12 | H6: 12 | I6: 確認済 | J6: 策定済 | K6: https://www.city.tsuruoka.lg.jp/seibi/tiikikoukyoukoutu/tiiki0120160419.files/R8.3honnpenn.pdf | L6: 第2次鶴岡市環境基本計画 | M6: R4〜R13 | N6: 13 | O6: 推定 | P6: 未確認 | Q6: https://www.city.tsuruoka.lg.jp/seibi/kankyo/kihonkeikaku/dainizi_kankyoukihon.html | R6: 交通：R7.6改定支援業務プロポーザル→R8.3策定（パブコメ結果 https://www.city.tsuruoka.lg.jp/shisei/koutyou/publiccomment/r07/tiiki0120260327.html ）。環境：第1次H24〜R3の後継、第2次はR4開始（期間は10年と推定）。 | S6: 調査済 | T6: 掲載
A7: 4 | B7: 酒田市 | C7: =IF(OR(D7="◎",E7="◎"),"◎ 営業",IF(OR(D7="△",E7="△"),"△ 着手済・要確認",IF(OR(D7="？",E7="？"),"？ 期間要確認","✕ 対象外"))) | D7: =IF(J7="計画なし","－",IF(J7="策定済","✕",IF(H7="","？",IF(AND(H7>=TGT_MIN,H7<=TGT_MAX),IF(J7="着手済","△","◎"),"✕")))) | E7: =IF(P7="計画なし","－",IF(P7="策定済","✕",IF(N7="","？",IF(AND(N7>=TGT_MIN,N7<=TGT_MAX),IF(P7="着手済","△","◎"),"✕")))) | F7: 酒田市地域公共交通計画 | G7: R3〜R8（延長） | H7: 8 | I7: 推定 | J7: 着手済 | K7: https://www.city.sakata.lg.jp/shisei/shisakukeikaku/kikaku/chiikokyokotsumo/trafficplan2021.html | L7: 第3次酒田市環境基本計画 | M7: R8〜不明 | O7: 推定 | P7: 策定済 | Q7: https://www.city.sakata.lg.jp/shisei/shisakukeikaku/shimin/kankyokihonkeikaku/kankyoplan03.files/kankyoplan3-data.pdf | R7: 交通：R3.2策定の計画(R3〜R7)。市サイトに『次期計画として令和9〜13年度を計画期間とする新計画』の記載があり、現計画はR8まで延長し次期計画を策定中とみられる（要確認）。計画一覧 https://www.city.sakata.lg.jp/shisei/shisakukeikaku/kikaku/chiikokyokotsumo/index.html 。環境：第3次をR8.3策定（資料編で確認、期間未確認）。 | S7: 調査済 | T7: 掲載
A8: 5 | B8: 新庄市 | C8: =IF(OR(D8="◎",E8="◎"),"◎ 営業",IF(OR(D8="△",E8="△"),"△ 着手済・要確認",IF(OR(D8="？",E8="？"),"？ 期間要確認","✕ 対象外"))) | D8: =IF(J8="計画なし","－",IF(J8="策定済","✕",IF(H8="","？",IF(AND(H8>=TGT_MIN,H8<=TGT_MAX),IF(J8="着手済","△","◎"),"✕")))) | E8: =IF(P8="計画なし","－",IF(P8="策定済","✕",IF(N8="","？",IF(AND(N8>=TGT_MIN,N8<=TGT_MAX),IF(P8="着手済","△","◎"),"✕")))) | F8: 山形県地域公共交通計画（県・市町村共同、R8.3.27策定） | G8: R8〜R12 | H8: 12 | I8: 確認済 | J8: 策定済 | K8: https://www.pref.yamagata.jp/documents/50579/keikaku_honpen.pdf | L8: 第4次新庄市環境基本計画 | M8: R3〜R12 | N8: 12 | O8: 確認済 | P8: 未確認 | Q8: http://www.city.shinjo.yamagata.jp/s008/170/010/kankyoukihonkeikakuno4.pdf | R8: 交通：市単独の地域公共交通計画は検索で見当たらず。県計画の最上地域部会で最上管内8市町村の公共交通再編を検討中（R7.11資料 https://www.pref.yamagata.jp/documents/47862/20251125shiryou2-2.pdf ）。山形県地域公共交通計画（前計画R3〜R7）は市町村の利便増進実施計画等を内包する県全域計画。次期計画はR8.2パブコメ（https://www200.pref.yamagata.jp/020057/keikakupabukomepress2.html ）を経てR8.3.27策定（期間は未確認、R8開始）。 【追加調査 2026-10】交通(2026-10調査)：市単独の「新庄市地域公共交通計画」は検索で見当たらず。新庄市の地域内フィーダー系統（まちなか循環線）は山形県地域公共交通計画に位置付け（https://www.pref.yamagata.jp/documents/22689/05_shinjo.pdf ）。国交省一覧の「単独・期間満了」は前県計画（R3〜R7、市町村共同作成）を指す可能性が高い。次期県計画は計画期間 令和8〜12年度（本編 https://www.pref.yamagata.jp/documents/50579/keikaku_honpen.pdf 、概要 https://www.pref.yamagata.jp/documents/50579/keikaku_gaiyou.pdf 、策定業務仕様書 https://www300.pref.yamagata.jp/documents/45835/02_shiyousyo.pdf ）。県全域＋全市町村が対象、4地域ブロック（最上ブロック）構成。 根拠: 山形県地域公共交通計画（本編）… 計画期間 令和8～12年度（検索結果本文） | S8: 調査済 | T8: 掲載／期間満了
A9: 6 | B9: 寒河江市 | C9: =IF(OR(D9="◎",E9="◎"),"◎ 営業",IF(OR(D9="△",E9="△"),"△ 着手済・要確認",IF(OR(D9="？",E9="？"),"？ 期間要確認","✕ 対象外"))) | D9: =IF(J9="計画なし","－",IF(J9="策定済","✕",IF(H9="","？",IF(AND(H9>=TGT_MIN,H9<=TGT_MAX),IF(J9="着手済","△","◎"),"✕")))) | E9: =IF(P9="計画なし","－",IF(P9="策定済","✕",IF(N9="","？",IF(AND(N9>=TGT_MIN,N9<=TGT_MAX),IF(P9="着手済","△","◎"),"✕")))) | F9: 寒河江市生活交通ネットワーク計画（法定計画か不明） | G9: 不明 | I9: 不明 | J9: 未確認 | K9: https://www.city.sagae.yamagata.jp/shisei/keikaku/toshikankyokeikaku/koutsu_net_sakutei.html | L9: 寒河江市環境基本計画（R5.3改定） | M9: R5〜R14（10年間） | N9: 14 | O9: 確認済 | P9: 未確認 | Q9: https://www.city.sagae.yamagata.jp/shisei/keikaku/toshikankyokeikaku/kankyokeikaku.html | R9: 交通：法定の地域公共交通計画は見当たらず、市の生活交通ネットワーク計画と県計画（山形県地域公共交通計画（県・市町村共同、次期計画R8.3.27策定））で対応。環境：R5.3改定、期間は検索で確認できず。 【追加調査 2026-10】環境：R5.3改定版の計画期間は2023（R5）〜2032（R14）年度の10年間。旧計画（H26〜R5）を1年前倒しで改定（R4ゼロカーボンシティ宣言を受け）。計画ページ https://www.city.sagae.yamagata.jp/shisei/keikaku/toshikankyokeikaku/kankyokeikaku.html 。 根拠: 計画期間は令和5年度から令和14年度までの10年間（前計画 平成26年度〜令和5年度を1年前倒しで改定） | S9: 調査済 | T9: 未掲載【当方は計画あり】
A10: 7 | B10: 上山市 | C10: =IF(OR(D10="◎",E10="◎"),"◎ 営業",IF(OR(D10="△",E10="△"),"△ 着手済・要確認",IF(OR(D10="？",E10="？"),"？ 期間要確認","✕ 対象外"))) | D10: =IF(J10="計画なし","－",IF(J10="策定済","✕",IF(H10="","？",IF(AND(H10>=TGT_MIN,H10<=TGT_MAX),IF(J10="着手済","△","◎"),"✕")))) | E10: =IF(P10="計画なし","－",IF(P10="策定済","✕",IF(N10="","？",IF(AND(N10>=TGT_MIN,N10<=TGT_MAX),IF(P10="着手済","△","◎"),"✕")))) | F10: 山形県地域公共交通計画（県・市町村共同、次期計画R8.3.27策定） | G10: R8〜不明 | I10: 推定 | J10: 策定済 | K10: https://www.pref.yamagata.jp/020057/kurashi/kendo/kotsuseisaku/ykotsu_kasseikakyougikai.html | L10: 第3期上山市快適環境基本計画 | M10: R6〜R12 | N10: 12 | O10: 確認済 | P10: 未確認 | Q10: https://www.city.kaminoyama.yamagata.jp/soshiki/6/kaitekikankyou-gaiyou.html | R10: 交通：市単独の地域公共交通計画は検索で見当たらず（上山市地域公共交通会議のみ）。山形県地域公共交通計画（前計画R3〜R7）は市町村の利便増進実施計画等を内包する県全域計画。次期計画はR8.2パブコメ（https://www200.pref.yamagata.jp/020057/keikakupabukomepress2.html ）を経てR8.3.27策定（期間は未確認、R8開始）。 環境：R6.4〜R13.3の8年間（第8次振興計画に合わせる）。 | S10: 調査済 | T10: 未掲載【当方は計画あり】
A11: 8 | B11: 村山市 | C11: =IF(OR(D11="◎",E11="◎"),"◎ 営業",IF(OR(D11="△",E11="△"),"△ 着手済・要確認",IF(OR(D11="？",E11="？"),"？ 期間要確認","✕ 対象外"))) | D11: =IF(J11="計画なし","－",IF(J11="策定済","✕",IF(H11="","？",IF(AND(H11>=TGT_MIN,H11<=TGT_MAX),IF(J11="着手済","△","◎"),"✕")))) | E11: =IF(P11="計画なし","－",IF(P11="策定済","✕",IF(N11="","？",IF(AND(N11>=TGT_MIN,N11<=TGT_MAX),IF(P11="着手済","△","◎"),"✕")))) | F11: 山形県地域公共交通計画（県・市町村共同、次期計画R8.3.27策定） | G11: R8〜不明 | I11: 推定 | J11: 策定済 | K11: https://www.pref.yamagata.jp/020057/kurashi/kendo/kotsuseisaku/ykotsu_kasseikakyougikai.html | L11: 村山市環境基本計画（第２次） | M11: H30〜R9 | N11: 9 | O11: 確認済 | P11: 未確認 | Q11: https://www.city.murayama.lg.jp/kurashi/shizen/kankyohozen/kankyoukihon.files/kankyou-2.pdf | R11: 環境：H30〜R9（2027）の10年計画で終期R9。次期（第3次）策定の着手は未確認（R8〜R9に着手見込み・営業対象）。交通：市単独計画は見当たらず（市営バス・乗合タクシー運行）。山形県地域公共交通計画（前計画R3〜R7）は市町村の利便増進実施計画等を内包する県全域計画。次期計画はR8.2パブコメ（https://www200.pref.yamagata.jp/020057/keikakupabukomepress2.html ）を経てR8.3.27策定（期間は未確認、R8開始）。 【ファクトチェック 2026-10-01: 正しい】確認期間: H30〜R9（平成30年度〜平成39年度）／次期: 確認できず（市サイト内で第3次計画・アンケート等の情報見当たらず）／根拠: https://www.city.murayama.lg.jp/kurashi/shizen/kankyohozen/kankyoukihon.files/kankyou-2.pdf | S11: 調査済 | T11: 未掲載【当方は計画あり】
A12: 9 | B12: 長井市 | C12: =IF(OR(D12="◎",E12="◎"),"◎ 営業",IF(OR(D12="△",E12="△"),"△ 着手済・要確認",IF(OR(D12="？",E12="？"),"？ 期間要確認","✕ 対象外"))) | D12: =IF(J12="計画なし","－",IF(J12="策定済","✕",IF(H12="","？",IF(AND(H12>=TGT_MIN,H12<=TGT_MAX),IF(J12="着手済","△","◎"),"✕")))) | E12: =IF(P12="計画なし","－",IF(P12="策定済","✕",IF(N12="","？",IF(AND(N12>=TGT_MIN,N12<=TGT_MAX),IF(P12="着手済","△","◎"),"✕")))) | F12: 長井市地域公共交通計画（案） | G12: 不明 | I12: 不明 | J12: 着手済 | K12: https://www.city.nagai.yamagata.jp/kurashi_tetsuzuki/kokyokotsu/1/15982.html | L12: 第4次長井市環境基本計画 | M12: R6〜R15 | N12: 15 | O12: 確認済 | P12: 未確認 | Q12: https://www.city.nagai.yamagata.jp/soshiki/sougoseisaku/106/205/6/sisakukeikaku/13731.html | R12: 交通：これまでは県計画内の利便増進実施計画（長井市版、R3〜R7）で対応。市独自の地域公共交通計画（案）のパブコメをR8.3.12〜3.25に実施、策定完了・期間は未確認。R7交通空白解消緊急対策事業調査検討業務プロポーザルあり https://www.city.nagai.yamagata.jp/soshiki/chiikidukuri/105/201/1/15228.html 。 | S12: 調査済 | T12: 掲載（広域：フラワー長井線沿線）
A13: 10 | B13: 天童市 | C13: =IF(OR(D13="◎",E13="◎"),"◎ 営業",IF(OR(D13="△",E13="△"),"△ 着手済・要確認",IF(OR(D13="？",E13="？"),"？ 期間要確認","✕ 対象外"))) | D13: =IF(J13="計画なし","－",IF(J13="策定済","✕",IF(H13="","？",IF(AND(H13>=TGT_MIN,H13<=TGT_MAX),IF(J13="着手済","△","◎"),"✕")))) | E13: =IF(P13="計画なし","－",IF(P13="策定済","✕",IF(N13="","？",IF(AND(N13>=TGT_MIN,N13<=TGT_MAX),IF(P13="着手済","△","◎"),"✕")))) | F13: 山形県地域公共交通計画（県・市町村共同、次期計画R8.3.27策定） | G13: R8〜不明 | I13: 推定 | J13: 策定済 | K13: https://www.pref.yamagata.jp/020057/kurashi/kendo/kotsuseisaku/ykotsu_kasseikakyougikai.html | L13: 第三次天童市環境基本計画 | M13: R4〜R13 | N13: 13 | O13: 確認済 | P13: 未確認 | Q13: https://www.city.tendo.yamagata.jp/municipal/shisaku/kannkyoukihonn.html | R13: 交通：市単独の地域公共交通計画は検索で見当たらず（地域公共交通会議で市民バス等を協議）。山形県地域公共交通計画（前計画R3〜R7）は市町村の利便増進実施計画等を内包する県全域計画。次期計画はR8.2パブコメ（https://www200.pref.yamagata.jp/020057/keikakupabukomepress2.html ）を経てR8.3.27策定（期間は未確認、R8開始）。 | S13: 調査済 | T13: 未掲載【当方は計画あり】
A14: 11 | B14: 東根市 | C14: =IF(OR(D14="◎",E14="◎"),"◎ 営業",IF(OR(D14="△",E14="△"),"△ 着手済・要確認",IF(OR(D14="？",E14="？"),"？ 期間要確認","✕ 対象外"))) | D14: =IF(J14="計画なし","－",IF(J14="策定済","✕",IF(H14="","？",IF(AND(H14>=TGT_MIN,H14<=TGT_MAX),IF(J14="着手済","△","◎"),"✕")))) | E14: =IF(P14="計画なし","－",IF(P14="策定済","✕",IF(N14="","？",IF(AND(N14>=TGT_MIN,N14<=TGT_MAX),IF(P14="着手済","△","◎"),"✕")))) | F14: 山形県地域公共交通計画（県・市町村共同、次期計画R8.3.27策定） | G14: R8〜不明 | I14: 推定 | J14: 策定済 | K14: https://www.pref.yamagata.jp/020057/kurashi/kendo/kotsuseisaku/ykotsu_kasseikakyougikai.html | L14: 第３次東根市大けやき環境基本計画 | M14: R5〜R14（10年間） | N14: 14 | O14: 確認済 | P14: 未確認 | Q14: https://www.city.higashine.yamagata.jp/section_list/section008/seikatsukankyo-keikaku/169 | R14: 交通：市単独の地域公共交通計画は見当たらず（市民バス運行、県計画を踏まえる）。山形県地域公共交通計画（前計画R3〜R7）は市町村の利便増進実施計画等を内包する県全域計画。次期計画はR8.2パブコメ（https://www200.pref.yamagata.jp/020057/keikakupabukomepress2.html ）を経てR8.3.27策定（期間は未確認、R8開始）。 環境：前計画H25〜R4の後継としてR4年度に第3次策定（期間は未確認、R5開始と推定）。 【追加調査 2026-10】環境：第3次東根市大けやき環境基本計画はR4年度策定、計画期間R5〜R14（2023〜2032年度）の10年間。前計画（改訂版）はH25〜R4。計画ページ https://www.city.higashine.yamagata.jp/section_list/section008/seikatsukankyo-keikaku/169 （本編・概要版PDF掲載）。 根拠: The third version covers the period from R5 to R14 (fiscal year 2023 to fiscal year 2032) | S14: 調査済 | T14: 未掲載【当方は計画あり】
A15: 12 | B15: 尾花沢市 | C15: =IF(OR(D15="◎",E15="◎"),"◎ 営業",IF(OR(D15="△",E15="△"),"△ 着手済・要確認",IF(OR(D15="？",E15="？"),"？ 期間要確認","✕ 対象外"))) | D15: =IF(J15="計画なし","－",IF(J15="策定済","✕",IF(H15="","？",IF(AND(H15>=TGT_MIN,H15<=TGT_MAX),IF(J15="着手済","△","◎"),"✕")))) | E15: =IF(P15="計画なし","－",IF(P15="策定済","✕",IF(N15="","？",IF(AND(N15>=TGT_MIN,N15<=TGT_MAX),IF(P15="着手済","△","◎"),"✕")))) | F15: 山形県地域公共交通計画（県・市町村共同、次期計画R8.3.27策定） | G15: R8〜不明 | I15: 推定 | J15: 策定済 | K15: https://www.pref.yamagata.jp/020057/kurashi/kendo/kotsuseisaku/ykotsu_kasseikakyougikai.html | L15: 尾花沢市環境基本計画（令和4年〜令和13年） | M15: R4〜R13 | N15: 13 | O15: 確認済 | P15: 未確認 | Q15: https://www.city.obanazawa.yamagata.jp/kurashi/kankyo/kankyo-shisaku/715 | R15: 交通：市単独の地域公共交通計画は見当たらず。R7.10から一部路線バス休止・AIデマンド交通へ移行。山形県地域公共交通計画（前計画R3〜R7）は市町村の利便増進実施計画等を内包する県全域計画。次期計画はR8.2パブコメ（https://www200.pref.yamagata.jp/020057/keikakupabukomepress2.html ）を経てR8.3.27策定（期間は未確認、R8開始）。 | S15: 調査済 | T15: 未掲載【当方は計画あり】
A16: 13 | B16: 南陽市 | C16: =IF(OR(D16="◎",E16="◎"),"◎ 営業",IF(OR(D16="△",E16="△"),"△ 着手済・要確認",IF(OR(D16="？",E16="？"),"？ 期間要確認","✕ 対象外"))) | D16: =IF(J16="計画なし","－",IF(J16="策定済","✕",IF(H16="","？",IF(AND(H16>=TGT_MIN,H16<=TGT_MAX),IF(J16="着手済","△","◎"),"✕")))) | E16: =IF(P16="計画なし","－",IF(P16="策定済","✕",IF(N16="","？",IF(AND(N16>=TGT_MIN,N16<=TGT_MAX),IF(P16="着手済","△","◎"),"✕")))) | F16: 南陽市地域公共交通計画（案） | G16: 不明 | I16: 不明 | J16: 着手済 | K16: http://www.city.nanyo.yamagata.jp/kikakusuishin/6356 | M16: 不明 | O16: 不明 | P16: 計画なし | R16: 交通：県計画(R3〜R7)終了に合わせR7年度に市独自の地域公共交通計画を策定（R7.5 協議会 http://www.city.nanyo.yamagata.jp/tiikikoukyoukoutuu/6089 、R7施政方針）。計画案のパブコメ実施を確認、策定完了・期間は未確認。環境：環境基本計画は検索で見当たらず。代替として地球温暖化対策実行計画（区域施策編）R5〜R12（R7.12一部改正）http://www.city.nanyo.yamagata.jp/up/files/siminkurasi/tikyuuonndannka/kuikishisakuhen_honpen(R7).pdf 。 | S16: 調査済 | T16: 掲載（広域：フラワー長井線沿線）
A17: 14 | B17: 山辺町 | C17: =IF(OR(D17="◎",E17="◎"),"◎ 営業",IF(OR(D17="△",E17="△"),"△ 着手済・要確認",IF(OR(D17="？",E17="？"),"？ 期間要確認","✕ 対象外"))) | D17: =IF(J17="計画なし","－",IF(J17="策定済","✕",IF(H17="","？",IF(AND(H17>=TGT_MIN,H17<=TGT_MAX),IF(J17="着手済","△","◎"),"✕")))) | E17: =IF(P17="計画なし","－",IF(P17="策定済","✕",IF(N17="","？",IF(AND(N17>=TGT_MIN,N17<=TGT_MAX),IF(P17="着手済","△","◎"),"✕")))) | F17: 山形県地域公共交通計画（県・市町村共同、次期計画R8.3.27策定） | G17: R8〜不明 | I17: 推定 | J17: 策定済 | K17: https://www.pref.yamagata.jp/020057/kurashi/kendo/kotsuseisaku/ykotsu_kasseikakyougikai.html | M17: 不明 | O17: 不明 | P17: 計画なし | R17: 交通：町単独の地域公共交通計画は見当たらず。旧『山辺町生活交通ネットワーク計画』https://www.town.yamanobe.yamagata.jp/uploaded/attachment/465.pdf あり、コミュニティバス運行。山形県地域公共交通計画（前計画R3〜R7）は市町村の利便増進実施計画等を内包する県全域計画。次期計画はR8.2パブコメ（https://www200.pref.yamagata.jp/020057/keikakupabukomepress2.html ）を経てR8.3.27策定（期間は未確認、R8開始）。 環境：環境基本計画は検索で見当たらず。 | S17: 調査済 | T17: 未掲載【当方は計画あり】
A18: 15 | B18: 中山町 | C18: =IF(OR(D18="◎",E18="◎"),"◎ 営業",IF(OR(D18="△",E18="△"),"△ 着手済・要確認",IF(OR(D18="？",E18="？"),"？ 期間要確認","✕ 対象外"))) | D18: =IF(J18="計画なし","－",IF(J18="策定済","✕",IF(H18="","？",IF(AND(H18>=TGT_MIN,H18<=TGT_MAX),IF(J18="着手済","△","◎"),"✕")))) | E18: =IF(P18="計画なし","－",IF(P18="策定済","✕",IF(N18="","？",IF(AND(N18>=TGT_MIN,N18<=TGT_MAX),IF(P18="着手済","△","◎"),"✕")))) | F18: 山形県地域公共交通計画（県・市町村共同、次期計画R8.3.27策定） | G18: R8〜不明 | I18: 推定 | J18: 策定済 | K18: https://www.pref.yamagata.jp/020057/kurashi/kendo/kotsuseisaku/ykotsu_kasseikakyougikai.html | M18: 不明 | O18: 不明 | P18: 計画なし | R18: 交通：町単独の地域公共交通計画は見当たらず。『中山町生活交通ネットワーク計画』策定（パブコメ結果 https://www.town.nakayama.yamagata.jp/soshiki/seisaku/machidukurisuishin/251.html 、期間未確認）。山形県地域公共交通計画（前計画R3〜R7）は市町村の利便増進実施計画等を内包する県全域計画。次期計画はR8.2パブコメ（https://www200.pref.yamagata.jp/020057/keikakupabukomepress2.html ）を経てR8.3.27策定（期間は未確認、R8開始）。 環境：環境基本計画は検索で見当たらず。 | S18: 調査済 | T18: 未掲載【当方は計画あり】
A19: 16 | B19: 河北町 | C19: =IF(OR(D19="◎",E19="◎"),"◎ 営業",IF(OR(D19="△",E19="△"),"△ 着手済・要確認",IF(OR(D19="？",E19="？"),"？ 期間要確認","✕ 対象外"))) | D19: =IF(J19="計画なし","－",IF(J19="策定済","✕",IF(H19="","？",IF(AND(H19>=TGT_MIN,H19<=TGT_MAX),IF(J19="着手済","△","◎"),"✕")))) | E19: =IF(P19="計画なし","－",IF(P19="策定済","✕",IF(N19="","？",IF(AND(N19>=TGT_MIN,N19<=TGT_MAX),IF(P19="着手済","△","◎"),"✕")))) | F19: 河北町地域公共交通計画（総合計画で言及） | G19: 不明 | I19: 不明 | J19: 未確認 | L19: 第3次雛とべに花の里環境基本計画 | M19: R6〜R15 | N19: 15 | O19: 確認済 | P19: 未確認 | Q19: https://www.town.kahoku.yamagata.jp/gyouseizyouhou/seisaku_keikaku/keikaku_matizukuri/index.html | R19: 交通：第8次総合計画に町地域公共交通計画への言及があるが計画書・期間は検索で確認できず（公共交通ページ https://www.town.kahoku.yamagata.jp/kurasi_tetuzuki/douro_koutuu/koukyoukoutuu/index.html ）。県計画（山形県地域公共交通計画（県・市町村共同、次期計画R8.3.27策定））も対象。環境：第3次（区域施策編を包含）R6年度から10年間。 | S19: 調査済 | T19: 掲載
A20: 17 | B20: 西川町 | C20: =IF(OR(D20="◎",E20="◎"),"◎ 営業",IF(OR(D20="△",E20="△"),"△ 着手済・要確認",IF(OR(D20="？",E20="？"),"？ 期間要確認","✕ 対象外"))) | D20: =IF(J20="計画なし","－",IF(J20="策定済","✕",IF(H20="","？",IF(AND(H20>=TGT_MIN,H20<=TGT_MAX),IF(J20="着手済","△","◎"),"✕")))) | E20: =IF(P20="計画なし","－",IF(P20="策定済","✕",IF(N20="","？",IF(AND(N20>=TGT_MIN,N20<=TGT_MAX),IF(P20="着手済","△","◎"),"✕")))) | F20: 西川町地域公共交通計画 | G20: R4〜R8 | H20: 8 | I20: 推定 | J20: 未確認 | K20: https://www.town.nishikawa.yamagata.jp/uploaded/attachment/510.pdf | M20: 不明 | O20: 不明 | P20: 計画なし | R20: 交通：R4.3策定（計画ページ https://www.town.nishikawa.yamagata.jp/soshiki/chomin/1317.html ）。期間は5年と仮定するとR8終期（未確認・要確認）。次期計画の着手は未確認。環境：環境基本計画は検索で見当たらず（ゼロカーボンシティ宣言あり）。 | S20: 調査済 | T20: 掲載
A21: 18 | B21: 朝日町 | C21: =IF(OR(D21="◎",E21="◎"),"◎ 営業",IF(OR(D21="△",E21="△"),"△ 着手済・要確認",IF(OR(D21="？",E21="？"),"？ 期間要確認","✕ 対象外"))) | D21: =IF(J21="計画なし","－",IF(J21="策定済","✕",IF(H21="","？",IF(AND(H21>=TGT_MIN,H21<=TGT_MAX),IF(J21="着手済","△","◎"),"✕")))) | E21: =IF(P21="計画なし","－",IF(P21="策定済","✕",IF(N21="","？",IF(AND(N21>=TGT_MIN,N21<=TGT_MAX),IF(P21="着手済","△","◎"),"✕")))) | F21: 山形県地域公共交通計画（県・市町村共同、次期計画R8.3.27策定） | G21: R8〜不明 | I21: 推定 | J21: 策定済 | K21: https://www.pref.yamagata.jp/020057/kurashi/kendo/kotsuseisaku/ykotsu_kasseikakyougikai.html | L21: 第2次朝日町環境基本計画 | M21: H30〜R9 | N21: 9 | O21: 確認済 | P21: 未確認 | Q21: https://www.town.asahi.yamagata.jp/portal/soshikinogoannai/somuka/bosaigakari/3_1/3/2438.html | R21: 環境：H30.3策定（第1次H23.3、見直し版あり）。第6次総合発展計画（H30〜R9の10年）と同期間とみられR9終期（計画書本文での期間記載は未確認）。次期計画着手は未確認・営業候補。交通：町単独の法定計画は見当たらず（旧・地域公共交通総合連携計画H22.3、H30活性化協議会設置）。山形県地域公共交通計画（前計画R3〜R7）は市町村の利便増進実施計画等を内包する県全域計画。次期計画はR8.2パブコメ（https://www200.pref.yamagata.jp/020057/keikakupabukomepress2.html ）を経てR8.3.27策定（期間は未確認、R8開始）。 【ファクトチェック 2026-10-01: 正しい】確認期間: H30〜R9（2018〜2027年度）／次期: 確認できず（第3次計画の情報なし）／根拠: https://www.town.asahi.yamagata.jp/portal/soshikinogoannai/somuka/bosaigakari/3_1/3/2438.html | S21: 調査済 | T21: 未掲載【当方は計画あり】
A22: 19 | B22: 大江町 | C22: =IF(OR(D22="◎",E22="◎"),"◎ 営業",IF(OR(D22="△",E22="△"),"△ 着手済・要確認",IF(OR(D22="？",E22="？"),"？ 期間要確認","✕ 対象外"))) | D22: =IF(J22="計画なし","－",IF(J22="策定済","✕",IF(H22="","？",IF(AND(H22>=TGT_MIN,H22<=TGT_MAX),IF(J22="着手済","△","◎"),"✕")))) | E22: =IF(P22="計画なし","－",IF(P22="策定済","✕",IF(N22="","？",IF(AND(N22>=TGT_MIN,N22<=TGT_MAX),IF(P22="着手済","△","◎"),"✕")))) | F22: 山形県地域公共交通計画（県・市町村共同、次期計画R8.3.27策定） | G22: R8〜不明 | I22: 推定 | J22: 策定済 | K22: https://www.pref.yamagata.jp/020057/kurashi/kendo/kotsuseisaku/ykotsu_kasseikakyougikai.html | L22: 第3次大江町環境基本計画 | M22: R7〜R12 | N22: 12 | O22: 確認済 | P22: 未確認 | Q22: https://www.town.oe.yamagata.jp/government/mainpolicy/keikaku/ | R22: 交通：町単独の地域公共交通計画は見当たらず。山形県地域公共交通計画（前計画R3〜R7）は市町村の利便増進実施計画等を内包する県全域計画。次期計画はR8.2パブコメ（https://www200.pref.yamagata.jp/020057/keikakupabukomepress2.html ）を経てR8.3.27策定（期間は未確認、R8開始）。 環境：第3次はR7〜R12年度（主な計画ページで確認）。 | S22: 調査済 | T22: 未掲載【当方は計画あり】
A23: 20 | B23: 大石田町 | C23: =IF(OR(D23="◎",E23="◎"),"◎ 営業",IF(OR(D23="△",E23="△"),"△ 着手済・要確認",IF(OR(D23="？",E23="？"),"？ 期間要確認","✕ 対象外"))) | D23: =IF(J23="計画なし","－",IF(J23="策定済","✕",IF(H23="","？",IF(AND(H23>=TGT_MIN,H23<=TGT_MAX),IF(J23="着手済","△","◎"),"✕")))) | E23: =IF(P23="計画なし","－",IF(P23="策定済","✕",IF(N23="","？",IF(AND(N23>=TGT_MIN,N23<=TGT_MAX),IF(P23="着手済","△","◎"),"✕")))) | F23: 山形県地域公共交通計画（県・市町村共同、次期計画R8.3.27策定） | G23: R8〜不明 | I23: 推定 | J23: 策定済 | K23: https://www.pref.yamagata.jp/020057/kurashi/kendo/kotsuseisaku/ykotsu_kasseikakyougikai.html | M23: 不明 | O23: 不明 | P23: 計画なし | R23: 交通：町単独の地域公共交通計画は見当たらず（各種計画一覧 https://www.town.oishida.yamagata.jp/chousei/keikaku/index.html ）。山形県地域公共交通計画（前計画R3〜R7）は市町村の利便増進実施計画等を内包する県全域計画。次期計画はR8.2パブコメ（https://www200.pref.yamagata.jp/020057/keikakupabukomepress2.html ）を経てR8.3.27策定（期間は未確認、R8開始）。 環境：環境基本計画は検索で見当たらず。 | S23: 調査済 | T23: 未掲載【当方は計画あり】
A24: 21 | B24: 金山町 | C24: =IF(OR(D24="◎",E24="◎"),"◎ 営業",IF(OR(D24="△",E24="△"),"△ 着手済・要確認",IF(OR(D24="？",E24="？"),"？ 期間要確認","✕ 対象外"))) | D24: =IF(J24="計画なし","－",IF(J24="策定済","✕",IF(H24="","？",IF(AND(H24>=TGT_MIN,H24<=TGT_MAX),IF(J24="着手済","△","◎"),"✕")))) | E24: =IF(P24="計画なし","－",IF(P24="策定済","✕",IF(N24="","？",IF(AND(N24>=TGT_MIN,N24<=TGT_MAX),IF(P24="着手済","△","◎"),"✕")))) | F24: 山形県地域公共交通計画（県・市町村共同、次期計画R8.3.27策定） | G24: R8〜不明 | I24: 推定 | J24: 策定済 | K24: https://www.pref.yamagata.jp/020057/kurashi/kendo/kotsuseisaku/ykotsu_kasseikakyougikai.html | M24: 不明 | O24: 不明 | P24: 計画なし | R24: 山形県最上郡金山町。交通：町単独計画は見当たらず（デマンドハイヤー運行）。山形県地域公共交通計画（前計画R3〜R7）は市町村の利便増進実施計画等を内包する県全域計画。次期計画はR8.2パブコメ（https://www200.pref.yamagata.jp/020057/keikakupabukomepress2.html ）を経てR8.3.27策定（期間は未確認、R8開始）。 最上地域8市町村は県計画の最上地域部会で広域的な公共交通再編を検討中（R7.11県協議会資料 https://www.pref.yamagata.jp/documents/47862/20251125shiryou2-2.pdf ）。 環境：環境基本計画は検索で見当たらず。 | S24: 調査済 | T24: 未掲載【当方は計画あり】
A25: 22 | B25: 最上町 | C25: =IF(OR(D25="◎",E25="◎"),"◎ 営業",IF(OR(D25="△",E25="△"),"△ 着手済・要確認",IF(OR(D25="？",E25="？"),"？ 期間要確認","✕ 対象外"))) | D25: =IF(J25="計画なし","－",IF(J25="策定済","✕",IF(H25="","？",IF(AND(H25>=TGT_MIN,H25<=TGT_MAX),IF(J25="着手済","△","◎"),"✕")))) | E25: =IF(P25="計画なし","－",IF(P25="策定済","✕",IF(N25="","？",IF(AND(N25>=TGT_MIN,N25<=TGT_MAX),IF(P25="着手済","△","◎"),"✕")))) | F25: 山形県地域公共交通計画（県・市町村共同、次期計画R8.3.27策定） | G25: R8〜不明 | I25: 推定 | J25: 策定済 | K25: https://www.pref.yamagata.jp/020057/kurashi/kendo/kotsuseisaku/ykotsu_kasseikakyougikai.html | M25: 不明 | O25: 不明 | P25: 計画なし | R25: 交通：町単独計画は見当たらず（予約制乗合バス https://town.mogami.lg.jp/life/03koutsuu/ ）。山形県地域公共交通計画（前計画R3〜R7）は市町村の利便増進実施計画等を内包する県全域計画。次期計画はR8.2パブコメ（https://www200.pref.yamagata.jp/020057/keikakupabukomepress2.html ）を経てR8.3.27策定（期間は未確認、R8開始）。 最上地域8市町村は県計画の最上地域部会で広域的な公共交通再編を検討中（R7.11県協議会資料 https://www.pref.yamagata.jp/documents/47862/20251125shiryou2-2.pdf ）。 環境：環境基本計画は検索で見当たらず。 | S25: 調査済 | T25: 未掲載【当方は計画あり】
A26: 23 | B26: 舟形町 | C26: =IF(OR(D26="◎",E26="◎"),"◎ 営業",IF(OR(D26="△",E26="△"),"△ 着手済・要確認",IF(OR(D26="？",E26="？"),"？ 期間要確認","✕ 対象外"))) | D26: =IF(J26="計画なし","－",IF(J26="策定済","✕",IF(H26="","？",IF(AND(H26>=TGT_MIN,H26<=TGT_MAX),IF(J26="着手済","△","◎"),"✕")))) | E26: =IF(P26="計画なし","－",IF(P26="策定済","✕",IF(N26="","？",IF(AND(N26>=TGT_MIN,N26<=TGT_MAX),IF(P26="着手済","△","◎"),"✕")))) | F26: 山形県地域公共交通計画（県・市町村共同、次期計画R8.3.27策定） | G26: R8〜不明 | I26: 推定 | J26: 策定済 | K26: https://www.pref.yamagata.jp/020057/kurashi/kendo/kotsuseisaku/ykotsu_kasseikakyougikai.html | M26: 不明 | O26: 不明 | P26: 計画なし | R26: 交通：町単独計画は見当たらず。山形県地域公共交通計画（前計画R3〜R7）は市町村の利便増進実施計画等を内包する県全域計画。次期計画はR8.2パブコメ（https://www200.pref.yamagata.jp/020057/keikakupabukomepress2.html ）を経てR8.3.27策定（期間は未確認、R8開始）。 最上地域8市町村は県計画の最上地域部会で広域的な公共交通再編を検討中（R7.11県協議会資料 https://www.pref.yamagata.jp/documents/47862/20251125shiryou2-2.pdf ）。 環境：環境基本計画は見当たらず。代替としてR7年度に地球温暖化対策実行計画（区域施策編）策定業務を発注（仕様書 https://www.town.funagata.yamagata.jp/s007/shigoto/050/sienn/kuikisesakusiyousyo.pdf ）。 | S26: 調査済 | T26: 未掲載【当方は計画あり】
A27: 24 | B27: 真室川町 | C27: =IF(OR(D27="◎",E27="◎"),"◎ 営業",IF(OR(D27="△",E27="△"),"△ 着手済・要確認",IF(OR(D27="？",E27="？"),"？ 期間要確認","✕ 対象外"))) | D27: =IF(J27="計画なし","－",IF(J27="策定済","✕",IF(H27="","？",IF(AND(H27>=TGT_MIN,H27<=TGT_MAX),IF(J27="着手済","△","◎"),"✕")))) | E27: =IF(P27="計画なし","－",IF(P27="策定済","✕",IF(N27="","？",IF(AND(N27>=TGT_MIN,N27<=TGT_MAX),IF(P27="着手済","△","◎"),"✕")))) | F27: 山形県地域公共交通計画（県・市町村共同、次期計画R8.3.27策定） | G27: R8〜不明 | I27: 推定 | J27: 策定済 | K27: https://www.pref.yamagata.jp/020057/kurashi/kendo/kotsuseisaku/ykotsu_kasseikakyougikai.html | M27: 不明 | O27: 不明 | P27: 計画なし | R27: 交通：町単独計画は見当たらず（町営バス・デマンドタクシー）。山形県地域公共交通計画（前計画R3〜R7）は市町村の利便増進実施計画等を内包する県全域計画。次期計画はR8.2パブコメ（https://www200.pref.yamagata.jp/020057/keikakupabukomepress2.html ）を経てR8.3.27策定（期間は未確認、R8開始）。 最上地域8市町村は県計画の最上地域部会で広域的な公共交通再編を検討中（R7.11県協議会資料 https://www.pref.yamagata.jp/documents/47862/20251125shiryou2-2.pdf ）。 環境：環境基本計画は検索で見当たらず。 | S27: 調査済 | T27: 未掲載【当方は計画あり】
A28: 25 | B28: 大蔵村 | C28: =IF(OR(D28="◎",E28="◎"),"◎ 営業",IF(OR(D28="△",E28="△"),"△ 着手済・要確認",IF(OR(D28="？",E28="？"),"？ 期間要確認","✕ 対象外"))) | D28: =IF(J28="計画なし","－",IF(J28="策定済","✕",IF(H28="","？",IF(AND(H28>=TGT_MIN,H28<=TGT_MAX),IF(J28="着手済","△","◎"),"✕")))) | E28: =IF(P28="計画なし","－",IF(P28="策定済","✕",IF(N28="","？",IF(AND(N28>=TGT_MIN,N28<=TGT_MAX),IF(P28="着手済","△","◎"),"✕")))) | F28: 山形県地域公共交通計画（県・市町村共同、次期計画R8.3.27策定） | G28: R8〜不明 | I28: 推定 | J28: 策定済 | K28: https://www.pref.yamagata.jp/020057/kurashi/kendo/kotsuseisaku/ykotsu_kasseikakyougikai.html | M28: 不明 | O28: 不明 | P28: 計画なし | R28: 交通：村単独計画は見当たらず（村営バス）。山形県地域公共交通計画（前計画R3〜R7）は市町村の利便増進実施計画等を内包する県全域計画。次期計画はR8.2パブコメ（https://www200.pref.yamagata.jp/020057/keikakupabukomepress2.html ）を経てR8.3.27策定（期間は未確認、R8開始）。 最上地域8市町村は県計画の最上地域部会で広域的な公共交通再編を検討中（R7.11県協議会資料 https://www.pref.yamagata.jp/documents/47862/20251125shiryou2-2.pdf ）。 環境：環境基本計画は検索で見当たらず（計画・公表 https://www.vill.ohkura.yamagata.jp/gyoseijoho/seisaku_keikaku/keikaku_kohyo/index.html ）。 | S28: 調査済 | T28: 未掲載【当方は計画あり】
A29: 26 | B29: 鮭川村 | C29: =IF(OR(D29="◎",E29="◎"),"◎ 営業",IF(OR(D29="△",E29="△"),"△ 着手済・要確認",IF(OR(D29="？",E29="？"),"？ 期間要確認","✕ 対象外"))) | D29: =IF(J29="計画なし","－",IF(J29="策定済","✕",IF(H29="","？",IF(AND(H29>=TGT_MIN,H29<=TGT_MAX),IF(J29="着手済","△","◎"),"✕")))) | E29: =IF(P29="計画なし","－",IF(P29="策定済","✕",IF(N29="","？",IF(AND(N29>=TGT_MIN,N29<=TGT_MAX),IF(P29="着手済","△","◎"),"✕")))) | F29: 山形県地域公共交通計画（県・市町村共同、次期計画R8.3.27策定） | G29: R8〜不明 | I29: 推定 | J29: 策定済 | K29: https://www.pref.yamagata.jp/020057/kurashi/kendo/kotsuseisaku/ykotsu_kasseikakyougikai.html | M29: 不明 | O29: 不明 | P29: 計画なし | R29: 交通：村単独計画は見当たらず。山形県地域公共交通計画（前計画R3〜R7）は市町村の利便増進実施計画等を内包する県全域計画。次期計画はR8.2パブコメ（https://www200.pref.yamagata.jp/020057/keikakupabukomepress2.html ）を経てR8.3.27策定（期間は未確認、R8開始）。 最上地域8市町村は県計画の最上地域部会で広域的な公共交通再編を検討中（R7.11県協議会資料 https://www.pref.yamagata.jp/documents/47862/20251125shiryou2-2.pdf ）。 環境：環境基本計画は検索で見当たらず（政策・各種計画 https://www.vill.sakegawa.yamagata.jp/government/jigyo-keikaku/seisaku/ ）。 | S29: 調査済 | T29: 未掲載【当方は計画あり】
A30: 27 | B30: 戸沢村 | C30: =IF(OR(D30="◎",E30="◎"),"◎ 営業",IF(OR(D30="△",E30="△"),"△ 着手済・要確認",IF(OR(D30="？",E30="？"),"？ 期間要確認","✕ 対象外"))) | D30: =IF(J30="計画なし","－",IF(J30="策定済","✕",IF(H30="","？",IF(AND(H30>=TGT_MIN,H30<=TGT_MAX),IF(J30="着手済","△","◎"),"✕")))) | E30: =IF(P30="計画なし","－",IF(P30="策定済","✕",IF(N30="","？",IF(AND(N30>=TGT_MIN,N30<=TGT_MAX),IF(P30="着手済","△","◎"),"✕")))) | F30: 山形県地域公共交通計画（県・市町村共同、次期計画R8.3.27策定） | G30: R8〜不明 | I30: 推定 | J30: 策定済 | K30: https://www.pref.yamagata.jp/020057/kurashi/kendo/kotsuseisaku/ykotsu_kasseikakyougikai.html | M30: 不明 | O30: 不明 | P30: 計画なし | R30: 交通：村単独計画は見当たらず（村営バス）。山形県地域公共交通計画（前計画R3〜R7）は市町村の利便増進実施計画等を内包する県全域計画。次期計画はR8.2パブコメ（https://www200.pref.yamagata.jp/020057/keikakupabukomepress2.html ）を経てR8.3.27策定（期間は未確認、R8開始）。 最上地域8市町村は県計画の最上地域部会で広域的な公共交通再編を検討中（R7.11県協議会資料 https://www.pref.yamagata.jp/documents/47862/20251125shiryou2-2.pdf ）。 環境：環境基本計画は検索で見当たらず（計画・施策 https://www.vill.tozawa.yamagata.jp/gyoseijoho/keikaku_sesaku/ ）。 | S30: 調査済 | T30: 未掲載【当方は計画あり】
A31: 28 | B31: 高畠町 | C31: =IF(OR(D31="◎",E31="◎"),"◎ 営業",IF(OR(D31="△",E31="△"),"△ 着手済・要確認",IF(OR(D31="？",E31="？"),"？ 期間要確認","✕ 対象外"))) | D31: =IF(J31="計画なし","－",IF(J31="策定済","✕",IF(H31="","？",IF(AND(H31>=TGT_MIN,H31<=TGT_MAX),IF(J31="着手済","△","◎"),"✕")))) | E31: =IF(P31="計画なし","－",IF(P31="策定済","✕",IF(N31="","？",IF(AND(N31>=TGT_MIN,N31<=TGT_MAX),IF(P31="着手済","△","◎"),"✕")))) | F31: 高畠町地域公共交通計画 | G31: R8〜不明 | I31: 推定 | J31: 策定済 | K31: https://www.town.takahata.yamagata.jp/soshikiichiran/kikaku/3/kokyokotsu/4511.html | L31: 第3次高畠町環境基本計画 | M31: R5〜（10年ならR14） | N31: 14 | O31: 推定 | P31: 未確認 | Q31: https://www.town.takahata.yamagata.jp/kurashi/gyoseijoho/kakushukeikaku/1/2728.html | R31: 交通：町単独の地域公共交通計画は見当たらず（デマンド交通運行）。山形県地域公共交通計画（前計画R3〜R7）は市町村の利便増進実施計画等を内包する県全域計画。次期計画はR8.2パブコメ（https://www200.pref.yamagata.jp/020057/keikakupabukomepress2.html ）を経てR8.3.27策定（期間は未確認、R8開始）。 環境：第2次がR4年度で終了→第3次策定（R5開始と推定、終期未確認）。 【追加調査 2026-10】交通(2026-10調査)：町単独の「高畠町地域公共交通計画」を新規策定。計画案のパブリックコメントを令和7年12月17日〜令和8年1月7日に実施（https://www.town.takahata.yamagata.jp/soshikiichiran/kikaku/3/kokyokotsu/4511.html ）、協議の場は高畠町公共交通会議（H22設置 https://www.town.takahata.yamagata.jp/soshikiichiran/kikaku/3/machizukuri/4298.html ）。国交省一覧(R8.5末)に単独計画あり（期間満了でない）ことから、R7年度末頃策定・R8開始と推定。計画期間は検索結果本文で確認できず（計画案PDF・町サイトはWebFetch不可）。参考：山形県地域公共交通計画（次期）はR8〜R12（https://www.pref.yamagata.jp/documents/50579/keikaku_honpen.pdf ）。 根拠: 高畠町地域公共交通計画…意見募集期間は令和7年12月17日（水曜日）～令和8年1月7日（水曜日） 【追加調査 2026-10】環境：第2次（H25.3策定）がR4年度で期間終了→第3次高畠町環境基本計画をR5年度から実施（計画ページ https://www.town.takahata.yamagata.jp/kurashi/gyoseijoho/kakushukeikaku/1/2728.html ）。終期は検索3回で本文に出ず、10年間と仮定しR14と推定。 根拠: 第2次計画の計画期間が令和4年度で終了…令和5年度から第3次計画 | S31: 調査済 | T31: 掲載
A32: 29 | B32: 川西町 | C32: =IF(OR(D32="◎",E32="◎"),"◎ 営業",IF(OR(D32="△",E32="△"),"△ 着手済・要確認",IF(OR(D32="？",E32="？"),"？ 期間要確認","✕ 対象外"))) | D32: =IF(J32="計画なし","－",IF(J32="策定済","✕",IF(H32="","？",IF(AND(H32>=TGT_MIN,H32<=TGT_MAX),IF(J32="着手済","△","◎"),"✕")))) | E32: =IF(P32="計画なし","－",IF(P32="策定済","✕",IF(N32="","？",IF(AND(N32>=TGT_MIN,N32<=TGT_MAX),IF(P32="着手済","△","◎"),"✕")))) | F32: 川西町地域公共交通計画 | G32: R8〜R12 | H32: 12 | I32: 確認済 | J32: 策定済 | K32: https://www.town.kawanishi.yamagata.jp/kurashi/doro/02keikaku.pdf | M32: 不明 | O32: 不明 | P32: 計画なし | R32: 交通：町単独計画は見当たらず。山形県地域公共交通計画（前計画R3〜R7）は市町村の利便増進実施計画等を内包する県全域計画。次期計画はR8.2パブコメ（https://www200.pref.yamagata.jp/020057/keikakupabukomepress2.html ）を経てR8.3.27策定（期間は未確認、R8開始）。 環境：環境基本計画は検索で見当たらず（政策・計画 https://www.town.kawanishi.yamagata.jp/machinojoho/seisaku/ ）。 【追加調査 2026-10】町単独の『川西町地域公共交通計画』を確認（区域：町全域、計画期間R8〜R12の5年間、デマンド型乗合交通等）。町サイト掲載 本編 https://www.town.kawanishi.yamagata.jp/kurashi/doro/02keikaku.pdf 、概要 https://www.town.kawanishi.yamagata.jp/kurashi/doro/01keikakugaiyou.pdf （2026-10-02検索。WebFetchはブロックのため本文直接閲覧不可、検索結果本文で期間確認）。R8開始の新計画のため策定済。広域：フラワー長井線（2市2町）は鉄道事業再構築実施計画R6.4.1〜R16.3.31（https://www.mlit.go.jp/report/press/tetsudo05_hh_000146.html ）。県計画の記載は参考に格下げ。 根拠: 計画期間は令和８年度（2026年度）から令和１２年度（2030年度）までの５年間 | S32: 調査済 | T32: 掲載（広域：フラワー長井線沿線）
A33: 30 | B33: 小国町 | C33: =IF(OR(D33="◎",E33="◎"),"◎ 営業",IF(OR(D33="△",E33="△"),"△ 着手済・要確認",IF(OR(D33="？",E33="？"),"？ 期間要確認","✕ 対象外"))) | D33: =IF(J33="計画なし","－",IF(J33="策定済","✕",IF(H33="","？",IF(AND(H33>=TGT_MIN,H33<=TGT_MAX),IF(J33="着手済","△","◎"),"✕")))) | E33: =IF(P33="計画なし","－",IF(P33="策定済","✕",IF(N33="","？",IF(AND(N33>=TGT_MIN,N33<=TGT_MAX),IF(P33="着手済","△","◎"),"✕")))) | F33: 小国町地域公共交通網形成計画 | G33: 不明 | I33: 不明 | J33: 未確認 | K33: https://www.town.oguni.yamagata.jp/soshiki/choumin/1214.html | M33: 不明 | O33: 不明 | P33: 計画なし | R33: 交通：活性化再生法に基づく網形成計画を策定済（期間は検索で未確認、旧計画の可能性）。地域公共交通計画への移行は未確認。県計画（山形県地域公共交通計画（県・市町村共同、次期計画R8.3.27策定））も対象。環境：環境基本計画は検索で見当たらず。 | S33: 調査済 | T33: 掲載／期間満了
A34: 31 | B34: 白鷹町 | C34: =IF(OR(D34="◎",E34="◎"),"◎ 営業",IF(OR(D34="△",E34="△"),"△ 着手済・要確認",IF(OR(D34="？",E34="？"),"？ 期間要確認","✕ 対象外"))) | D34: =IF(J34="計画なし","－",IF(J34="策定済","✕",IF(H34="","？",IF(AND(H34>=TGT_MIN,H34<=TGT_MAX),IF(J34="着手済","△","◎"),"✕")))) | E34: =IF(P34="計画なし","－",IF(P34="策定済","✕",IF(N34="","？",IF(AND(N34>=TGT_MIN,N34<=TGT_MAX),IF(P34="着手済","△","◎"),"✕")))) | F34: 山形県地域公共交通計画（県・市町村共同、次期計画R8.3.27策定） | G34: R8〜不明 | I34: 推定 | J34: 策定済 | K34: https://www.pref.yamagata.jp/020057/kurashi/kendo/kotsuseisaku/ykotsu_kasseikakyougikai.html | M34: 不明 | O34: 不明 | P34: 計画なし | R34: 交通：町単独計画は見当たらず。山形県地域公共交通計画（前計画R3〜R7）は市町村の利便増進実施計画等を内包する県全域計画。次期計画はR8.2パブコメ（https://www200.pref.yamagata.jp/020057/keikakupabukomepress2.html ）を経てR8.3.27策定（期間は未確認、R8開始）。 環境：環境基本計画は検索で見当たらず。 【追加調査 2026-10】国交省一覧の広域計画『フラワー長井線沿線』は、長井市・南陽市・川西町・白鷹町が平成28年2月に作成した『フラワー長井線沿線地域公共交通網形成計画』（H28.4〜R3.3＝H28〜R2、期間満了）と判断（本文PDF：https://www.town.kawanishi.yamagata.jp/machinojoho/seisaku/2017-1017-1735.pdf ）。後継の沿線広域交通計画は検索で確認できず。鉄道部分は鉄道事業再構築実施計画（R6.4.1〜R16.3.31、https://www.mlit.go.jp/report/press/tetsudo05_hh_000146.html ）が継続。町単独の地域公共交通計画は確認できず、白鷹町地域公共交通会議は山形県地域公共交通計画の町部分（デマンドタクシー全町線等、https://www.pref.yamagata.jp/documents/34797/20230628_6-10_31.pdf ）を協議。現行データ（県計画）を維持。2026-10-02検索。 根拠: フラワー長井線沿線地域公共交通網形成計画（平成28年2月、長井市・南陽市・川西町・白鷹町）／計画期間 平成28年4月〜平成33年3月 | S34: 調査済 | T34: 掲載（広域：フラワー長井線沿線）／期間満了
A35: 32 | B35: 飯豊町 | C35: =IF(OR(D35="◎",E35="◎"),"◎ 営業",IF(OR(D35="△",E35="△"),"△ 着手済・要確認",IF(OR(D35="？",E35="？"),"？ 期間要確認","✕ 対象外"))) | D35: =IF(J35="計画なし","－",IF(J35="策定済","✕",IF(H35="","？",IF(AND(H35>=TGT_MIN,H35<=TGT_MAX),IF(J35="着手済","△","◎"),"✕")))) | E35: =IF(P35="計画なし","－",IF(P35="策定済","✕",IF(N35="","？",IF(AND(N35>=TGT_MIN,N35<=TGT_MAX),IF(P35="着手済","△","◎"),"✕")))) | F35: 山形県地域公共交通計画（県・市町村共同、次期計画R8.3.27策定） | G35: R8〜不明 | I35: 推定 | J35: 策定済 | K35: https://www.pref.yamagata.jp/020057/kurashi/kendo/kotsuseisaku/ykotsu_kasseikakyougikai.html | M35: 不明 | O35: 不明 | P35: 計画なし | R35: 交通：町単独計画は見当たらず（活性化再生法6条に基づく地域公共交通会議あり、R8.2デマンド交通『ほほえみカー』変更協議 https://www.town.iide.yamagata.jp/005/detr_mtng_r6.html ）。山形県地域公共交通計画（前計画R3〜R7）は市町村の利便増進実施計画等を内包する県全域計画。次期計画はR8.2パブコメ（https://www200.pref.yamagata.jp/020057/keikakupabukomepress2.html ）を経てR8.3.27策定（期間は未確認、R8開始）。 環境：環境基本計画は検索で見当たらず。 | S35: 調査済 | T35: 未掲載【当方は計画あり】
A36: 33 | B36: 三川町 | C36: =IF(OR(D36="◎",E36="◎"),"◎ 営業",IF(OR(D36="△",E36="△"),"△ 着手済・要確認",IF(OR(D36="？",E36="？"),"？ 期間要確認","✕ 対象外"))) | D36: =IF(J36="計画なし","－",IF(J36="策定済","✕",IF(H36="","？",IF(AND(H36>=TGT_MIN,H36<=TGT_MAX),IF(J36="着手済","△","◎"),"✕")))) | E36: =IF(P36="計画なし","－",IF(P36="策定済","✕",IF(N36="","？",IF(AND(N36>=TGT_MIN,N36<=TGT_MAX),IF(P36="着手済","△","◎"),"✕")))) | F36: 山形県地域公共交通計画（県・市町村共同、次期計画R8.3.27策定） | G36: R8〜不明 | I36: 推定 | J36: 策定済 | K36: https://www.pref.yamagata.jp/020057/kurashi/kendo/kotsuseisaku/ykotsu_kasseikakyougikai.html | M36: 不明 | O36: 不明 | P36: 計画なし | R36: 交通：町単独計画は見当たらず。県協議会でR8.3に地域旅客運送サービス継続実施計画（鶴岡三川線・三川酒田線）策定。山形県地域公共交通計画（前計画R3〜R7）は市町村の利便増進実施計画等を内包する県全域計画。次期計画はR8.2パブコメ（https://www200.pref.yamagata.jp/020057/keikakupabukomepress2.html ）を経てR8.3.27策定（期間は未確認、R8開始）。 環境：環境基本計画は検索で見当たらず。 | S36: 調査済 | T36: 未掲載【当方は計画あり】
A37: 34 | B37: 庄内町 | C37: =IF(OR(D37="◎",E37="◎"),"◎ 営業",IF(OR(D37="△",E37="△"),"△ 着手済・要確認",IF(OR(D37="？",E37="？"),"？ 期間要確認","✕ 対象外"))) | D37: =IF(J37="計画なし","－",IF(J37="策定済","✕",IF(H37="","？",IF(AND(H37>=TGT_MIN,H37<=TGT_MAX),IF(J37="着手済","△","◎"),"✕")))) | E37: =IF(P37="計画なし","－",IF(P37="策定済","✕",IF(N37="","？",IF(AND(N37>=TGT_MIN,N37<=TGT_MAX),IF(P37="着手済","△","◎"),"✕")))) | F37: 庄内町地域公共交通計画 | G37: R8〜不明 | I37: 推定 | J37: 策定済 | K37: https://www.town.shonai.lg.jp/kurashi/koutsu/chiikikoukyou/tiikikoukyokotsukaigi.html | L37: 第3次庄内町環境基本計画 | M37: R8〜不明 | O37: 推定 | P37: 策定済 | Q37: https://www.town.shonai.lg.jp/gyousei/shisaku/seisaku/index.html | R37: 交通：町単独の地域公共交通計画は検索で確認できず。山形県地域公共交通計画（前計画R3〜R7）は市町村の利便増進実施計画等を内包する県全域計画。次期計画はR8.2パブコメ（https://www200.pref.yamagata.jp/020057/keikakupabukomepress2.html ）を経てR8.3.27策定（期間は未確認、R8開始）。 環境：第2次（H29.3策定）の後継として第3次案のパブコメを経てR8.3策定とみられる（期間未確認）。計画一覧 https://www.town.shonai.lg.jp/gyousei/shisaku/index.files/R6_keikaku.pdf 。 【追加調査 2026-10】町単独の『庄内町地域公共交通計画』をR8.3策定（基本方針「住み続けたいまちの基盤となる交通体系の構築」）。計画（案）のパブコメ R8.2.2〜R8.2.24（https://www.town.shonai.lg.jp/gyousei/public/iken/koutuukeikaku.html ）。計画に基づき既存循環線4路線・デマンド2路線を区域運行型デマンドタクシー「しょうないデマンド」へ転換、AI予約配車システム導入委託をプロポで実施（https://www.town.shonai.lg.jp/kurashi/koutsu/choueibasu/demandtaxi_reservation_system.html ）。計画期間の終期は検索結果本文で確認できず（R8開始、5年ならR8〜R12）。町サイトはWebFetchブロック。2026-10-02検索。 根拠: 令和8年度からの「庄内町地域公共交通計画（案）」…令和8年2月2日から令和8年2月24日までパブリックコメント募集 | S37: 調査済 | T37: 掲載
A38: 35 | B38: 遊佐町 | C38: =IF(OR(D38="◎",E38="◎"),"◎ 営業",IF(OR(D38="△",E38="△"),"△ 着手済・要確認",IF(OR(D38="？",E38="？"),"？ 期間要確認","✕ 対象外"))) | D38: =IF(J38="計画なし","－",IF(J38="策定済","✕",IF(H38="","？",IF(AND(H38>=TGT_MIN,H38<=TGT_MAX),IF(J38="着手済","△","◎"),"✕")))) | E38: =IF(P38="計画なし","－",IF(P38="策定済","✕",IF(N38="","？",IF(AND(N38>=TGT_MIN,N38<=TGT_MAX),IF(P38="着手済","△","◎"),"✕")))) | F38: 山形県地域公共交通計画（県・市町村共同、次期計画R8.3.27策定） | G38: R8〜不明 | I38: 推定 | J38: 策定済 | K38: https://www.pref.yamagata.jp/020057/kurashi/kendo/kotsuseisaku/ykotsu_kasseikakyougikai.html | L38: 第3次遊佐町環境基本計画 | M38: R4〜R13 | N38: 13 | O38: 推定 | P38: 未確認 | Q38: https://www.town.yuza.yamagata.jp/genre/living/environment | R38: 交通：町単独計画は見当たらず。山形県地域公共交通計画（前計画R3〜R7）は市町村の利便増進実施計画等を内包する県全域計画。次期計画はR8.2パブコメ（https://www200.pref.yamagata.jp/020057/keikakupabukomepress2.html ）を経てR8.3.27策定（期間は未確認、R8開始）。 環境：第3次遊佐町環境基本計画の存在を確認（期間未確認）。R8.1策定の第9次振興計画で環境基本計画に言及。 【追加調査 2026-10】環境：町ドメイン検索の要約で第3次遊佐町環境基本計画の計画期間は令和4（2022）〜令和13（2031）年度。裏付け検索1回では再現せず、計画PDFのURLも未特定のため推定。 根拠: 第３次遊佐町環境基本計画 計画期間 令和4年度〜令和13年度（検索要約） | S38: 調査済 | T38: 未掲載【当方は計画あり】

Sheet 福島県
A1: 福島県 地域公共交通計画・環境基本計画の終期一覧（2026年9月30日時点の調査）
A2: ="営業判定の対象：終期 R"&TGT_MIN&"〜R"&TGT_MAX&"年度 →◎（着手済は△、期間不明は？）。終期セルの色：緑＝対象年度／橙＝その翌年度（次の候補）。対象年度は「集計・設定」シートのC4・C5のプルダウンで切替。"
A3: No | B3: 市町村 | C3: 営業判定 | D3: 交通判定 | E3: 環境判定 | F3: 地域公共交通計画 | G3: 交通 計画期間 | H3: 交通 終期(令和年度) | I3: 交通 確度 | J3: 交通 改定状況 | K3: 交通 計画リンク（エビデンス） | L3: 環境基本計画 | M3: 環境 計画期間 | N3: 環境 終期(令和年度) | O3: 環境 確度 | P3: 環境 改定状況 | Q3: 環境 計画リンク（エビデンス） | R3: 注釈（改定作業の状況など） | S3: 調査状況 | T3: 国交省一覧(R8.5末)
A4: 1 | B4: 福島市 | C4: =IF(OR(D4="◎",E4="◎"),"◎ 営業",IF(OR(D4="△",E4="△"),"△ 着手済・要確認",IF(OR(D4="？",E4="？"),"？ 期間要確認","✕ 対象外"))) | D4: =IF(J4="計画なし","－",IF(J4="策定済","✕",IF(H4="","？",IF(AND(H4>=TGT_MIN,H4<=TGT_MAX),IF(J4="着手済","△","◎"),"✕")))) | E4: =IF(P4="計画なし","－",IF(P4="策定済","✕",IF(N4="","？",IF(AND(N4>=TGT_MIN,N4<=TGT_MAX),IF(P4="着手済","△","◎"),"✕")))) | F4: 福島市地域公共交通計画 | G4: R5〜R12（県計画に準拠） | H4: 12 | I4: 確認済 | J4: 未確認 | K4: https://www.city.fukushima.fukushima.jp/material/files/group/62/40koutuukeikaku-honnpenn1.pdf | L4: 福島市環境基本計画（第3次） | M4: R3〜R7 | N4: 7 | O4: 確認済 | P4: 着手済 | Q4: https://www.city.fukushima.fukushima.jp/material/files/group/36/02_r6_kannkyoukihonnkeikaku.pdf | R4: 交通：R5.3策定、最終年度2027(R9)。R7.2.26に計画改定資料あり（一部改定）https://www.city.fukushima.fukushima.jp/material/files/group/62/20250226koutuukeikakukaitei1-3.pdf 。R7.10.3協議会で県北圏域地域公共交通利便増進実施計画の変更協議。R9終期のため次期計画策定はR8〜R9に着手見込み。環境：R7(2025)終期、2026年度からの第4次計画策定を環境審議会で審議開始（R7.6.23報道資料 https://www.city.fukushima.fukushima.jp/material/files/group/3/press2025-06-23-3.pdf）。第4次の策定完了は未確認。 【ファクトチェック 2026-10-01: 誤り】確認期間: R5〜R12（2023〜2030年度、8年間）／次期: 該当なし（終期R12のため次期計画は当面なし）／根拠: https://www.city.fukushima.fukushima.jp/material/files/group/62/40koutuukeikaku-honnpenn1.pdf | S4: 調査済 | T4: 掲載（広域：福島県避難地域・阿武隈急行線地域）
A5: 2 | B5: 会津若松市 | C5: =IF(OR(D5="◎",E5="◎"),"◎ 営業",IF(OR(D5="△",E5="△"),"△ 着手済・要確認",IF(OR(D5="？",E5="？"),"？ 期間要確認","✕ 対象外"))) | D5: =IF(J5="計画なし","－",IF(J5="策定済","✕",IF(H5="","？",IF(AND(H5>=TGT_MIN,H5<=TGT_MAX),IF(J5="着手済","△","◎"),"✕")))) | E5: =IF(P5="計画なし","－",IF(P5="策定済","✕",IF(N5="","？",IF(AND(N5>=TGT_MIN,N5<=TGT_MAX),IF(P5="着手済","△","◎"),"✕")))) | F5: 会津圏域地域公共交通計画（会津若松市・喜多方市ほか6市町村共同） | G5: R8〜R13 | H5: 13 | I5: 確認済 | J5: 策定済 | K5: https://www.pref.fukushima.lg.jp/sec/16005d/aizukenikimoukeikaku.html | L5: 会津若松市第3期環境基本計画 | M5: R6〜R12 | N5: 12 | O5: 確認済 | P5: 未確認 | Q5: https://www.city.aizuwakamatsu.fukushima.jp/docs/2024050800012/ | R5: 交通：前計画（会津圏域地域公共交通網形成計画/再編実施計画 R2〜R7）の後継として新計画を策定、パブコメR7.12.15〜R8.1.5。環境：R6.3策定。 | S5: 調査済 | T5: 掲載（広域：会津圏域）
A6: 3 | B6: 郡山市 | C6: =IF(OR(D6="◎",E6="◎"),"◎ 営業",IF(OR(D6="△",E6="△"),"△ 着手済・要確認",IF(OR(D6="？",E6="？"),"？ 期間要確認","✕ 対象外"))) | D6: =IF(J6="計画なし","－",IF(J6="策定済","✕",IF(H6="","？",IF(AND(H6>=TGT_MIN,H6<=TGT_MAX),IF(J6="着手済","△","◎"),"✕")))) | E6: =IF(P6="計画なし","－",IF(P6="策定済","✕",IF(N6="","？",IF(AND(N6>=TGT_MIN,N6<=TGT_MAX),IF(P6="着手済","△","◎"),"✕")))) | F6: 郡山市総合交通計画マスタープラン（地域公共交通計画を包含） | G6: R5〜R12 | H6: 12 | I6: 確認済 | J6: 未確認 | K6: https://www.city.koriyama.lg.jp/soshiki/125/68026.html | L6: 郡山市第五次環境基本計画 | M6: R8〜R11 | N6: 11 | O6: 確認済 | P6: 着手済 | Q6: https://www.city.koriyama.lg.jp/uploaded/attachment/109925.pdf | R6: 交通：活性化再生法第5条の地域公共交通計画・バリアフリー方針を統合した総合計画。環境：第四次R4〜R7満了、第五次（R8〜R11）案のパブコメR8.2.17〜3.18実施、策定完了は未確認（R8.3策定の可能性大）。e_urlは第五次関連の検索上位PDF。旧e_url（第四次掲載の年次報告書）https://www.city.koriyama.lg.jp/uploaded/attachment/76651.pdf | S6: 調査済 | T6: 掲載
A7: 4 | B7: いわき市 | C7: =IF(OR(D7="◎",E7="◎"),"◎ 営業",IF(OR(D7="△",E7="△"),"△ 着手済・要確認",IF(OR(D7="？",E7="？"),"？ 期間要確認","✕ 対象外"))) | D7: =IF(J7="計画なし","－",IF(J7="策定済","✕",IF(H7="","？",IF(AND(H7>=TGT_MIN,H7<=TGT_MAX),IF(J7="着手済","△","◎"),"✕")))) | E7: =IF(P7="計画なし","－",IF(P7="策定済","✕",IF(N7="","？",IF(AND(N7>=TGT_MIN,N7<=TGT_MAX),IF(P7="着手済","△","◎"),"✕")))) | F7: いわき市地域公共交通計画 | G7: R5〜R9 | H7: 9 | I7: 確認済 | J7: 未確認 | K7: https://www.city.iwaki.lg.jp/www/contents/1679296597893/simple/koukyoukoutuukeikaku1.pdf | L7: いわき市環境基本計画（第三次）（中間改定版） | M7: R3〜R12 | N7: 12 | O7: 確認済 | P7: 策定済 | Q7: https://www.city.iwaki.lg.jp/www/contents/1774836268840/simple/gaiyo.pdf | R7: 交通：R5.3策定、計画期間「概ね5年間」（R9終期は推定）。R7.1.20第15回いわき都市圏総合都市交通推進協議会で計画改定を協議（一部改定）。次期計画策定の着手は検索で確認できず（R9終期のため要注視）。概要版 https://www.city.iwaki.lg.jp/www/contents/1679296597893/simple/gaiyouban.pdf 。環境：第三次R3〜R12（R3.3策定）、R6〜R7で中間の一部改定を実施、改定版の期間R8〜R12（概要gaiyo.pdf）。 【ファクトチェック 2026-10-01: 正しい】確認期間: R5〜R9（令和5年3月〜令和10年3月、概ね5年間）／次期: 確認できず（次期計画策定業務・協議会での審議情報は見当たらず）／根拠: https://www.city.iwaki.lg.jp/www/contents/1679296597893/index.html | S7: 調査済 | T7: 掲載（広域：福島県避難地域）
A8: 5 | B8: 白河市 | C8: =IF(OR(D8="◎",E8="◎"),"◎ 営業",IF(OR(D8="△",E8="△"),"△ 着手済・要確認",IF(OR(D8="？",E8="？"),"？ 期間要確認","✕ 対象外"))) | D8: =IF(J8="計画なし","－",IF(J8="策定済","✕",IF(H8="","？",IF(AND(H8>=TGT_MIN,H8<=TGT_MAX),IF(J8="着手済","△","◎"),"✕")))) | E8: =IF(P8="計画なし","－",IF(P8="策定済","✕",IF(N8="","？",IF(AND(N8>=TGT_MIN,N8<=TGT_MAX),IF(P8="着手済","△","◎"),"✕")))) | F8: 白河市地域公共交通計画 | G8: R6〜R10 | H8: 10 | I8: 確認済 | J8: 未確認 | K8: https://www.city.shirakawa.fukushima.jp/data/doc/1712536078_doc_45_0.pdf | L8: 第3次白河市環境基本計画 | M8: R3〜R12 | N8: 12 | O8: 確認済 | P8: 未確認 | Q8: https://www.city.shirakawa.fukushima.jp/data/doc/1634185398_doc_49_0.pdf | R8: 交通：R6.3策定、R6〜R10の5年間。環境：第3次2021〜2030年度（第2次はH28策定）。e_urlは検索上位のPDF（計画本体か要確認）。次期計画作業は確認できず。 | S8: 調査済 | T8: 掲載
A9: 6 | B9: 須賀川市 | C9: =IF(OR(D9="◎",E9="◎"),"◎ 営業",IF(OR(D9="△",E9="△"),"△ 着手済・要確認",IF(OR(D9="？",E9="？"),"？ 期間要確認","✕ 対象外"))) | D9: =IF(J9="計画なし","－",IF(J9="策定済","✕",IF(H9="","？",IF(AND(H9>=TGT_MIN,H9<=TGT_MAX),IF(J9="着手済","△","◎"),"✕")))) | E9: =IF(P9="計画なし","－",IF(P9="策定済","✕",IF(N9="","？",IF(AND(N9>=TGT_MIN,N9<=TGT_MAX),IF(P9="着手済","△","◎"),"✕")))) | F9: 須賀川市地域公共交通計画 | G9: 不明 | I9: 不明 | J9: 未確認 | K9: https://www.city.sukagawa.fukushima.jp/kurashi/koutsu/koutsu_keikaku/1015962.html | L9: 第3次須賀川市環境基本計画（中間改定版） | M9: H30〜R9 | N9: 9 | O9: 推定 | P9: 未確認 | Q9: https://www.city.sukagawa.fukushima.jp/kurashi/gomi_recycle/kankyo_hozen/1002334/index.html | R9: 交通：計画ページあり、R7.1.29一部改定。計画期間は検索で確認できず。環境：第3次計画（中間改定版）を公表（計画・条例ページ）、期間は検索で確認できず。区域施策編はR4〜R12。参考：須賀川市の環境（R7.5）https://www.city.sukagawa.fukushima.jp/material/files/group/47/r05shinokankyo.pdf 【追加調査 2026-10】市サイト内検索の要約で第3次計画はH30(2018)〜R9(2027)、R4.3中間見直し（出典は『須賀川市の環境』R7.5 https://www.city.sukagawa.fukushima.jp/material/files/group/47/r05shinokankyo.pdf と思われるが本文未確認）。R9終期だが次期（第4次）計画の策定業務・審議会等は市サイト検索で見当たらず。 根拠: Third Environmental Basic Plan covers the period from fiscal year 2018 (Heisei 30) to fiscal year 2027 (Reiwa 9)（検索要約） | S9: 調査済 | T9: 掲載
A10: 7 | B10: 喜多方市 | C10: =IF(OR(D10="◎",E10="◎"),"◎ 営業",IF(OR(D10="△",E10="△"),"△ 着手済・要確認",IF(OR(D10="？",E10="？"),"？ 期間要確認","✕ 対象外"))) | D10: =IF(J10="計画なし","－",IF(J10="策定済","✕",IF(H10="","？",IF(AND(H10>=TGT_MIN,H10<=TGT_MAX),IF(J10="着手済","△","◎"),"✕")))) | E10: =IF(P10="計画なし","－",IF(P10="策定済","✕",IF(N10="","？",IF(AND(N10>=TGT_MIN,N10<=TGT_MAX),IF(P10="着手済","△","◎"),"✕")))) | F10: 会津圏域地域公共交通計画（会津若松市・喜多方市ほか共同） | G10: R8〜R13 | H10: 13 | I10: 確認済 | J10: 策定済 | K10: https://www.pref.fukushima.lg.jp/sec/16005d/aizukenikimoukeikaku.html | L10: 喜多方市環境基本計画（R4.3中間見直し） | M10: H28〜R8 | N10: 8 | O10: 推定 | P10: 未確認 | Q10: https://www.city.kitakata.fukushima.jp/life/4/25/125/ | R10: 交通：会津圏域6市町村共同計画、パブコメR7.12.15〜R8.1.5、R8〜R13。環境：環境基本計画ありR4.3.29中間見直し（地球温暖化対策総合ビジョン2023-2050を個別方針に位置付け https://www.city.kitakata.fukushima.jp/soshiki/kankyo/49610.html ）、計画期間は検索で確認できず（中間見直しR4から逆算するとR8前後終期の可能性、要確認）。 【追加調査 2026-10】市サイト内検索の要約2件でH28(2016)〜R8(2026)、R4.3中間見直し（パブコメ結果R4.3.2公表）。本文未確認のため推定（e_urlは市の計画一覧ページ）。R8終期だが次期計画の策定業務・審議会・パブコメ等は市サイト検索（R7〜R8）で見当たらず＝未確認。 根拠: planning period spanning fiscal year 2016 (平成28年度) through fiscal year 2026 (令和8年度)（検索要約） | S10: 調査済 | T10: 掲載（広域：会津圏域）
A11: 8 | B11: 相馬市 | C11: =IF(OR(D11="◎",E11="◎"),"◎ 営業",IF(OR(D11="△",E11="△"),"△ 着手済・要確認",IF(OR(D11="？",E11="？"),"？ 期間要確認","✕ 対象外"))) | D11: =IF(J11="計画なし","－",IF(J11="策定済","✕",IF(H11="","？",IF(AND(H11>=TGT_MIN,H11<=TGT_MAX),IF(J11="着手済","△","◎"),"✕")))) | E11: =IF(P11="計画なし","－",IF(P11="策定済","✕",IF(N11="","？",IF(AND(N11>=TGT_MIN,N11<=TGT_MAX),IF(P11="着手済","△","◎"),"✕")))) | G11: 不明 | I11: 不明 | J11: 未確認 | L11: 第2次相馬市環境基本計画 | M11: H30〜R9 | N11: 9 | O11: 推定 | P11: 未確認 | Q11: https://www.city.soma.fukushima.jp/shinososhiki/seikatsukankyoka/keikaku_shisaku/1622.html | R11: 交通・環境とも検索で確認できず（市サイト内検索でも該当ページ出ず、南相馬市の結果に埋もれる）。公共交通情報 https://www.city.soma.fukushima.jp/shinososhiki/kikakuseisakuka/seikatsu/1/1679.html 。参考：福島県地域公共交通計画（R6.3策定）https://www.pref.fukushima.lg.jp/uploaded/attachment/622613.pdf 【追加調査 2026-10】市HP「環境・廃棄物」計画ページ（1622.html）に相馬市環境基本条例に基づく相馬市環境基本計画を掲載。検索要約で第2次計画はH30.3策定・10年間（H30〜R9）、策定5年経過で見直し実施。R9終期だが第3次計画の策定作業は市サイト検索で見当たらず（R8.8に長期総合計画の審議会・市民アンケートは開始）。 根拠: 第2次相馬市環境基本計画は平成30年3月に策定され、10年間を計画期間（検索要約） | S11: 環境のみ調査 | T11: 未掲載
A12: 9 | B12: 二本松市 | C12: =IF(OR(D12="◎",E12="◎"),"◎ 営業",IF(OR(D12="△",E12="△"),"△ 着手済・要確認",IF(OR(D12="？",E12="？"),"？ 期間要確認","✕ 対象外"))) | D12: =IF(J12="計画なし","－",IF(J12="策定済","✕",IF(H12="","？",IF(AND(H12>=TGT_MIN,H12<=TGT_MAX),IF(J12="着手済","△","◎"),"✕")))) | E12: =IF(P12="計画なし","－",IF(P12="策定済","✕",IF(N12="","？",IF(AND(N12>=TGT_MIN,N12<=TGT_MAX),IF(P12="着手済","△","◎"),"✕")))) | F12: 二本松市地域公共交通計画 | G12: R6〜不明 | I12: 不明 | J12: 未確認 | K12: https://www.city.nihonmatsu.lg.jp/kurashi_tetsuduki/koutsu/page011927.html | L12: 第2次二本松市環境基本計画（改定版） | M12: R1〜R10 | N12: 10 | O12: 確認済 | P12: 未確認 | Q12: https://www.city.nihonmatsu.lg.jp/data/doc/1716164612_doc_33_0.pdf | R12: 交通：R6.3策定（網形成計画R1〜R5の後継）、終期は検索で確認できず（5年ならR10）。環境：第2次2019〜2028年度、R6.5改定（区域施策編を包含）。次期計画作業は確認できず。 | S12: 調査済 | T12: 掲載
A13: 10 | B13: 田村市 | C13: =IF(OR(D13="◎",E13="◎"),"◎ 営業",IF(OR(D13="△",E13="△"),"△ 着手済・要確認",IF(OR(D13="？",E13="？"),"？ 期間要確認","✕ 対象外"))) | D13: =IF(J13="計画なし","－",IF(J13="策定済","✕",IF(H13="","？",IF(AND(H13>=TGT_MIN,H13<=TGT_MAX),IF(J13="着手済","△","◎"),"✕")))) | E13: =IF(P13="計画なし","－",IF(P13="策定済","✕",IF(N13="","？",IF(AND(N13>=TGT_MIN,N13<=TGT_MAX),IF(P13="着手済","△","◎"),"✕")))) | F13: 田村市地域公共交通計画 | G13: R4〜R8 | H13: 8 | I13: 確認済 | J13: 着手済 | K13: https://www.city.tamura.lg.jp/soshiki/1/assets/【set】田村市地域公共交通計画概要版2406改訂.pdf | M13: 不明 | O13: 不明 | P13: 計画なし | R13: 交通：R4〜R8、R6.6一部改訂。R8.3協議会で「第2次田村市地域公共交通計画策定業務」の審査委員会設置を協議→次期計画策定着手（資料 https://www.city.tamura.lg.jp/soshiki/1/assets/%E8%B3%87%E6%96%99%E4%B8%80%E5%BC%8F%EF%BC%88R7%E7%AC%AC1%E5%9B%9E%EF%BC%89.pdf ほか）。環境：環境基本計画は検索で確認できず（一般廃棄物処理計画等のみヒット）。 【追加調査 2026-10】市サイト内検索で環境基本計画は見当たらず、環境分野は第4期田村市地球温暖化対策実行計画【区域施策編・事務事業編】(R4〜R12, https://www.city.tamura.lg.jp/soshiki/8/entry_5.html)・地域新エネルギービジョン・一般廃棄物処理基本計画のみ。第2次総合計画が上位計画。根拠は検索ベースで中程度。 根拠: 第４期田村市地球温暖化対策実行計画【区域施策編・事務事業編】 | S13: 調査済 | T13: 掲載（広域：福島県避難地域）
A14: 11 | B14: 南相馬市 | C14: =IF(OR(D14="◎",E14="◎"),"◎ 営業",IF(OR(D14="△",E14="△"),"△ 着手済・要確認",IF(OR(D14="？",E14="？"),"？ 期間要確認","✕ 対象外"))) | D14: =IF(J14="計画なし","－",IF(J14="策定済","✕",IF(H14="","？",IF(AND(H14>=TGT_MIN,H14<=TGT_MAX),IF(J14="着手済","△","◎"),"✕")))) | E14: =IF(P14="計画なし","－",IF(P14="策定済","✕",IF(N14="","？",IF(AND(N14>=TGT_MIN,N14<=TGT_MAX),IF(P14="着手済","△","◎"),"✕")))) | F14: 南相馬市地域公共交通計画 | G14: R8〜R12 | H14: 12 | I14: 確認済 | J14: 策定済 | K14: https://www.city.minamisoma.lg.jp/material/files/group/3/202601281245.pdf | L14: 第三次南相馬市環境基本計画 | M14: R5〜R12（推定） | N14: 12 | O14: 推定 | P14: 未確認 | Q14: https://www.city.minamisoma.lg.jp/material/files/group/3/20231024_co148.pdf | R14: 交通：新計画R8〜R12（R8.1資料）。旧計画概要 https://www.city.minamisoma.lg.jp/material/files/group/13/koutuukeikakugaiyou.pdf 。環境：第三次計画R5.10策定（第二次はH36=R6まで）、期間は検索で確認できず（R6開始と推定）。ゼロカーボン推進計画2023〜2030。 【追加調査 2026-10】市サイト内検索の要約で第三次計画は2023〜2030年度（8年間）・4年後中間評価とされる（R5.10策定、第三次総合計画R5〜R12と整合）。ただし別の要約ではR6〜R13とも出ており本文未確認のため推定。終期R12で次期作業は対象外。 根拠: The plan period spans from fiscal year 2023 to fiscal year 2030 (8 years)（検索要約） | S14: 調査済 | T14: 掲載（広域：福島県避難地域）／期間満了
A15: 12 | B15: 伊達市 | C15: =IF(OR(D15="◎",E15="◎"),"◎ 営業",IF(OR(D15="△",E15="△"),"△ 着手済・要確認",IF(OR(D15="？",E15="？"),"？ 期間要確認","✕ 対象外"))) | D15: =IF(J15="計画なし","－",IF(J15="策定済","✕",IF(H15="","？",IF(AND(H15>=TGT_MIN,H15<=TGT_MAX),IF(J15="着手済","△","◎"),"✕")))) | E15: =IF(P15="計画なし","－",IF(P15="策定済","✕",IF(N15="","？",IF(AND(N15>=TGT_MIN,N15<=TGT_MAX),IF(P15="着手済","△","◎"),"✕")))) | F15: 伊達市地域公共交通計画 | G15: 不明 | I15: 不明 | J15: 未確認 | K15: https://www.city.fukushima-date.lg.jp/soshiki/86/47231.html | L15: 第2次伊達市環境基本計画 | M15: R3〜R12 | N15: 12 | O15: 確認済 | P15: 策定済 | Q15: https://www.city.fukushima-date.lg.jp/soshiki/86/47604.html | R15: 交通：R2年度策定（網形成計画H27.8〜R2の後継）、期間は検索で確認できず。利便増進実施計画 https://www.city.fukushima-date.lg.jp/soshiki/86/49036.html 、県北圏域利便増進実施計画R7.10〜R13.3にも参加。環境：R3.3策定、2021〜2030年度、R8.3中間見直し実施（策定済は中間見直し版の意）。 | S15: 調査済 | T15: 掲載（広域：阿武隈急行線地域）
A16: 13 | B16: 本宮市 | C16: =IF(OR(D16="◎",E16="◎"),"◎ 営業",IF(OR(D16="△",E16="△"),"△ 着手済・要確認",IF(OR(D16="？",E16="？"),"？ 期間要確認","✕ 対象外"))) | D16: =IF(J16="計画なし","－",IF(J16="策定済","✕",IF(H16="","？",IF(AND(H16>=TGT_MIN,H16<=TGT_MAX),IF(J16="着手済","△","◎"),"✕")))) | E16: =IF(P16="計画なし","－",IF(P16="策定済","✕",IF(N16="","？",IF(AND(N16>=TGT_MIN,N16<=TGT_MAX),IF(P16="着手済","△","◎"),"✕")))) | F16: 本宮市地域公共交通計画 | G16: 不明（R8度末終了と推定） | H16: 8 | I16: 推定 | J16: 着手済 | K16: https://www.city.motomiya.lg.jp/soshiki/10/tiikikoukyoukoutsuukeikaku.html | L16: 本宮市第2次環境基本計画 | M16: 不明（R1〜R10と推定） | O16: 不明 | P16: 未確認 | R16: 2026-07-06 「本宮市第2期地域公共交通計画策定支援業務委託」公募型プロポーザル実施を市が公表（生活環境課、https://www.city.motomiya.lg.jp/soshiki/10/tiikikoukyoukoutsuukeikaku.html）。現行計画期間は未確認（第2期がR9開始と推定）。環境基本計画は「本宮市第2次環境基本計画」（市HP掲載、2019-05-13更新と検索結果に表示、計画・事業ページ https://www.city.motomiya.lg.jp/life/6/25/ ）だが計画期間は再検索でも確認できず。ゼロカーボンシティ宣言2021年3月（https://www.city.motomiya.lg.jp/soshiki/10/2050zerocarboncity.html）。 【追加調査 2026-10】市サイト内検索の要約で第1次本宮市環境基本計画はH21〜H30の10年間→第2次（2019.5掲載）はR1〜R10の可能性が高いが本文で確認できず。計画・事業ページ https://www.city.motomiya.lg.jp/life/6/25/ 。 根拠: 本宮市環境基本計画の計画期間は平成21年度から平成30年度までの10年間（検索要約、第1次） | S16: 調査済 | T16: 掲載
A17: 14 | B17: 桑折町 | C17: =IF(OR(D17="◎",E17="◎"),"◎ 営業",IF(OR(D17="△",E17="△"),"△ 着手済・要確認",IF(OR(D17="？",E17="？"),"？ 期間要確認","✕ 対象外"))) | D17: =IF(J17="計画なし","－",IF(J17="策定済","✕",IF(H17="","？",IF(AND(H17>=TGT_MIN,H17<=TGT_MAX),IF(J17="着手済","△","◎"),"✕")))) | E17: =IF(P17="計画なし","－",IF(P17="策定済","✕",IF(N17="","？",IF(AND(N17>=TGT_MIN,N17<=TGT_MAX),IF(P17="着手済","△","◎"),"✕")))) | G17: 不明 | I17: 不明 | J17: 未確認 | M17: 不明 | O17: 不明 | P17: 計画なし | R17: 地域公共交通計画は町HP内検索・一般検索とも確認できず（都市計画マスタープランR6年度策定、公共交通は環境係所管）。環境基本計画も見当たらず、代替として地球温暖化対策実行計画 区域施策編（地域まるごと省エネ計画、R6.2改正）・事務事業編（第4期、R4.3策定）あり: https://www.town.koori.fukushima.jp/soshiki/kankyo/1/3/9286.html 。都市計画マスタープランはR6年度策定。環境基本計画の「計画なし」は検索未ヒットに基づく推定。 | S17: 環境のみ調査 | T17: 未掲載
A18: 15 | B18: 国見町 | C18: =IF(OR(D18="◎",E18="◎"),"◎ 営業",IF(OR(D18="△",E18="△"),"△ 着手済・要確認",IF(OR(D18="？",E18="？"),"？ 期間要確認","✕ 対象外"))) | D18: =IF(J18="計画なし","－",IF(J18="策定済","✕",IF(H18="","？",IF(AND(H18>=TGT_MIN,H18<=TGT_MAX),IF(J18="着手済","△","◎"),"✕")))) | E18: =IF(P18="計画なし","－",IF(P18="策定済","✕",IF(N18="","？",IF(AND(N18>=TGT_MIN,N18<=TGT_MAX),IF(P18="着手済","△","◎"),"✕")))) | G18: 不明 | I18: 不明 | J18: 未確認 | M18: 不明 | O18: 不明 | P18: 計画なし | R18: 地域公共交通計画は町HP内検索でも確認できず。「地域公共交通あり方協議会」設置、国見まちなかタクシー・ももたんパス（タクシー助成実証、https://www.town.kunimi.fukushima.jp/soshiki/4/16576.html）等を実施。広報くにみR3.4号特集、町資料「これからの公共交通のカタチ」（https://www.town.kunimi.fukushima.jp/uploaded/attachment/6659.pdf）。環境基本計画は検索で確認できず。代替として地球温暖化対策実行計画をR6.1.9公表（住民防災課所管）。第6次総合計画（KuniMirai2030）あり。 【追加調査 2026-10】町サイト内検索で環境基本計画は見当たらず。環境分野は地球温暖化対策実行計画（R6.1公表）、自然環境等と再エネ発電事業との調和条例（https://www.town.kunimi.fukushima.jp/soshiki/4/18511.html）、第6次総合計画（R3〜R12）のみ。根拠は検索ベース。 | S18: 環境のみ調査 | T18: 未掲載
A19: 16 | B19: 川俣町 | C19: =IF(OR(D19="◎",E19="◎"),"◎ 営業",IF(OR(D19="△",E19="△"),"△ 着手済・要確認",IF(OR(D19="？",E19="？"),"？ 期間要確認","✕ 対象外"))) | D19: =IF(J19="計画なし","－",IF(J19="策定済","✕",IF(H19="","？",IF(AND(H19>=TGT_MIN,H19<=TGT_MAX),IF(J19="着手済","△","◎"),"✕")))) | E19: =IF(P19="計画なし","－",IF(P19="策定済","✕",IF(N19="","？",IF(AND(N19>=TGT_MIN,N19<=TGT_MAX),IF(P19="着手済","△","◎"),"✕")))) | F19: 福島県避難地域広域公共交通計画（県・避難12市町村の広域計画） | G19: R5〜R9 | H19: 9 | I19: 確認済 | J19: 未確認 | K19: https://www.pref.fukushima.lg.jp/sec/16005d/hinankeikaku.html | M19: 不明 | O19: 不明 | P19: 計画なし | R19: 地域公共交通計画は検索で確認できず。川俣町地域公共交通会議（H20.3設置、https://www.town.kawamata.lg.jp/site/kurashi-tetsuzuki/kawamatakoukyokotsu.html）がH21.3に地域公共交通総合連携計画を策定（デマンド型乗合タクシー導入、国交省資料）—旧法計画で現行計画は未確認。環境基本計画も検索で確認できず（各種計画一覧 https://www.town.kawamata.lg.jp/site/chosei-shisetsu/list74.html 要確認）。循環型社会形成推進地域計画（R3〜R7）あり。 【追加調査 2026-10】国交省一覧の広域計画『福島県避難地域』＝福島県避難地域広域公共交通計画（前身はH30.3.28策定の避難地域広域公共交通網形成計画）。対象は田村市・南相馬市・川俣町・広野町・楢葉町・富岡町・川内村・大熊町・双葉町・浪江町・葛尾村・飯舘村の12市町村。計画期間R5.4〜R10.3。次期計画：R8年度に最終評価・次期計画の方向性決定、R9年度に次期計画策定（R10.4開始）予定。R8.6.25福島県地域公共交通活性化協議会で避難地域広域公共交通検討協議会の今年度スケジュールを報告（資料 https://www.pref.fukushima.lg.jp/uploaded/attachment/756354.pdf 、協議会 https://www.pref.fukushima.lg.jp/sec/16005d/chiikikoukyoukasseikakyougikai.html ）。策定委託・パブコメは未確認のため着手済とはせず。町単独計画は確認できず（H21.3旧法連携計画のみ）。2026-10-02検索。 根拠: 避難地域広域公共交通計画は令和5年4月から令和10年3月までの計画期間…令和８年度に最終評価 【追加調査 2026-10】町サイト内検索で環境基本計画は見当たらず、環境分野は「川俣町地域まるごと脱炭素計画（地球温暖化対策実行計画 区域施策編）」（https://www.town.kawamata.lg.jp/site/chosei-shisetsu/chiikimarugotodathutansokeikaku.html）と循環型社会形成推進地域計画のみ。 根拠: 川俣町地域まるごと脱炭素計画～川俣町地球温暖化対策実行計画（区域施策編） | S19: 調査済 | T19: 掲載（広域：福島県避難地域）
A20: 17 | B20: 大玉村 | C20: =IF(OR(D20="◎",E20="◎"),"◎ 営業",IF(OR(D20="△",E20="△"),"△ 着手済・要確認",IF(OR(D20="？",E20="？"),"？ 期間要確認","✕ 対象外"))) | D20: =IF(J20="計画なし","－",IF(J20="策定済","✕",IF(H20="","？",IF(AND(H20>=TGT_MIN,H20<=TGT_MAX),IF(J20="着手済","△","◎"),"✕")))) | E20: =IF(P20="計画なし","－",IF(P20="策定済","✕",IF(N20="","？",IF(AND(N20>=TGT_MIN,N20<=TGT_MAX),IF(P20="着手済","△","◎"),"✕")))) | F20: 大玉村地域公共交通計画 | G20: R4〜R8（推定） | H20: 8 | I20: 推定 | J20: 未確認 | K20: https://www.vill.otama.fukushima.jp/gyousei_jouhou/keikaku/ | M20: 不明 | O20: 不明 | P20: 未確認 | R20: 地域公共交通計画は素案パブコメR4.1.28〜2.25実施（結果 https://www.vill.otama.fukushima.jp/file/contents/527/25641/koukyoukoutuu_kekka.pdf）→R3年度末策定、期間は5年と推定（R8度末終了なら次期計画作業の可能性、ただし検索で確認できず）。デマンド型乗合タクシー（AI配車）・通勤通学バス運行。環境基本計画は検索で確認できず（各種計画一覧に見当たらず、第5次総合振興計画・立地適正化計画R6.8等のみ）。 【追加調査 2026-10】大玉村環境基本条例（https://www.vill.otama.fukushima.jp/reiki_int/reiki_honbun/c522RG00000647.html）で村長に環境基本計画策定を規定しているが、計画本体は村サイト検索・一般検索とも見当たらず（総合振興計画・都市マス等のみ）。条例があるため計画なしとは断定せず未確認のまま。 | S20: 交通のみ調査 | T20: 掲載
A21: 18 | B21: 鏡石町 | C21: =IF(OR(D21="◎",E21="◎"),"◎ 営業",IF(OR(D21="△",E21="△"),"△ 着手済・要確認",IF(OR(D21="？",E21="？"),"？ 期間要確認","✕ 対象外"))) | D21: =IF(J21="計画なし","－",IF(J21="策定済","✕",IF(H21="","？",IF(AND(H21>=TGT_MIN,H21<=TGT_MAX),IF(J21="着手済","△","◎"),"✕")))) | E21: =IF(P21="計画なし","－",IF(P21="策定済","✕",IF(N21="","？",IF(AND(N21>=TGT_MIN,N21<=TGT_MAX),IF(P21="着手済","△","◎"),"✕")))) | G21: 不明 | I21: 不明 | J21: 未確認 | M21: 不明 | O21: 不明 | P21: 計画なし | R21: 地域公共交通計画は町HP内検索でも確認できず（都市計画マスタープラン、鏡石駅周辺将来まちづくりビジョンR7.3のみ）。環境基本計画も検索で確認できず。各種まちづくり計画一覧: https://www.town.kagamiishi.fukushima.jp/kurashi/chousei/008285.html 【追加調査 2026-10】町サイト内検索で環境基本計画は見当たらず、環境分野は第3次鏡石町地球温暖化対策実行計画（区域施策編・事務事業編）（https://www.town.kagamiishi.fukushima.jp/kurashi/kurashi_tetuzuki/kankyo/011647.html）のみ。 根拠: 第３次鏡石町地球温暖化対策実行計画（区域施策編、事務事業編） | S21: 環境のみ調査 | T21: 未掲載
A22: 19 | B22: 天栄村 | C22: =IF(OR(D22="◎",E22="◎"),"◎ 営業",IF(OR(D22="△",E22="△"),"△ 着手済・要確認",IF(OR(D22="？",E22="？"),"？ 期間要確認","✕ 対象外"))) | D22: =IF(J22="計画なし","－",IF(J22="策定済","✕",IF(H22="","？",IF(AND(H22>=TGT_MIN,H22<=TGT_MAX),IF(J22="着手済","△","◎"),"✕")))) | E22: =IF(P22="計画なし","－",IF(P22="策定済","✕",IF(N22="","？",IF(AND(N22>=TGT_MIN,N22<=TGT_MAX),IF(P22="着手済","△","◎"),"✕")))) | G22: 不明 | I22: 不明 | J22: 未確認 | M22: 不明 | O22: 不明 | P22: 計画なし | R22: 地域公共交通計画・環境基本計画とも検索で確認できず（村HPはほぼ検索インデックスなし）。小規模村で計画なしの可能性。 【追加調査 2026-10】村HP計画一覧（https://www.vill.tenei.fukushima.jp/life/4/16/120/）・サイト内検索で環境基本計画は見当たらず、第1次天栄村地球温暖化対策実行計画（区域施策編）・ゼロカーボンシティ宣言（https://www.vill.tenei.fukushima.jp/soshiki/3/zero-co2.html）・第五次総合計画のみ。 | S22: 環境のみ調査 | T22: 未掲載
A23: 20 | B23: 下郷町 | C23: =IF(OR(D23="◎",E23="◎"),"◎ 営業",IF(OR(D23="△",E23="△"),"△ 着手済・要確認",IF(OR(D23="？",E23="？"),"？ 期間要確認","✕ 対象外"))) | D23: =IF(J23="計画なし","－",IF(J23="策定済","✕",IF(H23="","？",IF(AND(H23>=TGT_MIN,H23<=TGT_MAX),IF(J23="着手済","△","◎"),"✕")))) | E23: =IF(P23="計画なし","－",IF(P23="策定済","✕",IF(N23="","？",IF(AND(N23>=TGT_MIN,N23<=TGT_MAX),IF(P23="着手済","△","◎"),"✕")))) | G23: 不明 | I23: 不明 | J23: 未確認 | M23: 不明 | O23: 不明 | P23: 計画なし | R23: 町単独の地域公共交通計画・環境基本計画は検索で確認できず。会津線沿線（会津若松市・下郷町・南会津町）で会津線活性化連携協議会が地域公共交通総合連携計画を策定（旧法）、会津鉄道の鉄道事業再構築実施計画はR7.4〜R17.3。会津地域の広域公共交通計画（2026〜2031、6市町村）の記載が検索要約にあるが対象市町村・名称は要確認。過疎地域持続的発展計画（R3〜R7）あり。 【追加調査 2026-10】町サイト内検索で環境基本計画・温暖化対策実行計画とも見当たらず。総合計画等ページ（https://www.town.shimogo.fukushima.jp/organization/sougouseisaku/kikakuseisaku/1/820.html）は第7次総合計画中心で、環境は総合計画の基本目標「住み続けたいまち（生活環境）」で扱う。根拠は検索ベースで弱め。 | S23: 環境のみ調査 | T23: 未掲載
A24: 21 | B24: 檜枝岐村 | C24: =IF(OR(D24="◎",E24="◎"),"◎ 営業",IF(OR(D24="△",E24="△"),"△ 着手済・要確認",IF(OR(D24="？",E24="？"),"？ 期間要確認","✕ 対象外"))) | D24: =IF(J24="計画なし","－",IF(J24="策定済","✕",IF(H24="","？",IF(AND(H24>=TGT_MIN,H24<=TGT_MAX),IF(J24="着手済","△","◎"),"✕")))) | E24: =IF(P24="計画なし","－",IF(P24="策定済","✕",IF(N24="","？",IF(AND(N24>=TGT_MIN,N24<=TGT_MAX),IF(P24="着手済","△","◎"),"✕")))) | G24: 不明 | I24: 不明 | J24: 未確認 | M24: 不明 | O24: 不明 | P24: 未確認 | R24: 地域公共交通計画・環境基本計画とも検索で確認できず。小規模村で計画なしの可能性（南会津地域4町村の共同交通計画も確認できず）。 【追加調査 2026-10】環境基本計画・地球温暖化対策実行計画とも検索で確認できず（ヒットは循環型社会形成推進地域計画 H29〜R3 https://www.env.go.jp/recycle/waste/3r_network/5_region/project_list/07_fukushima/06_hinoemata_h29.pdf のみ）。人口約500人の小規模村で計画なしの可能性高いが、村HPの計画一覧で否定確認できず未確認のまま。 | S24: 未調査 | T24: 未掲載
A25: 22 | B25: 只見町 | C25: =IF(OR(D25="◎",E25="◎"),"◎ 営業",IF(OR(D25="△",E25="△"),"△ 着手済・要確認",IF(OR(D25="？",E25="？"),"？ 期間要確認","✕ 対象外"))) | D25: =IF(J25="計画なし","－",IF(J25="策定済","✕",IF(H25="","？",IF(AND(H25>=TGT_MIN,H25<=TGT_MAX),IF(J25="着手済","△","◎"),"✕")))) | E25: =IF(P25="計画なし","－",IF(P25="策定済","✕",IF(N25="","？",IF(AND(N25>=TGT_MIN,N25<=TGT_MAX),IF(P25="着手済","△","◎"),"✕")))) | G25: 不明 | I25: 不明 | J25: 未確認 | M25: 不明 | O25: 不明 | P25: 計画なし | R25: 地域公共交通計画は町HP内検索でも確認できず（只見駅周回バス、雪んこタクシー等運行）。環境基本計画も検索で確認できず（ユネスコエコパーク関連の取組はあり）。 【追加調査 2026-10】町HP「環境関連の計画」ページ https://www.town.tadami.lg.jp/lifeguide/cat01/cat5/000082.html に掲載されるのは生活排水処理基本計画・一般廃棄物処理実施計画・地球温暖化対策実行計画等で、環境基本計画は無し（検索結果要約ベース）。環境施策は第七次只見町振興計画・野生動植物を保護する条例(H28.6)・ユネスコエコパークで対応。 根拠: 只見町は生活排水処理基本計画、一般廃棄物処理実施計画、地球温暖化対策実行計画などを策定（『環境関連の計画』ページ） | S25: 環境のみ調査 | T25: 未掲載
A26: 23 | B26: 南会津町 | C26: =IF(OR(D26="◎",E26="◎"),"◎ 営業",IF(OR(D26="△",E26="△"),"△ 着手済・要確認",IF(OR(D26="？",E26="？"),"？ 期間要確認","✕ 対象外"))) | D26: =IF(J26="計画なし","－",IF(J26="策定済","✕",IF(H26="","？",IF(AND(H26>=TGT_MIN,H26<=TGT_MAX),IF(J26="着手済","△","◎"),"✕")))) | E26: =IF(P26="計画なし","－",IF(P26="策定済","✕",IF(N26="","？",IF(AND(N26>=TGT_MIN,N26<=TGT_MAX),IF(P26="着手済","△","◎"),"✕")))) | F26: 南会津町地域公共交通計画 | G26: R6〜R10 | H26: 10 | I26: 確認済 | J26: 未確認 | K26: https://www.town.minamiaizu.lg.jp/official/soshikikarasagasu/sogoseisakuka/kakushukeikaku/1/3114.html | L26: 第2次南会津町環境基本計画 | M26: 不明 | O26: 不明 | P26: 未確認 | Q26: https://www.town.minamiaizu.lg.jp/official/soshikikarasagasu/kankyosuidoka/kakushukeikaku/1/450.html | R26: 交通計画はR6.3策定（R6.6改訂、本編 https://www.town.minamiaizu.lg.jp/material/files/group/3/6gatukaiteibann.pdf ）。会津線沿線3市町の連携計画・会津鉄道再構築（R7.4〜R17.3）にも関係。環境基本条例H19.12、第1次計画H21.3、第2次計画の期間は確認できず。地球温暖化対策実行計画（区域施策編）をR7.3策定（https://www.town.minamiaizu.lg.jp/official/soshikikarasagasu/kankyosuidoka/kakushukeikaku/1/3540.html）、ゼロカーボン宣言済、エスプールとゼロカーボンタウン連携協定。 【追加調査 2026-10】第2次計画の期間は検索で確認できず（町HP 450.htmlの要約：『2009年3月に南会津町環境基本計画を策定…前計画の策定から10年が経過したため第2次を策定』）。H31(2019)頃策定・10年計画ならR1〜R10頃と推測されるが未確認のため不明のまま。町は令和元〜6年度の環境年次報告書を公表。WebFetchは町HPブロック。 根拠: 前計画の策定から10年が経過したため、「第2次南会津町環境基本計画」を策定 | S26: 調査済 | T26: 掲載
